Workbook

Sheet Input sheet
C1: Input cell | E1: Calculated cell
A3: Date of valuation | B3: 01/08/2025 | C3: Important: Before you run this spreadsheet, go into preferences in Excel and check under Calculation options
A4: Company name | B4: Apple | C4: There should be a check against the iteration box. If there is not, you will get circular reasoning errors.
A5: Numbers from your base year below ( in consistent units)
B6: This year | C6: Last year | E6: Updated in January 2024 with updated Industry averages and risk premiums
A7: Country of incorporation | B7: United States
A8: Industry (US) | B8: Electronics (General)
A9: Industry (Global) | B9: Electronics (General)
B10: Most Recent 12 months | C10: Last 10K | D10: Years since last 10K
A11: Revenues | B11: 399294 | C11: 391035 | D11: 0.75
A12: Operating income or EBIT | B12: 126066 | C12: 123216 | D12: 0.75
A13: Interest expense | B13: 0 | C13: 0
A14: Book value of equity | B14: 65830 | C14: 56950
A15: Book value of debt | B15: 101698 | C15: 119059
A16: Do you have R&D expenses to capitalize? | B16: Yes | C16: If you want to capitalize R&D, you have to input the numbers into the R&D worksheet.
A17: Do you have operating lease commitments? | B17: No | C17: If you lease or other contractual commitments that have not been converteed to debt already, say yes to this option and do the conversion.
A18: Cash and Marketable Securities | B18: 132986 | C18: 156650
A19: Cross holdings and other non-operating assets | B19: 55335 | C19: 46906
A20: Minority interests | B20: 0 | C20: 0
A21: Number of shares outstanding = | B21: 15053 | E21: Computed numbers: Here is what your company's numbers look like, relative to industry.
A22: Current stock price = | B22: 229.53999 | E22: If you are not working in US dollars, you should add the inflation differential to the industry averages.
A23: Effective tax rate = | B23: 0.164 | J23: Industry (US) | K23: Industry (Global) | L23: Global Distribution Stats
A24: Marginal tax rate = | B24: 0.25 | I24: Company | J24: Average | K24: Average | L24: 1st Quartile | M24: Median | N24: 3rd Quartile
A25: The value drivers below: | E25: Revenue growth in the most recent year = | I25: =IF(C11>0,(B11/C11)^(1/D11)-1, "NA") | J25: =VLOOKUP(B8,'Industry Averages(US)'!A2:S95,3) | K25: =VLOOKUP(B9,'Industry Average Beta (Global)'!A2:N95,3) | L25: =VLOOKUP($B$9,'Input Stat Distributioons'!$A$3:$R$96,3,FALSE) | M25: =VLOOKUP($B$9,'Input Stat Distributioons'!$A$3:$R$96,4,FALSE) | N25: =VLOOKUP($B$9,'Input Stat Distributioons'!$A$3:$R$96,5,FALSE)
A26: Revenue growth rate for next year | B26: 0.075 | C26: Growth Lever - Next year | E26: Pre-tax operating margin in the most recent year = | I26: ='Valuation output'!B4 | J26: =VLOOKUP(B8,'Industry Averages(US)'!A2:AA95,4) | K26: =VLOOKUP(B9,'Industry Average Beta (Global)'!A2:N95,4) | L26: =VLOOKUP($B$9,'Input Stat Distributioons'!$A$3:$R$96,6,FALSE) | M26: =VLOOKUP($B$9,'Input Stat Distributioons'!$A$3:$R$96,7,FALSE) | N26: =VLOOKUP($B$9,'Input Stat Distributioons'!$A$3:$R$96,8,FALSE)
A27: Operating Margin for next year | B27: 0.3177 | C27: Profitability Lever - Next year | E27: Sales to capital ratio in most recent year = | I27: =B11/'Valuation output'!B39 | J27: =VLOOKUP(B8,'Industry Averages(US)'!A2:S95,14) | K27: =VLOOKUP(B9,'Industry Average Beta (Global)'!A2:N95,14) | L27: =VLOOKUP($B$9,'Input Stat Distributioons'!$A$3:$R$96,9,FALSE) | M27: =VLOOKUP($B$9,'Input Stat Distributioons'!$A$3:$R$96,10,FALSE) | N27: =VLOOKUP($B$9,'Input Stat Distributioons'!$A$3:$R$96,11,FALSE)
A28: Compounded annual revenue growth rate - years 2-5 = | B28: 0.075 | C28: Growth Lever - Long term | E28: Marginal sales to capital ratio = | I28: =IF(('Input sheet'!B11-'Input sheet'!C11)/(('Input sheet'!B14+'Input sheet'!B15-'Input sheet'!B18)-('Input sheet'!C14+'Input sheet'!C15-'Input sheet'!C18))>0,('Input sheet'!B11-'Input sheet'!C11)/(('Input sheet'!B14+'Input sheet'!B15-'Input sheet'!B18)-('Input sheet'!C14+'Input sheet'!C15-'Input sheet'!C18)),"NA")
A29: Target pre-tax operating margin = | B29: 0.36 | C29: Profitability Lever - Long term | E29: Return on invested capital in most recent year= | I29: ='Valuation output'!B7/'Valuation output'!B39 | J29: =VLOOKUP(B8,'Industry Averages(US)'!A2:S95,5) | K29: =VLOOKUP(B9,'Industry Average Beta (Global)'!A2:N95,5)
A30: Year of convergence for margin | B30: 5 | C30: Speed of convergence level | E30: Standard deviation in stock prices = | J30: =VLOOKUP(B8,'Industry Averages(US)'!A2:S95,10) | K30: =VLOOKUP(B8,'Industry Average Beta (Global)'!A2:Z95,10)
A31: Sales to capital ratio (for years 1-5) | B31: 5 | C31: Efficency of Growth Lever (first 5 years) | E31: Cost of capital = | J31: =VLOOKUP(B8,'Industry Averages(US)'!A2:S95,13) | K31: =VLOOKUP(B8,'Industry Average Beta (Global)'!A2:Z95,13) | L31: =VLOOKUP($B$9,'Input Stat Distributioons'!$A$3:$R$96,12,FALSE) | M31: =VLOOKUP($B$9,'Input Stat Distributioons'!$A$3:$R$96,13,FALSE) | N31: =VLOOKUP($B$9,'Input Stat Distributioons'!$A$3:$R$96,14,FALSE)
A32: Sales to capital ratio (for years 6-10) | B32: 5 | C32: Efficency of Growth Lever (years 6-10)
A33: Market numbers | E33: Valuation Output Feedback (for you to use to fine tune your inputs, if you want)
A34: Riskfree rate | B34: 0.0428 | E34: Revenues in year 10, based on your revenue growth = | J34: ='Valuation output'!M3
A35: Initial cost of capital = | B35: ='Cost of capital worksheet'!B13 | C35: Do not input. Go to cost of capital sheet. | E35: Pre-tax Operating Income in year 10, based on your operating margin = | J35: ='Valuation output'!M5
A36: Other inputs | E36: Return on invested capital in year 10, based on your sales/capital ratio = | J36: ='Valuation output'!L40
A37: Do you have employee options outstanding? | B37: No | E37: Check the Diagnostics worksheet for more details.
A38: Number of options outstanding = | B38: 7.72
A39: Average strike price = | B39: 1.29
A40: Average maturity = | B40: 7
A41: Standard deviation on stock price = | B41: 0.45
A43: Default assumptions.
A44: In stable growth, I will assume that your firm will have a cost of capital similar to that of typical mature companies (riskfree rate + 4.5%)
A45: Do you want to override this assumption = | B45: Yes | C45: Mature companies generally see their risk levels approach the average
A46: If yes, enter the cost of capital after year 10 = | B46: 0.08 | C46: Though some sectors, even in stable growth, may have higher risk. If you change your risk free rate after year 10 (see cell B57 & 58), you should incorporate the change into your stable cost of capital estimate.
A47: I will assume that your firm will earn a return on capital equal to its cost of capital after year 10. I am assuming that whatever competitive advantages you have today will fade over time.
A48: Do you want to override this assumption = | B48: Yes | C48: Mature companies find it difficult to generate returns that exceed the cost of capital
A49: If yes, enter the return on capital you expect after year 10 | B49: 0.15 | C49: But there are significant exceptions among companies with long-lasting competitive advantages.
A50: I will assume that your firm has no chance of failure over the foreseeable future.
A51: Do you want to override this assumption = | B51: No | C51: Many young, growth companies fail, especially if they have trouble raising cash. Many distressed companies fail, because they have trouble making debt payments.
A52: If yes, enter the probability of failure = | B52: 0.12 | C52: Tough to estimate but a key input. Use the failure rate worksheet, if necessary.
A53: What do you want to tie your proceeds in failure to? | B53: V | C53: B: Book value of capital, V= Estimated fair value for the company
A54: Enter the distress proceeds as percentage of book or fair value | B54: 0.5 | C54: This can be zero, if the assets will be worth nothing if the firm fails.
A55: I assume that reinvestment in a year translates into growth in the next year, i.e., there is a one year lag between reinvesting and generating growth from that reinvestment.
A56: Do you want override this assumption = | B56: No
A57: If yes, enter a different lag (0 = no lag to 3 = lag of 3 years) | B57: 1
A58: I will assume that your effective tax rate will adjust to your marginal tax rate by your terminal year. If you override this assumption, I will leave the tax rate at your effective tax rate.
A59: Do you want to override this assumption = | B59: No
A60: I will assume that you have no losses carried forward from prior years ( NOL) coming into the valuation. If you have a money losing company, you may want to override tis.
A61: Do you want to override this assumption = | B61: No | C61: Check the financial statements.
A62: If yes, enter the NOL that you are carrying over into year 1 | B62: =474.8+256.6 | C62: An NOL will shield your income from taxes, even after you start making money.
A63: I will asssume that today's risk free rate will prevail in perpetuity. If you override this assumption, I will change the riskfree rate after year 10.
A64: Do you want to override this assumption = | B64: No | C64: If yes, you will be asked to enter a normal risk free rate and your growth in perpetuity will be adjusted accordingly.
A65: If yes, enter the riskfree rate after year 10 | B65: 0.02 | C65: Enter your estimate of what the riskfree rate (in your currency of choice) will be after year 10
A66: I will assume that the growth rate in perpetuity will be equal to the risk free rate. This allows for both valuation consistency and prevents "impossible" growth rates.
A67: Do you want to override this assumption = | B67: No | C67: This is an option to let you use a negative growth rate in perpetuity or to even liquidate the firm.
A68: If yes, enter the growth rate in perpetuity | B68: -0.05 | C68: This can be negative, if you feel the company will decline (and disappear) after growth is done. If you let it exceed the risk free rate, you are on your own in uncharted territory.
A69: I have assumed that none of the cash is trapped (in foreign countries) and that there is no additional tax liability coming due and that cash is a neutral asset.
A70: Do you want to override this assumption | B70: No
A71: If yes, enter trapped cash (if taxes) or entire balance (if mistrust) | B71: 140000 | C71: Cash that is trapped in foreign markets (and subject to additoinal tax) or cash that is being discounted by the market (because of management mistrust)
A72: & Average tax rate of the foreign markets where the cash is trapped | B72: 0.15 | C72: Additional tax rate due on trapped cash or discount being applied to cash balance because of mistrust.

Sheet Valuation output
B1: Base year | C1: 1 | D1: 2 | E1: 3 | F1: 4 | G1: 5 | H1: 6 | I1: 7 | J1: 8 | K1: 9 | L1: 10 | M1: Terminal year
A2: Revenue growth rate | C2: ='Input sheet'!B26 | D2: ='Input sheet'!B28 | E2: =D2 | F2: =E2 | G2: =F2 | H2: =G2-((G2-$M$2)/5) | I2: =G2-((G2-$M$2)/5)*2 | J2: =G2-((G2-$M$2)/5)*3 | K2: =G2-((G2-$M$2)/5)*4 | L2: =G2-((G2-$M$2)/5)*5 | M2: =IF('Input sheet'!B67="Yes",'Input sheet'!B68,IF('Input sheet'!B64="Yes",'Input sheet'!B65,'Input sheet'!B34))
A3: Revenues | B3: ='Input sheet'!B11 | C3: =B3*(1+C2) | D3: =C3*(1+D2) | E3: =D3*(1+E2) | F3: =E3*(1+F2) | G3: =F3*(1+G2) | H3: =G3*(1+H2) | I3: =H3*(1+I2) | J3: =I3*(1+J2) | ... M3: =L3*(1+M2)
A4: EBIT (Operating) margin | B4: =B5/B3 | C4: ='Input sheet'!B27 | D4: =IF(D1>'Input sheet'!$B$30,'Input sheet'!$B$29,'Input sheet'!$B$29-(('Input sheet'!$B$29-$C$4)/'Input sheet'!$B$30)*('Input sheet'!$B$30-D1)) | E4: =IF(E1>'Input sheet'!$B$30,'Input sheet'!$B$29,'Input sheet'!$B$29-(('Input sheet'!$B$29-$C$4)/'Input sheet'!$B$30)*('Input sheet'!$B$30-E1)) | F4: =IF(F1>'Input sheet'!$B$30,'Input sheet'!$B$29,'Input sheet'!$B$29-(('Input sheet'!$B$29-$C$4)/'Input sheet'!$B$30)*('Input sheet'!$B$30-F1)) | G4: =IF(G1>'Input sheet'!$B$30,'Input sheet'!$B$29,'Input sheet'!$B$29-(('Input sheet'!$B$29-$C$4)/'Input sheet'!$B$30)*('Input sheet'!$B$30-G1)) | H4: =IF(H1>'Input sheet'!$B$30,'Input sheet'!$B$29,'Input sheet'!$B$29-(('Input sheet'!$B$29-$C$4)/'Input sheet'!$B$30)*('Input sheet'!$B$30-H1)) | I4: =IF(I1>'Input sheet'!$B$30,'Input sheet'!$B$29,'Input sheet'!$B$29-(('Input sheet'!$B$29-$C$4)/'Input sheet'!$B$30)*('Input sheet'!$B$30-I1)) | J4: =IF(J1>'Input sheet'!$B$30,'Input sheet'!$B$29,'Input sheet'!$B$29-(('Input sheet'!$B$29-$C$4)/'Input sheet'!$B$30)*('Input sheet'!$B$30-J1)) | K4: =IF(K1>'Input sheet'!$B$30,'Input sheet'!$B$29,'Input sheet'!$B$29-(('Input sheet'!$B$29-$C$4)/'Input sheet'!$B$30)*('Input sheet'!$B$30-K1)) | L4: =IF(L1>'Input sheet'!$B$30,'Input sheet'!$B$29,'Input sheet'!$B$29-(('Input sheet'!$B$29-$C$4)/'Input sheet'!$B$30)*('Input sheet'!$B$30-L1)) | M4: =L4
A5: EBIT (Operating income) | B5: =IF('Input sheet'!B17="Yes",IF('Input sheet'!B16="Yes",'Input sheet'!B12+'Operating lease converter'!F32+'R& D converter'!D39,'Input sheet'!B12+'Operating lease converter'!F32),IF('Input sheet'!B16="Yes",'Input sheet'!B12+'R& D converter'!D39,'Input sheet'!B12)) | C5: =C4*C3 | D5: =D4*D3 | E5: =E4*E3 | F5: =F4*F3 | G5: =G4*G3 | H5: =H4*H3 | I5: =I4*I3 | J5: =J4*J3 | ... M5: =M4*M3 | N5: =M5-B5
A6: Tax rate | B6: ='Input sheet'!B23 | C6: =B6 | D6: =C6 | E6: =D6 | F6: =E6 | G6: =F6 | H6: =G6+($M$6-$G$6)/5 | I6: =H6+($M$6-$G$6)/5 | J6: =I6+($M$6-$G$6)/5 | K6: =J6+($M$6-$G$6)/5 | L6: =K6+($M$6-$G$6)/5 | M6: =IF('Input sheet'!B59="Yes",'Input sheet'!B23,'Input sheet'!B24)
A7: EBIT(1-t) | B7: =IF(B5>0,B5*(1-B6),B5) | C7: =IF(C5>0,IF(C5<B10,C5,C5-(C5-B10)*C6),C5) | D7: =IF(D5>0,IF(D5<C10,D5,D5-(D5-C10)*D6),D5) | E7: =IF(E5>0,IF(E5<D10,E5,E5-(E5-D10)*E6),E5) | F7: =IF(F5>0,IF(F5<E10,F5,F5-(F5-E10)*F6),F5) | G7: =IF(G5>0,IF(G5<F10,G5,G5-(G5-F10)*G6),G5) | H7: =IF(H5>0,IF(H5<G10,H5,H5-(H5-G10)*H6),H5) | I7: =IF(I5>0,IF(I5<H10,I5,I5-(I5-H10)*I6),I5) | J7: =IF(J5>0,IF(J5<I10,J5,J5-(J5-I10)*J6),J5) | ... L7: =IF(L5>0,IF(L5<K10,L5,L5-(L5-K10)*L6),L5) | M7: =M5*(1-M6)
A8: - Reinvestment | C8: =IF('Input sheet'!$B$56="No",(D3-C3)/C38,IF('Input sheet'!$B$57=0,(C3-B3)/C38,IF('Input sheet'!$B$57=2,(E3-D3)/C38,IF('Input sheet'!$B$57=3,(F3-E3)/C38,(D3-C3)/C38)))) | D8: =IF('Input sheet'!$B$56="No",(E3-D3)/D38,IF('Input sheet'!$B$57=0,(D3-C3)/D38,IF('Input sheet'!$B$57=2,(F3-E3)/D38,IF('Input sheet'!$B$57=3,(G3-F3)/D38,(E3-D3)/D38)))) | E8: =IF('Input sheet'!$B$56="No",(F3-E3)/E38,IF('Input sheet'!$B$57=0,(E3-D3)/E38,IF('Input sheet'!$B$57=2,(G3-F3)/E38,IF('Input sheet'!$B$57=3,(H3-G3)/E38,(F3-E3)/E38)))) | F8: =IF('Input sheet'!$B$56="No",(G3-F3)/F38,IF('Input sheet'!$B$57=0,(F3-E3)/F38,IF('Input sheet'!$B$57=2,(H3-G3)/F38,IF('Input sheet'!$B$57=3,(I3-H3)/F38,(G3-F3)/F38)))) | G8: =IF('Input sheet'!$B$56="No",(H3-G3)/G38,IF('Input sheet'!$B$57=0,(G3-F3)/G38,IF('Input sheet'!$B$57=2,(I3-H3)/G38,IF('Input sheet'!$B$57=3,(J3-I3)/G38,(H3-G3)/G38)))) | H8: =IF('Input sheet'!$B$56="No",(I3-H3)/H38,IF('Input sheet'!$B$57=0,(H3-G3)/H38,IF('Input sheet'!$B$57=2,(J3-I3)/H38,IF('Input sheet'!$B$57=3,(K3-J3)/H38,(I3-H3)/H38)))) | I8: =IF('Input sheet'!$B$56="No",(J3-I3)/I38,IF('Input sheet'!$B$57=0,(I3-H3)/I38,IF('Input sheet'!$B$57=2,(K3-J3)/I38,IF('Input sheet'!$B$57=3,(L3-K3)/I38,(J3-I3)/I38)))) | J8: =IF('Input sheet'!$B$56="No",(K3-J3)/J38,IF('Input sheet'!$B$57=0,(J3-I3)/J38,IF('Input sheet'!$B$57=2,(L3-K3)/J38,IF('Input sheet'!$B$57=3,(M3-L3)/J38,(K3-J3)/J38)))) | K8: =IF('Input sheet'!$B$56="No",(L3-K3)/K38,IF('Input sheet'!$B$57=0,(K3-J3)/K38,IF('Input sheet'!$B$57=2,L3*L2/K38,IF('Input sheet'!$B$57=3,M3*M2/K38,(L3-K3)/K38)))) | L8: =IF('Input sheet'!$B$56="No",(M3-L3)/L38,IF('Input sheet'!$B$57=0,(L3-K3)/L38,IF('Input sheet'!$B$57=2,M3*M2/L38,IF('Input sheet'!$B$57=3,K8*(1+M2),(M3-L3)/L38)))) | M8: =IF(M2>0,(M2/M40)*M7,0) | N8: =SUM(C8:M8)
A9: FCFF | C9: =C7-C8 | D9: =D7-D8 | E9: =E7-E8 | F9: =F7-F8 | G9: =G7-G8 | H9: =H7-H8 | I9: =I7-I8 | J9: =J7-J8 | ... M9: =M7-M8
A10: NOL | B10: =IF('Input sheet'!B61="Yes",'Input sheet'!B62,0) | C10: =IF(C5<0,B10-C5,IF(B10>C5,B10-C5,0)) | D10: =IF(D5<0,C10-D5,IF(C10>D5,C10-D5,0)) | E10: =IF(E5<0,D10-E5,IF(D10>E5,D10-E5,0)) | F10: =IF(F5<0,E10-F5,IF(E10>F5,E10-F5,0)) | G10: =IF(G5<0,F10-G5,IF(F10>G5,F10-G5,0)) | H10: =IF(H5<0,G10-H5,IF(G10>H5,G10-H5,0)) | I10: =IF(I5<0,H10-I5,IF(H10>I5,H10-I5,0)) | J10: =IF(J5<0,I10-J5,IF(I10>J5,I10-J5,0)) | ... M10: =IF(M5<0,L10-M5,IF(L10>M5,L10-M5,0))
A12: Cost of capital | C12: ='Input sheet'!B35 | D12: =C12 | E12: =D12 | F12: =E12 | G12: =F12 | H12: =G12-($G$12-$M$12)/5 | I12: =H12-($G$12-$M$12)/5 | J12: =I12-($G$12-$M$12)/5 | K12: =J12-($G$12-$M$12)/5 | L12: =K12-($G$12-$M$12)/5 | M12: =IF('Input sheet'!B45="Yes",'Input sheet'!B46,IF('Input sheet'!B64="Yes",'Input sheet'!B65+'Country equity risk premiums'!B1,'Input sheet'!B34+'Country equity risk premiums'!B1))
A13: Cumulated discount factor | C13: =1/(1+C12) | D13: =C13*(1/(1+D12)) | E13: =D13*(1/(1+E12)) | F13: =E13*(1/(1+F12)) | G13: =F13*(1/(1+G12)) | H13: =G13*(1/(1+H12)) | I13: =H13*(1/(1+I12)) | J13: =I13*(1/(1+J12)) | K13: =J13*(1/(1+K12)) | L13: =K13*(1/(1+L12))
A14: PV(FCFF) | C14: =C9*C13 | D14: =D9*D13 | E14: =E9*E13 | F14: =F9*F13 | G14: =G9*G13 | H14: =H9*H13 | I14: =I9*I13 | J14: =J9*J13 | ... L14: =L9*L13
A16: Terminal cash flow | B16: =M9
A17: Terminal cost of capital | B17: =M12
A18: Terminal value | B18: =B16/(B17-M2)
A19: PV(Terminal value) | B19: =B18*L13
A20: PV (CF over next 10 years) | B20: =SUM(C14:L14)
A21: Sum of PV | B21: =B19+B20
A22: Probability of failure = | B22: =IF('Input sheet'!B51="Yes",'Input sheet'!B52,0)
A23: Proceeds if firm fails = | B23: =IF('Input sheet'!B53="B",('Input sheet'!B14+'Input sheet'!B15)*'Input sheet'!B54,'Valuation output'!B21*'Input sheet'!B54)
A24: Value of operating assets = | B24: =B21*(1-B22)+B23*B22
A25: - Debt | B25: =IF('Input sheet'!B17="Yes",'Input sheet'!B15+'Operating lease converter'!C28,'Input sheet'!B15)
A26: - Minority interests | B26: ='Input sheet'!B20
A27: + Cash | B27: =IF('Input sheet'!B70="YES",'Input sheet'!B18-'Input sheet'!B71*('Input sheet'!B24-'Input sheet'!B72),'Input sheet'!B18)
A28: + Non-operating assets | B28: ='Input sheet'!B19
A29: Value of equity | B29: =B24-B25-B26+B27+B28
A30: - Value of options | B30: =IF('Input sheet'!B37="No",0,'Option value'!B29)
A31: Value of equity in common stock | B31: =B29-B30
A32: Number of shares | B32: ='Input sheet'!B21
A33: Estimated value /share | B33: =B31/B32
A34: Price | B34: ='Input sheet'!B22
A35: Price as % of value | B35: =B34/B33
A37: Implied variables | M37: After year 10
A38: Sales to capital ratio | C38: ='Input sheet'!B31 | D38: ='Input sheet'!B31 | E38: =D38 | F38: =E38 | G38: ='Input sheet'!B32 | H38: =G38 | I38: =H38 | J38: =I38 | K38: =J38 | L38: =K38
A39: Invested capital | B39: =IF('Input sheet'!B17="Yes",IF('Input sheet'!B16="Yes",'Input sheet'!B14+'Input sheet'!B15-'Input sheet'!B18+'Operating lease converter'!F33+'R& D converter'!D35,'Input sheet'!B14+'Input sheet'!B15-'Input sheet'!B18+'Operating lease converter'!F33),IF('Input sheet'!B16="Yes",'Input sheet'!B14+'Input sheet'!B15-'Input sheet'!B18+'R& D converter'!D35,'Input sheet'!B14+'Input sheet'!B15-'Input sheet'!B18)) | C39: =B39+C8 | D39: =C39+D8 | E39: =D39+E8 | F39: =E39+F8 | G39: =F39+G8 | H39: =G39+H8 | I39: =H39+I8 | J39: =I39+J8 | ... L39: =K39+L8
A40: ROIC | B40: =B7/B39 | C40: =C7/B39 | D40: =D7/C39 | E40: =E7/D39 | F40: =F7/E39 | G40: =G7/F39 | H40: =H7/G39 | I40: =I7/H39 | J40: =J7/I39 | ... L40: =L7/K39 | M40: =IF('Input sheet'!B48="Yes",'Input sheet'!B49,'Valuation output'!L12)

Sheet Stories to Numbers
A1: ='Input sheet'!B4 | G1: ='Input sheet'!B3
A2: The Greatest Cah Machine in History!
A3: Apple remains a company centered on smartphones, and facing slower growth in that market, the company has been building up its services business. That growth will continue, and its profitability will improve margins. Apple's cash balance will keept its cost of captial at close to the median for the US market. | H3: Tell your story about the company. Keep it focuses on the company's businesses and tie it into the three key levers of value: cash flows, growth and risk
A7: The Assumptions
B8: Base year | C8: Next year | D8: Years 2-5 | E8: Years 6-10 | F8: After year 10 | G8: Link to story
A9: Revenues (a) | B9: ='Valuation output'!B3 | C9: ='Input sheet'!B26 | D9: ='Input sheet'!B28 | E9: Changes to | F9: ='Valuation output'!M2 | G9: Growth from services & other businesses | H9: Tie each assumption to the part of your story that relates to it.
A10: Operating margin (b) | B10: ='Valuation output'!B4 | C10: ='Input sheet'!B27 | D10: Moves to | E10: ='Valuation output'!G4 | F10: ='Valuation output'!M4 | G10: High margins on smartphones & electronics, supplemented by service business profits.
A11: Tax rate | B11: ='Valuation output'!B6 | D11: =B11 | E11: Changes to | F11: ='Valuation output'!M6 | G11: Global/US marginal tax rate over time
A12: Sales to Capital (c ) | C12: ='Input sheet'!B31 | D12: ='Input sheet'!B31 | E12: ='Input sheet'!B32 | F12: ='Valuation output'!M2/'Valuation output'!M40 | G12: Low capital intensity business allows for growth with little reinvestment.
A13: Return on capital | B13: ='Valuation output'!B40 | C13: Marginal ROIC = | D13: =Diagnostics!C27 | F13: ='Valuation output'!M40 | G13: Strong competitive edges
A14: Cost of capital (d) | D14: ='Valuation output'!C12 | F14: ='Valuation output'!M12 | G14: Cost of capital close to median company
A15: The Cash Flows
B16: Revenues | C16: Operating Margin | D16: EBIT | E16: EBIT (1-t) | F16: Reinvestment | G16: FCFF | H16: These are the numbers that come from your assumptions. The revenues over time reflect your revenue growth, the operating margins evolve towards your target margin and your tax rate will change, if you have set it to. The reinvestment is estimated using the sales to capital ratio for the first 10 years and based on a reinvestment rate in stable growth (g/ ROC).
A17: 1 | B17: ='Valuation output'!C3 | C17: ='Valuation output'!C4 | D17: =B17*C17 | E17: ='Valuation output'!C7 | F17: ='Valuation output'!C8 | G17: =E17-F17
A18: 2 | B18: ='Valuation output'!D3 | C18: ='Valuation output'!D4 | D18: =B18*C18 | E18: ='Valuation output'!D7 | F18: ='Valuation output'!D8 | G18: =E18-F18
A19: 3 | B19: ='Valuation output'!E3 | C19: ='Valuation output'!E4 | D19: =B19*C19 | E19: ='Valuation output'!E7 | F19: ='Valuation output'!E8 | G19: =E19-F19
A20: 4 | B20: ='Valuation output'!F3 | C20: ='Valuation output'!F4 | D20: =B20*C20 | E20: ='Valuation output'!F7 | F20: ='Valuation output'!F8 | G20: =E20-F20
A21: 5 | B21: ='Valuation output'!G3 | C21: ='Valuation output'!G4 | D21: =B21*C21 | E21: ='Valuation output'!G7 | F21: ='Valuation output'!G8 | G21: =E21-F21
A22: 6 | B22: ='Valuation output'!H3 | C22: ='Valuation output'!H4 | D22: =B22*C22 | E22: ='Valuation output'!H7 | F22: ='Valuation output'!H8 | G22: =E22-F22
A23: 7 | B23: ='Valuation output'!I3 | C23: ='Valuation output'!I4 | D23: =B23*C23 | E23: ='Valuation output'!I7 | F23: ='Valuation output'!I8 | G23: =E23-F23
A24: 8 | B24: ='Valuation output'!J3 | C24: ='Valuation output'!J4 | D24: =B24*C24 | E24: ='Valuation output'!J7 | F24: ='Valuation output'!J8 | G24: =E24-F24
A25: 9 | B25: ='Valuation output'!K3 | C25: ='Valuation output'!K4 | D25: =B25*C25 | E25: ='Valuation output'!K7 | F25: ='Valuation output'!K8 | G25: =E25-F25
A26: 10 | B26: ='Valuation output'!L3 | C26: ='Valuation output'!L4 | D26: =B26*C26 | E26: ='Valuation output'!L7 | F26: ='Valuation output'!L8 | G26: =E26-F26
A27: Terminal year | B27: ='Valuation output'!M3 | C27: ='Valuation output'!M4 | D27: =B27*C27 | E27: ='Valuation output'!M7 | F27: ='Valuation output'!M8 | G27: =E27-F27
A28: The Value
A29: Terminal value | D29: ='Valuation output'!B18 | H29: This is the output from your valuation. It reflects your cash flows being discounted back at the cost of capital to get to your operating asset value, which then gets adjusted for the likelihood that your firm will not make it. We add cash and non-operating assets, subtract out debt and minority interests to get to value of equity.
A30: PV(Terminal value) | D30: ='Valuation output'!B19
A31: PV (CF over next 10 years) | D31: ='Valuation output'!B20
A32: Value of operating assets = | D32: ='Valuation output'!B21
A33: Adjustment for distress | D33: =D32-'Valuation output'!B24 | E33: Probability of failure = | G33: ='Valuation output'!B22
A34: - Debt & Minority Interests | D34: ='Valuation output'!B25+'Valuation output'!B26
A35: + Cash & Other Non-operating assets | D35: ='Valuation output'!B27+'Valuation output'!B28
A36: Value of equity | D36: =D32-D33-D34+D35
A37: - Value of equity options | D37: ='Valuation output'!B30
A38: Number of shares | D38: ='Valuation output'!B32
A39: Value per share | D39: =(D36-D37)/D38 | E39: Stock was trading at = | G39: ='Input sheet'!B22

Sheet Valuation as picture
A1: You can modify this picture and bring in relevant details to back up your cost of capital and other details that you think flesh out your company's valuation story.
A3: ='Input sheet'!B4 | O3: ='Input sheet'!B3
A5: Base Year and Comparison | E5: Growth Story | H5: Profitability Story | K5: Growth Efficiency Story
B6: Company | C6: Industry | E6: ='Stories to Numbers'!G9 | H6: ='Stories to Numbers'!G10 | K6: ='Stories to Numbers'!G12 | O6: Terminal Value
A7: Revenue Growth | B7: ='Input sheet'!I25 | C7: ='Input sheet'!K25 | O7: Growth Rate | P7: =O16
A8: Revenue | B8: ='Valuation output'!B3 | O8: Cost of capital | P8: ='Valuation output'!M12
A9: Operating Margin | B9: ='Valuation output'!B4 | C9: ='Input sheet'!K26 | O9: Return on capital | P9: ='Valuation output'!M40
A10: Operating Income | B10: ='Valuation output'!B5 | O10: Reinvestment Rate | P10: =P7/P9
A11: EBIT (1-t) | B11: ='Valuation output'!B7
A15: ='Valuation output'!A19 | B15: ='Valuation output'!B19 | E15: ='Valuation output'!C1 | F15: ='Valuation output'!D1 | G15: ='Valuation output'!E1 | H15: ='Valuation output'!F1 | I15: ='Valuation output'!G1 | J15: ='Valuation output'!H1 | K15: ='Valuation output'!I1 | L15: ='Valuation output'!J1 | ... O15: ='Valuation output'!M1
A16: ='Valuation output'!A20 | B16: ='Valuation output'!B20 | D16: Revenue Growth | E16: ='Valuation output'!C2 | F16: ='Valuation output'!D2 | G16: ='Valuation output'!E2 | H16: ='Valuation output'!F2 | I16: ='Valuation output'!G2 | J16: ='Valuation output'!H2 | K16: ='Valuation output'!I2 | L16: ='Valuation output'!J2 | ... O16: ='Valuation output'!M2
A17: ='Valuation output'!A22 | B17: ='Valuation output'!B22 | D17: Revenue | E17: ='Valuation output'!C3 | F17: ='Valuation output'!D3 | G17: ='Valuation output'!E3 | H17: ='Valuation output'!F3 | I17: ='Valuation output'!G3 | J17: ='Valuation output'!H3 | K17: ='Valuation output'!I3 | L17: ='Valuation output'!J3 | ... O17: ='Valuation output'!M3
A18: ='Valuation output'!A24 | B18: ='Valuation output'!B24 | D18: Operating Margin | E18: ='Valuation output'!C4 | F18: ='Valuation output'!D4 | G18: ='Valuation output'!E4 | H18: ='Valuation output'!F4 | I18: ='Valuation output'!G4 | J18: ='Valuation output'!H4 | K18: ='Valuation output'!I4 | L18: ='Valuation output'!J4 | ... O18: ='Valuation output'!M4
A19: ='Valuation output'!A25 | B19: ='Valuation output'!B25 | D19: Operating Income | E19: ='Valuation output'!C5 | F19: ='Valuation output'!D5 | G19: ='Valuation output'!E5 | H19: ='Valuation output'!F5 | I19: ='Valuation output'!G5 | J19: ='Valuation output'!H5 | K19: ='Valuation output'!I5 | L19: ='Valuation output'!J5 | ... O19: ='Valuation output'!M5
A20: ='Valuation output'!A26 | B20: ='Valuation output'!B26 | D20: EBIT (1-t) | E20: ='Valuation output'!C7 | F20: ='Valuation output'!D7 | G20: ='Valuation output'!E7 | H20: ='Valuation output'!F7 | I20: ='Valuation output'!G7 | J20: ='Valuation output'!H7 | K20: ='Valuation output'!I7 | L20: ='Valuation output'!J7 | ... O20: ='Valuation output'!M7
A21: ='Valuation output'!A27 | B21: ='Valuation output'!B27 | D21: Reinvestment | E21: ='Valuation output'!C8 | F21: ='Valuation output'!D8 | G21: ='Valuation output'!E8 | H21: ='Valuation output'!F8 | I21: ='Valuation output'!G8 | J21: ='Valuation output'!H8 | K21: ='Valuation output'!I8 | L21: ='Valuation output'!J8 | ... O21: ='Valuation output'!M8
A22: ='Valuation output'!A28 | B22: ='Valuation output'!B28 | D22: FCFF | E22: ='Valuation output'!C9 | F22: ='Valuation output'!D9 | G22: ='Valuation output'!E9 | H22: ='Valuation output'!F9 | I22: ='Valuation output'!G9 | J22: ='Valuation output'!H9 | K22: ='Valuation output'!I9 | L22: ='Valuation output'!J9 | ... O22: ='Valuation output'!M9
A23: ='Valuation output'!A29 | B23: ='Valuation output'!B29 | N23: ='Valuation output'!B18
A24: ='Valuation output'!A30 | B24: ='Valuation output'!B30
A25: ='Valuation output'!A31 | B25: ='Valuation output'!B31 | D25: Cost of Capital | E25: ='Valuation output'!C12 | F25: ='Valuation output'!D12 | G25: ='Valuation output'!E12 | H25: ='Valuation output'!F12 | I25: ='Valuation output'!G12 | J25: ='Valuation output'!H12 | K25: ='Valuation output'!I12 | L25: ='Valuation output'!J12 | ... N25: ='Valuation output'!L12
A26: ='Valuation output'!A32 | B26: ='Valuation output'!B32 | D26: Cumulated WACC | E26: ='Valuation output'!C13 | F26: ='Valuation output'!D13 | G26: ='Valuation output'!E13 | H26: ='Valuation output'!F13 | I26: ='Valuation output'!G13 | J26: ='Valuation output'!H13 | K26: ='Valuation output'!I13 | L26: ='Valuation output'!J13 | ... N26: ='Valuation output'!L13
A27: ='Valuation output'!A33 | B27: ='Valuation output'!B33
D28: Sales to Capital | E28: ='Valuation output'!C38 | F28: ='Valuation output'!D38 | G28: ='Valuation output'!E38 | H28: ='Valuation output'!F38 | I28: ='Valuation output'!G38 | J28: ='Valuation output'!H38 | K28: ='Valuation output'!I38 | L28: ='Valuation output'!J38 | ... N28: ='Valuation output'!L38
A29: Price per share | B29: ='Stories to Numbers'!G39 | D29: ROIC | E29: ='Valuation output'!C40 | F29: ='Valuation output'!D40 | G29: ='Valuation output'!E40 | H29: ='Valuation output'!F40 | I29: ='Valuation output'!G40 | J29: ='Valuation output'!H40 | K29: ='Valuation output'!I40 | L29: ='Valuation output'!J40 | ... O29: ='Valuation output'!M40
A30: % Under or Over Valued | B30: =B29/B27-1
D32: Risk Story | G32: Competitive Advantages
D33: ='Stories to Numbers'!G14 | G33: ='Stories to Numbers'!G13

Sheet Diagnostics
A1: Step 1: Check revenue growth rate | D1: Your forecasts | G1: Questions to ask
B2: Industry Average | C2: Most Recent year | D2: Next year | E2: Years 2-5 | G2: 1. If you are forecasting a revenue growth rate > industry average, is your company small?
A3: Annual Revenue Growth Rate | B3: ='Input sheet'!J25 | C3: ='Input sheet'!I25 | D3: ='Valuation output'!C2 | E3: ='Valuation output'!D2 | G3: 2. If your forecasted revenue growth rate is very different from your company's most recent year of growth, what is the reason?
A5: Step 2: Check dollar revenues
B6: Most Recent year | C6: Next year | D6: Year 5 | E6: Year 10 | G6: 1. How big is the total market today?
A7: Revenues | B7: ='Valuation output'!B3 | C7: ='Valuation output'!C3 | D7: ='Valuation output'!G3 | E7: ='Valuation output'!L3 | G7: 2. How much revenues do the biggest companies in that market make today?
G8: 3. How much growth is there in the total market?
G9: 4. What type of market share are you forecasting for your company in year 10?
A11: Step 3: Check your margins | B11: Most Recent year | C11: Next year | D11: Year 5 | E11: Year 10 | G11: 1. What are the margins of the industry that the company is in?
A12: Operating Margin | B12: ='Valuation output'!B4 | C12: ='Valuation output'!C4 | D12: ='Valuation output'!G4 | E12: ='Valuation output'!M4 | G12: 2. What are the unit economics of the business? (How much does it cost you to make the extra unit that you sell?
G13: 3. What does the competition in this business look like?
A15: Step 4: Check how much you are reinvesting
B16: Most Recent year | C16: Next year | D16: Year 5 | E16: Year 10 | G16: 1. is the growth that you are forecasting bounce-back growth or new growth?
A17: Sales to Capital | B17: ='Input sheet'!I27 | C17: ='Valuation output'!C38 | D17: ='Valuation output'!G38 | E17: ='Valuation output'!L38 | G17: 2. How much excess capacity do you have to service near term growth?
G18: 3. Does investment efficiency in this business change as companies get bigger?
A19: Reinvestment effect on cash flows
B20: $ Value | C20: As % of value
A21: PV of after-tax operating income for next 10 yearas | B21: ='Valuation output'!C7*'Valuation output'!C13+'Valuation output'!D7*'Valuation output'!D13+'Valuation output'!E7*'Valuation output'!E13+'Valuation output'!F7*'Valuation output'!F13+'Valuation output'!G7*'Valuation output'!G13+'Valuation output'!H7*'Valuation output'!H13+'Valuation output'!I7*'Valuation output'!I13+'Valuation output'!J7*'Valuation output'!J13+'Valuation output'!K7*'Valuation output'!K13+'Valuation output'!L7*'Valuation output'!L13 | C21: =B21/B21 | G21: 1. Is your reinvestment consitent with your revenue growth forecast?
A22: Value effect of reinvestment for next 10 years | B22: =B21-B23 | C22: =B22/B21 | G22: 2. Are you comfortable with your return on capital in year 10?
A23: PV of FCFF for next ten years | B23: ='Valuation output'!B20 | C23: =C21-C22
A25: Return on capital effects
B26: Most recent year | C26: Marginal (1-10) | D26: ROC in year 10 | E26: Stable ROC
A27: Return on capital | B27: ='Valuation output'!B40 | C27: =('Valuation output'!L7-'Valuation output'!B7)/('Valuation output'!L39-'Valuation output'!B39) | D27: ='Valuation output'!L40 | E27: ='Valuation output'!M40
A29: Step 5: Risk Metrics
B30: Industry Average | C30: Compounded | D30: Year 1-5 | E30: Stable Growth | G30: 1. How does your cost of capital compare to the industry average?
A31: Cost of capital | B31: ='Input sheet'!J31 | C31: =(1/'Valuation output'!L13)^(1/10)-1 | D31: ='Valuation output'!C12 | E31: ='Valuation output'!M12 | G31: 2. What is happenign to your cost of capital over time? Why?
G32: 3. Is your failure rate consistent with your company's characteristics?
A33: Failure Rate | B33: ='Valuation output'!B22
A35: Step 6: Price versus Value
A36: Your calculated value as a percent of current price | B36: ='Valuation output'!B33/'Valuation output'!B34
B37: =IF(B36="NA","Value is negative. See below",IF(B36>2,"Value seems high. See below",IF(B36<0.5,"Value seems low. See below"," ")))
A38: Inputs | B38: If calculated value is negative or looks too low | C38: If calculated value looks too high
A39: Revenue growth rate (input cell B25, B27) | B39: Increase revenue growth rate | C39: Decrease revenue growth rate
A40: Operating margin (B26, B28) | B40: Increase the target pre-tax operating margin | C40: Decrease the target pre-tax operating margin
A41: Sales to Capital (B30-B32) | B41: Increase the sales/capital ratio | C41: Decrease the sales/capital ratio
A42: Return on capital in perpetuity (B48, B49) | B42: Increase relative to your cost of capital | C42: If higher than your cost of capital, lower towards your cost of capital | D42: T

Sheet Option value
A1: Note: This worksheet is the most finicky of all of the worksheets in this spreadsheet. If you start to get errors, here is a quick fix. Go into cell B12 and replace the contents with a number (say 5), and then undo your action. The spreadsheet will fix itself magically.
A3: Valuing Options or Warrants
A4: Enter the current stock price = | B4: ='Input sheet'!B22
A5: Enter the strike price on the option = | B5: ='Input sheet'!B39
A6: Enter the expiration of the option = | B6: ='Input sheet'!B40
A7: Enter the standard deviation in stock prices = | B7: ='Input sheet'!B41 | C7: (volatility)
A8: Enter the annualized dividend yield on stock = | B8: 0
A9: Enter the treasury bond rate = | B9: ='Input sheet'!B34
A10: Enter the number of warrants (options) outstanding = | B10: ='Input sheet'!B38
A11: Enter the number of shares outstanding = | B11: ='Input sheet'!B21
A13: Do not input any numbers below this line
A14: Dilution-adjusted Black-Scholes
A15: Stock Price= | B15: =B4 | C15: # Warrants issued= | D15: =B10
A16: Strike Price= | B16: =B5 | C16: # Shares outstanding= | D16: =B11
A17: Adjusted S = | B17: =(B15*D16+B28*D15)/(D16+D15) | C17: T.Bond rate= | D17: =B9
A18: Adjusted K = | B18: =B16 | C18: Variance= | D18: =B7^2
A19: Expiration (in years) = | B19: =B6 | C19: Annualized dividend yield= | D19: =B8
C20: Div. Adj. interest rate= | D20: =D17-D19
A22: d1 = | B22: =(LN(B17/B18)+(D20+(D18/2))*B19)/(((D18)^(0.5))*(B19^0.5))
A23: N (d1) = | B23: =NORMSDIST(B22)
A25: d2 = | B25: =B22-((D18^0.5)*(B19^(0.5)))
A26: N (d2) = | B26: =NORMSDIST(B25)
A28: Value per option = | B28: =((EXP((0-D19)*B19))*B17*B23-B18*(EXP((0-D17)*B19))*B26)
A29: Value of all options outstanding = | B29: =B28*B10

Sheet Synthetic rating
A1: If you have negative operating income, this spreadsheet will offer you a D rating. Do not use that rating as your cost of debt for a going concern. Insread give your company a low, but going concern rating like BB and use that cost of debt.
A4: Inputs for synthetic rating estimation
A5: Please read the special cases worksheet (see below) before you use this spreadsheet.
A6: Before you use this spreadsheet, make sure that the iteration box (under calculation options in excel) is checked.
A7: Enter the type of firm = | C7: ='Cost of capital worksheet'!B36
A8: Enter current Earnings before interest and taxes (EBIT) = | F8: =IF('Input sheet'!B17="Yes",'Input sheet'!B12+'Operating lease converter'!F32,'Input sheet'!B12) | G8: (Add back only long term interest expense for financial firms)
A9: Enter current interest expenses = | F9: =IF('Input sheet'!B17="Yes",'Cost of capital worksheet'!B31+'Operating lease converter'!C28*'Operating lease converter'!C15,'Cost of capital worksheet'!B31) | G9: (Use only long term interest expense for financial firms)
A10: Enter long term risk free rate = | F10: ='Input sheet'!B34
A11: Output
A12: Interest coverage ratio = | D12: =IF(F9=0,1000000,IF(F8<0,-100000,F8/F9))
A13: Estimated Bond Rating = | D13: =IF(C7=1,VLOOKUP(D12,A22:D36,3),(IF(C7=2,VLOOKUP(D12,A41:D55,3),VLOOKUP(D12,F22:I36,3)))) | F13: Note: If you get REF! All over the place, set the operating lease commitment question in cell F5
A14: Estimated Company Default Spread = | D14: =IF(C7=1,VLOOKUP(D12,A22:D36,4),(IF(C7=2,VLOOKUP(D12,A41:D55,4),VLOOKUP(D12,F22:I36,4)))) | F14: to No, and then reset it to Yes. It should work.
A15: Estimated County Default Spread (if any) = | D15: =VLOOKUP('Input sheet'!B7,'Country equity risk premiums'!A5:C195,3)
A16: Estimated Cost of Debt = | D16: =F10+D14+D15
A18: If you want to update the spreads listed below, please visit http://www.bondsonline.com
A19: For large manufacturing firms | J19: Default Probabilities over time (1 - 10 year time horizons)
A20: If interest coverage ratio is | J20: Rating | K20: 1 | L20: 2 | M20: 3 | N20: 4 | O20: 5 | P20: 6 | Q20: 7 | R20: 8 | S20: 9 | T20: 10
A21: > | B21: ≤ to | C21: Rating is | D21: Spread is | J21: AAA | K21: 0 | L21: 0.0003 | M21: 0.0013 | N21: 0.0024 | O21: 0.0035 | P21: 0.0045 | Q21: 0.0051 | R21: 0.0059 | S21: 0.0064 | T21: 0.007
A22: -100000 | B22: 0.199999 | C22: D2/D | D22: 0.2 | J22: AA | K22: 0.0002 | L22: 0.0006 | M22: 0.0012 | N22: 0.0021 | O22: 0.0031 | P22: 0.0042 | Q22: 0.005 | R22: 0.0058 | S22: 0.0065 | T22: 0.0072
A23: 0.2 | B23: 0.649999 | C23: C2/C | D23: 0.17 | J23: A | K23: 0.0005 | L23: 0.0014 | M23: 0.0023 | N23: 0.0035 | O23: 0.0047 | P23: 0.0062 | Q23: 0.0079 | R23: 0.0093 | S23: 0.0108 | T23: 0.0124
A24: 0.65 | B24: 0.799999 | C24: Ca2/CC | D24: 0.1178 | J24: BBB | K24: 0.0016 | L24: 0.0045 | M24: 0.0078 | N24: 0.0117 | O24: 0.0158 | P24: 0.0198 | Q24: 0.0233 | R24: 0.0267 | S24: 0.03 | T24: 0.0332
A25: 0.8 | B25: 1.249999 | C25: Caa/CCC | D25: 0.0851 | J25: BB | K25: 0.0061 | L25: 0.0192 | M25: 0.0348 | N25: 0.0505 | O25: 0.0652 | P25: 0.0785 | Q25: 0.0901 | R25: 0.1004 | S25: 0.1097 | T25: 0.1178
A26: 1.25 | B26: 1.499999 | C26: B3/B- | D26: 0.0524 | J26: B | K26: 0.0333 | L26: 0.0771 | M26: 0.1155 | N26: 0.1458 | O26: 0.1693 | P26: 0.1883 | Q26: 0.2036 | R26: 0.216 | S26: 0.227 | T26: 0.2374
A27: 1.5 | B27: 1.749999 | C27: B2/B | D27: 0.0361 | J27: CCC/C | K27: 0.2708 | L27: 0.3664 | M27: 0.4141 | N27: 0.441 | O27: 0.4619 | P27: 0.4709 | Q27: 0.4826 | R27: 0.4905 | S27: 0.4976 | T27: 0.5038
A28: 1.75 | B28: 1.999999 | C28: B1/B+ | D28: 0.0314
A29: 2 | B29: 2.2499999 | C29: Ba2/BB | D29: 0.0221
A30: 2.25 | B30: 2.49999 | C30: Ba1/BB+ | D30: 0.0174
A31: 2.5 | B31: 2.999999 | C31: Baa2/BBB | D31: 0.0147
A32: 3 | B32: 4.249999 | C32: A3/A- | D32: 0.0121
A33: 4.25 | B33: 5.499999 | C33: A2/A | D33: 0.0107
A34: 5.5 | B34: 6.499999 | C34: A1/A+ | D34: 0.0092
A35: 6.5 | B35: 8.499999 | C35: Aa2/AA | D35: 0.007
A36: 8.5 | B36: 100000 | C36: Aaa/AAA | D36: 0.0059
A38: For smaller and riskier firms
A39: If interest coverage ratio is
A40: greater than | B40: ≤ to | C40: Rating is | D40: Spread is
A41: -100000 | B41: 0.499999 | C41: D2/D | D41: 0.2 | G41: Rating is | H41: Spread is
A42: 0.5 | B42: 0.799999 | C42: C2/C | D42: 0.17 | G42: A1/A+ | H42: 0.0092
A43: 0.8 | B43: 1.249999 | C43: Ca2/CC | D43: 0.1178 | G43: A2/A | H43: 0.0107
A44: 1.25 | B44: 1.499999 | C44: Caa/CCC | D44: 0.0851 | G44: A3/A- | H44: 0.0121
A45: 1.5 | B45: 1.999999 | C45: B3/B- | D45: 0.0524 | G45: Aa2/AA | H45: 0.007
A46: 2 | B46: 2.499999 | C46: B2/B | D46: 0.0361 | G46: Aaa/AAA | H46: 0.0059
A47: 2.5 | B47: 2.999999 | C47: B1/B+ | D47: 0.0314 | G47: B1/B+ | H47: 0.0314
A48: 3 | B48: 3.499999 | C48: Ba2/BB | D48: 0.0221 | G48: B2/B | H48: 0.0361
A49: 3.5 | B49: 3.9999999 | C49: Ba1/BB+ | D49: 0.0174 | G49: B3/B- | H49: 0.0524
A50: 4 | B50: 4.499999 | C50: Baa2/BBB | D50: 0.0147 | G50: Ba1/BB+ | H50: 0.0174
A51: 4.5 | B51: 5.999999 | C51: A3/A- | D51: 0.0121 | G51: Ba2/BB | H51: 0.0221
A52: 6 | B52: 7.499999 | C52: A2/A | D52: 0.0107 | G52: Baa2/BBB | H52: 0.0147
A53: 7.5 | B53: 9.499999 | C53: A1/A+ | D53: 0.0092 | G53: C2/C | H53: 0.17
... A55: 12.5 | B55: 100000 | C55: Aaa/AAA | D55: 0.0059 | G55: Caa/CCC | H55: 0.0851
G56: D2/D | H56: 0.2

Sheet R& D converter
A1: R & D Converter
A2: This spreadsheet converts R&D expenses from operating to capital expenses. It makes the appropriate adjustments to operating income, net
A3: income, the book value of assets and the book value of equity.
A5: Inputs
A6: Over how many years do you want to amortize R&D expenses | F6: 3 | G6: ! If in doubt, use the lookup table below
A7: Enter the current year's R&D expense = | F7: 32230 | G7: The maximum allowed is ten years
A8: Enter R& D expenses for past years: the number of years that you will need to enter will be determined by the amortization period
A9: Do not input numbers in the first column (Year). It will get automatically updated based on the input above.
A10: Year | B10: R& D Expenses
A11: -1 | B11: 31370 | C11: ! Year -1 is the year prior to the current year
A12: =IF((0-A11)<$F$6,IF(A11>-1,,A11-1),) | B12: 29915 | C12: ! Year -2 is the two years prior to the current year
A13: =IF((0-A12)<$F$6,IF(A12>-1,,A12-1),) | B13: 26251
A14: =IF((0-A13)<$F$6,IF(A13>-1,,A13-1),)
A15: =IF((0-A14)<$F$6,IF(A14>-1,,A14-1),)
A16: =IF((0-A15)<$F$6,IF(A15>-1,,A15-1),)
A17: =IF((0-A16)<$F$6,IF(A16>-1,,A16-1),)
A18: =IF((0-A17)<$F$6,IF(A17>-1,,A17-1),)
A19: =IF((0-A18)<$F$6,IF(A18>-1,,A18-1),)
A20: =IF((0-A19)<$F$6,IF(A19>-1,,A19-1),)
A22: Output
A23: Year | B23: R&D Expense | C23: Unamortized portion | E23: Amortization this year
A24: Current | B24: =F7 | C24: =1 | D24: =B24*C24
A25: =A11 | B25: =B11 | C25: =IF(A25<0,($F$6+A25)/$F$6,0) | D25: =B25*C25 | E25: =IF(A25<0,B25/$F$6,0)
A26: =A12 | B26: =B12 | C26: =IF(A26<0,($F$6+A26)/$F$6,0) | D26: =B26*C26 | E26: =IF(A26<0,B26/$F$6,0)
A27: =A13 | B27: =B13 | C27: =IF(A27<0,($F$6+A27)/$F$6,0) | D27: =B27*C27 | E27: =IF(A27<0,B27/$F$6,0)
A28: =A14 | B28: =B14 | C28: =IF(A28<0,($F$6+A28)/$F$6,0) | D28: =B28*C28 | E28: =IF(A28<0,B28/$F$6,0)
A29: =A15 | B29: =B15 | C29: =IF(A29<0,($F$6+A29)/$F$6,0) | D29: =B29*C29 | E29: =IF(A29<0,B29/$F$6,0)
A30: =A16 | B30: =B16 | C30: =IF(A30<0,($F$6+A30)/$F$6,0) | D30: =B30*C30 | E30: =IF(A30<0,B30/$F$6,0)
A31: =A17 | B31: =B17 | C31: =IF(A31<0,($F$6+A31)/$F$6,0) | D31: =B31*C31 | E31: =IF(A31<0,B31/$F$6,0)
A32: =A18 | B32: =B18 | C32: =IF(A32<0,($F$6+A32)/$F$6,0) | D32: =B32*C32 | E32: =IF(A32<0,B32/$F$6,0)
A33: =A19 | B33: =B19 | C33: =IF(A33<0,($F$6+A33)/$F$6,0) | D33: =B33*C33 | E33: =IF(A33<0,B33/$F$6,0)
A34: =A20 | B34: =B20 | C34: =IF(A34<0,($F$6+A34)/$F$6,0) | D34: =B34*C34 | E34: =IF(A34<0,B34/$F$6,0)
A35: Value of Research Asset = | D35: =SUM(D24:D34) | E35: =SUM(E25:E34)
A37: Amortization of asset for current year = | D37: =E35
A39: Adjustment to Operating Income = | D39: =F7-D37 | E39: ! A positive number indicates an increase in operating income (add to reported EBIT)
A40: Tax Effect of R&D Expensing | D40: =D39*'Input sheet'!B24

Sheet Operating lease converter
A1: Operating Lease Converter
A2: The yellow cells are input cells. Please enter them.
A3: Inputs | H3: Until 2019, this worksheet had to be used for every firm with operating lease commitments, since accountants treated operating lease expenses as operating expenses. In 2019, IFRS and GAAP made the long-overdue change to treat leases as debt, and for firms that follow these standards, the conversion that I am doing on this spreadsheet is being done by accountants, with lease debt and operating income already adjusted. If that is the case, and you showed the lease debt as part of debt in the input page, please do not use this spreadsheet, since you will be double counting.
A4: Operating lease expense in current year = | E4: 295
A5: Operating Lease Commitments (From footnote to financials)
A6: Year | B6: Commitment | C6: ! Year 1 is next year, ….
A7: 1 | B7: 287
A8: 2 | B8: 235
A9: 3 | B9: 194
A10: 4 | B10: 151
A11: 5 | B11: 98
A12: 6 and beyond | B12: 605
A14: Output
A15: Pre-tax Cost of Debt = | C15: ='Cost of capital worksheet'!B37 | D15: ! If you do not have a cost of debt, use the synthetic rating estimator
A18: Number of years embedded in yr 6 estimate = | D18: =IF(B12>0,ROUND(B12/AVERAGE(B7:B11),0),0) | E18: ! I use the average lease expense over the first five years
E19: to estimate the number of years of expenses in yr 6
A20: Converting Operating Leases into debt
A21: Year | B21: Commitment | C21: Present Value
A22: =A7 | B22: =B7 | C22: =B22/(1+$C$15)^A22
A23: =A8 | B23: =B8 | C23: =B23/(1+$C$15)^A23
A24: =A9 | B24: =B9 | C24: =B24/(1+$C$15)^A24
A25: =A10 | B25: =B10 | C25: =B25/(1+$C$15)^A25
A26: =A11 | B26: =B11 | C26: =B26/(1+$C$15)^A26
A27: =A12 | B27: =IF(B12>0,IF(D18>0,B12/D18,B12),0) | C27: =IF(D18>0,(B27*(1-(1+C15)^(-D18))/C15)/(1+$C$15)^5,B27/(1+C15)^6) | D27: ! Commitment beyond year 6 converted into an annuity for ten years
A28: Debt Value of leases = | C28: =SUM(C22:C27)
A30: Restated Financials
A31: Depreciation on Operating Lease Asset = | F31: =C28/(5+D18) | G31: ! I use straight line depreciation
A32: Adjustment to Operating Earnings = | F32: =E4-F31 | G32: ! Add this amount to pre-tax operating income
A33: Adjustment to Total Debt outstanding = | F33: =C28 | G33: ! Add this amount to debt
A34: Adjustment to Depreciation = | F34: =C28/(5+D18)

Sheet Cost of capital worksheet
A1: You can use this spreadsheet to compute your cost of capital. You can either use the built-in data to compute key inputs (beta, equity risk premium, default spread) or enter them directly. If you choose to use the built in ERP data, you can update the ERP numbers to reflect a more current mature market premuum (since the spreadsheet uses the start of the year numbers).
A3: Estimation of Current Cost of Capital | G3: Operating Countries ERP calculator
A4: There are four ways in whch you can estimate your cost of capital. In the first, you can directly input a cost of captial. In the second, you can work through your company's cost of capital inputs in detail, entering business, geogaphical mix and debt, and I will help you estimate a cost of capital. In the third, you can look up the cost of capital for the industry or industries your firm belongs to and in the fourth, you can use a crosssectional distribution of costs of capital for companies at the start of the year to make your estimate. | G4: Country | H4: Revenues | I4: ERP | J4: Weight | K4: Weighted ERP
G5: United States | H5: 193636 | I5: =IF(H5=0,0,VLOOKUP(G5,'Country equity risk premiums'!$A$5:$D$195,4)) | J5: =IF(H5>0,H5/$H$18,) | K5: =IF(J5=0,0,I5*J5) | M5: The last two rows in each of country/region risk premium tables is set aside for your input to provide you with flexibility to enter some numbers directly. For instance, assume that you have a company that breaks its revenues down into three countries and then puts the rest into "Rest of the World". You can enter the "Rest of the World" in one of these two rows and enter an equity risk premium for the rest of the world. The easiest way to do that is to go into the country equity risk premium worksheet and change the GDP for the three countries that you have data for to zero and compute the global weighted average ERP for the remaining countries. With the regional worksheet, you can use the last two rows to enter the data for an individual country (usually the domestic country) that might be broken out though the rest of the revenues are broken down by region. You can look up the ERP for the country in the country ERP worksheet.
G6: China | H6: 500 | I6: =IF(H6=0,0,VLOOKUP(G6,'Country equity risk premiums'!$A$5:$D$195,4)) | J6: =IF(H6>0,H6/$H$18,) | K6: =IF(J6=0,0,I6*J6)
I7: =IF(H7=0,0,VLOOKUP(G7,'Country equity risk premiums'!$A$5:$D$195,4)) | J7: =IF(H7>0,H7/$H$18,) | K7: =IF(J7=0,0,I7*J7)
I8: =IF(H8=0,0,VLOOKUP(G8,'Country equity risk premiums'!$A$5:$D$195,4)) | J8: =IF(H8>0,H8/$H$18,) | K8: =IF(J8=0,0,I8*J8)
I9: =IF(H9=0,0,VLOOKUP(G9,'Country equity risk premiums'!$A$5:$D$195,4)) | J9: =IF(H9>0,H9/$H$18,) | K9: =IF(J9=0,0,I9*J9)
I10: =IF(H10=0,0,VLOOKUP(G10,'Country equity risk premiums'!$A$5:$D$195,4)) | J10: =IF(H10>0,H10/$H$18,) | K10: =IF(J10=0,0,I10*J10)
A11: Which approach will you be using? | B11: Detailed | I11: =IF(H11=0,0,VLOOKUP(G11,'Country equity risk premiums'!$A$5:$D$195,4)) | J11: =IF(H11>0,H11/$H$18,) | K11: =IF(J11=0,0,I11*J11)
A12: If direct input, enter cost of capital to use | B12: 0.09 | I12: =IF(H12=0,0,VLOOKUP(G12,'Country equity risk premiums'!$A$5:$D$195,4)) | J12: =IF(H12>0,H12/$H$18,) | K12: =IF(J12=0,0,I12*J12)
A13: Cost of capital based upon approach = | B13: =IF(B11="I will input",B12,IF(B11="Detailed",E62,IF(B11="Industry Average",B67,B72))) | I13: =IF(H13=0,0,VLOOKUP(G13,'Country equity risk premiums'!$A$5:$D$195,4)) | J13: =IF(H13>0,H13/$H$18,) | K13: =IF(J13=0,0,I13*J13)
I14: =IF(H14=0,0,VLOOKUP(G14,'Country equity risk premiums'!$A$5:$D$195,4)) | J14: =IF(H14>0,H14/$H$18,) | K14: =IF(J14=0,0,I14*J14)
A15: Approach 1: Detailed Cost of Capital | I15: =IF(H15=0,0,VLOOKUP(G15,'Country equity risk premiums'!$A$5:$D$195,4)) | J15: =IF(H15>0,H15/$H$18,) | K15: =IF(J15=0,0,I15*J15)
A16: Inputs | G16: Rest of the World | H16: 31335 | I16: 0.0641 | J16: =IF(H16>0,H16/$H$18,) | K16: =IF(J16=0,0,I16*J16)
A17: Equity | J17: =IF(H17>0,H17/$H$18,) | K17: =IF(J17=0,0,I17*J17)
A18: Number of Shares outstanding = | B18: ='Input sheet'!B21 | G18: Total | H18: =SUM(H5:H17) | J18: =SUM(J5:J17) | K18: =SUM(K5:K17)
A19: Current Market Price per share = | B19: ='Input sheet'!B22 | G19: Operating Regions ERP calculator
G20: Region | H20: Revenues | I20: ERP | J20: Weight | K20: Weighted ERP
A21: Approach for estimating beta | B21: Single Business(US) | G21: ='Country equity risk premiums'!A201 | I21: ='Country equity risk premiums'!B201 | J21: =H21/$H$32 | K21: =I21*J21
A22: If direct input, enter levered beta (or regression beta) | B22: 1.2 | G22: ='Country equity risk premiums'!A202 | H22: 30658 | I22: ='Country equity risk premiums'!B202 | J22: =H22/$H$32 | K22: =I22*J22
A23: Unlevered beta = | B23: =IF(B21="Single Business(US)",VLOOKUP('Input sheet'!B8,'Industry Averages(US)'!A2:G95,7),IF(B21="Multibusiness(US)",K48,IF(B21="Single Business(Global)",VLOOKUP('Input sheet'!B9,'Industry Average Beta (Global)'!A2:G95,7),'Cost of capital worksheet'!K64))) | G23: ='Country equity risk premiums'!A203 | I23: ='Country equity risk premiums'!B203 | J23: =H23/$H$32 | K23: =I23*J23
A24: Riskfree Rate = | B24: ='Input sheet'!B34 | G24: ='Country equity risk premiums'!A204 | I24: ='Country equity risk premiums'!B204 | J24: =H24/$H$32 | K24: =I24*J24
A25: What approach do you want to use to input ERP? | B25: Operating regions | G25: ='Country equity risk premiums'!A205 | I25: ='Country equity risk premiums'!B205 | J25: =H25/$H$32 | K25: =I25*J25
A26: Direct input for ERP (if you choose "will input" | B26: 0.06 | G26: ='Country equity risk premiums'!A206 | I26: ='Country equity risk premiums'!B206 | J26: =H26/$H$32 | K26: =I26*J26
A27: Equity Risk Premium used in cost of equity = | B27: =IF(B25="Will Input",B26,IF(B25="Country of Incorporation",VLOOKUP('Input sheet'!B7,'Country equity risk premiums'!A5:E181,4),IF(B25="Operating regions",'Cost of capital worksheet'!K32,'Cost of capital worksheet'!K18))) | G27: ='Country equity risk premiums'!A207 | I27: ='Country equity risk premiums'!B207 | J27: =H27/$H$32 | K27: =I27*J27
G28: ='Country equity risk premiums'!A208 | H28: 167045 | I28: ='Country equity risk premiums'!B208 | J28: =H28/$H$32 | K28: =I28*J28
A29: Debt | G29: ='Country equity risk premiums'!A209 | H29: 101328 | I29: ='Country equity risk premiums'!B209 | J29: =H29/$H$32 | K29: =I29*J29
A30: Book Value of Straight Debt = | B30: ='Input sheet'!B15 | G30: Japão | H30: 25052 | I30: =$B$1+E93 | J30: =H30/$H$32 | K30: =I30*J30
A31: Interest Expense on Debt = | B31: ='Input sheet'!B13 | G31: China | H31: 66952 | I31: =$B$1+E42 | J31: =H31/$H$32 | K31: =I31*J31
A32: Average Maturity = | B32: 0 | G32: Total | H32: =SUM(H21:H31) | J32: =SUM(J21:J31) | K32: =SUM(K21:K31)
A33: Approach for estimating pre-tax cost of debt | B33: Actual rating
A34: If direct input, input the pre-tax cost of debt | B34: 0.04 | G34: Multi Business (US Industry Averages)
A35: If actual rating, input the rating | B35: Aa2/AA | G35: Business | H35: Revenues | I35: EV/Sales | J35: Estimated Value | K35: Unlevered Beta | L35: Cost of capital
A36: If synethetic rating, input the type of company | B36: 2 | G36: Computers/Peripherals | H36: 195010 | I36: =IF(G36=0,,VLOOKUP(G36,'Industry Averages(US)'!$A$2:$S$95,15)) | J36: =H36*I36 | K36: =IF(I36=0,0,VLOOKUP(G36,'Industry Averages(US)'!$A$2:$S$95,7)) | L36: =IF(I36=0,0,VLOOKUP(G36,'Industry Averages(US)'!$A$2:$S$95,13))
A37: Pre-tax Cost of Debt = | B37: =IF(B33="Direct Input",B34,IF(B33="Synthetic Rating",'Synthetic rating'!D16,B24+VLOOKUP('Cost of capital worksheet'!B35,'Synthetic rating'!G42:H56,2))) | G37: Electronics (General) | H37: 43000 | I37: =IF(G37=0,,VLOOKUP(G37,'Industry Averages(US)'!$A$2:$S$95,15)) | J37: =H37*I37 | K37: =IF(I37=0,0,VLOOKUP(G37,'Industry Averages(US)'!$A$2:$S$95,7)) | L37: =IF(I37=0,0,VLOOKUP(G37,'Industry Averages(US)'!$A$2:$S$95,13))
A38: Tax Rate = | B38: ='Input sheet'!B24 | G38: Entertainment | H38: 15000 | I38: =IF(G38=0,,VLOOKUP(G38,'Industry Averages(US)'!$A$2:$S$95,15)) | J38: =H38*I38 | K38: =IF(I38=0,0,VLOOKUP(G38,'Industry Averages(US)'!$A$2:$S$95,7)) | L38: =IF(I38=0,0,VLOOKUP(G38,'Industry Averages(US)'!$A$2:$S$95,13))
I39: =IF(G39=0,,VLOOKUP(G39,'Industry Averages(US)'!$A$2:$S$95,15)) | J39: =H39*I39 | K39: =IF(I39=0,0,VLOOKUP(G39,'Industry Averages(US)'!$A$2:$S$95,7)) | L39: =IF(I39=0,0,VLOOKUP(G39,'Industry Averages(US)'!$A$2:$S$95,13))
A40: Book Value of Convertible Debt = | B40: 0 | I40: =IF(G40=0,,VLOOKUP(G40,'Industry Averages(US)'!$A$2:$S$95,15)) | J40: =H40*I40 | K40: =IF(I40=0,0,VLOOKUP(G40,'Industry Averages(US)'!$A$2:$S$95,7)) | L40: =IF(I40=0,0,VLOOKUP(G40,'Industry Averages(US)'!$A$2:$S$95,13))
A41: Interest Expense on Convertible = | B41: 0 | I41: =IF(G41=0,,VLOOKUP(G41,'Industry Averages(US)'!$A$2:$S$95,15)) | J41: =H41*I41 | K41: =IF(I41=0,0,VLOOKUP(G41,'Industry Averages(US)'!$A$2:$S$95,7)) | L41: =IF(I41=0,0,VLOOKUP(G41,'Industry Averages(US)'!$A$2:$S$95,13))
A42: Maturity of Convertible Bond = | B42: 0 | I42: =IF(G42=0,,VLOOKUP(G42,'Industry Averages(US)'!$A$2:$S$95,15)) | J42: =H42*I42 | K42: =IF(I42=0,0,VLOOKUP(G42,'Industry Averages(US)'!$A$2:$S$95,7)) | L42: =IF(I42=0,0,VLOOKUP(G42,'Industry Averages(US)'!$A$2:$S$95,13))
A43: Market Value of Convertible = | B43: 0 | I43: =IF(G43=0,,VLOOKUP(G43,'Industry Averages(US)'!$A$2:$S$95,15)) | J43: =H43*I43 | K43: =IF(I43=0,0,VLOOKUP(G43,'Industry Averages(US)'!$A$2:$S$95,7)) | L43: =IF(I43=0,0,VLOOKUP(G43,'Industry Averages(US)'!$A$2:$S$95,13))
I44: =IF(G44=0,,VLOOKUP(G44,'Industry Averages(US)'!$A$2:$S$95,15)) | J44: =H44*I44 | K44: =IF(I44=0,0,VLOOKUP(G44,'Industry Averages(US)'!$A$2:$S$95,7)) | L44: =IF(I44=0,0,VLOOKUP(G44,'Industry Averages(US)'!$A$2:$S$95,13)) | M44: The costt of capital is in US dollars, using the riskfree rate at the start of the year. It will be adjusted for the difference in riskfree rates to make it more current and to change currencies.
A45: Debt value of operating leases = | B45: =IF('Input sheet'!B17="Yes",'Operating lease converter'!F33,0) | I45: =IF(G45=0,,VLOOKUP(G45,'Industry Averages(US)'!$A$2:$S$95,15)) | J45: =H45*I45 | K45: =IF(I45=0,0,VLOOKUP(G45,'Industry Averages(US)'!$A$2:$S$95,7)) | L45: =IF(I45=0,0,VLOOKUP(G45,'Industry Averages(US)'!$A$2:$S$95,13))
I46: =IF(G46=0,,VLOOKUP(G46,'Industry Averages(US)'!$A$2:$S$95,15)) | J46: =H46*I46 | K46: =IF(I46=0,0,VLOOKUP(G46,'Industry Averages(US)'!$A$2:$S$95,7)) | L46: =IF(I46=0,0,VLOOKUP(G46,'Industry Averages(US)'!$A$2:$S$95,13))
A47: Preferred Stock | I47: =IF(G47=0,,VLOOKUP(G47,'Industry Averages(US)'!$A$2:$S$95,15)) | J47: =H47*I47 | K47: =IF(I47=0,0,VLOOKUP(G47,'Industry Averages(US)'!$A$2:$S$95,7)) | L47: =IF(I47=0,0,VLOOKUP(G47,'Industry Averages(US)'!$A$2:$S$95,13))
A48: Number of Preferred Shares = | B48: 0 | G48: Company | H48: =SUM(H36:H47) | J48: =SUM(J36:J47) | K48: =K36*(J36/J48)+K37*J37/J48+K38*J38/J48+K39*J39/J48+K40*J40/J48+K41*J41/J48+K42*J42/J48+K43*J43/J48+K44*J44/J48+K45*J45/J48+K46*J46/J48+K47*J47/J48 | L48: =L36*(J36/J48)+L37*J37/J48+L38*J38/J48+L39*J39/J48+L40*J40/J48+L41*J41/J48+L42*J42/J48+L43*J43/J48+L44*J44/J48+L45*J45/J48+L46*J46/J48+L47*J47/J48
A49: Current Market Price per Share= | B49: 70
A50: Annual Dividend per Share = | B50: 5 | G50: Multi Business (Global Industry Averages)
G51: Business | H51: Revenues | I51: EV/Sales | J51: Estimated Value | K51: Unlevered Beta | L51: Cost of capital
A52: Output | G52: Electronics (General) | H52: 81363 | I52: =IF(G52=0,,VLOOKUP(G52,'Industry Average Beta (Global)'!$A$2:$O$95,15)) | J52: =H52*I52 | K52: =IF(G52=0,,VLOOKUP(G52,'Industry Average Beta (Global)'!$A$2:$O$95,7)) | L52: =IF(I52=0,0,VLOOKUP(G52,'Industry Average Beta (Global)'!$A$2:$M$95,13))
A53: Estimating Market Value of Straight Debt = | C53: =B31*(1-(1+B37)^(-B32))/B37+B30/(1+B37)^B32 | I53: =IF(G53=0,,VLOOKUP(G53,'Industry Average Beta (Global)'!$A$2:$O$95,15)) | J53: =H53*I53 | K53: =IF(G53=0,,VLOOKUP(G53,'Industry Average Beta (Global)'!$A$2:$O$95,7)) | L53: =IF(I53=0,0,VLOOKUP(G53,'Industry Average Beta (Global)'!$A$2:$M$95,13))
A54: Estimated Value of Straight Debt in Convertible = | C54: =B41*(1-(1+B37)^(-B42))/B37+B40/(1+B37)^B42 | I54: =IF(G54=0,,VLOOKUP(G54,'Industry Average Beta (Global)'!$A$2:$O$95,15)) | J54: =H54*I54 | K54: =IF(G54=0,,VLOOKUP(G54,'Industry Average Beta (Global)'!$A$2:$O$95,7)) | L54: =IF(I54=0,0,VLOOKUP(G54,'Industry Average Beta (Global)'!$A$2:$M$95,13))
A55: Value of Debt in Operating leases = | C55: =B45 | I55: =IF(G55=0,,VLOOKUP(G55,'Industry Average Beta (Global)'!$A$2:$O$95,15)) | J55: =H55*I55 | K55: =IF(G55=0,,VLOOKUP(G55,'Industry Average Beta (Global)'!$A$2:$O$95,7)) | L55: =IF(I55=0,0,VLOOKUP(G55,'Industry Average Beta (Global)'!$A$2:$M$95,13))
A56: Estimated Value of Equity in Convertible = | C56: =B43-C54 | I56: =IF(G56=0,,VLOOKUP(G56,'Industry Average Beta (Global)'!$A$2:$O$95,15)) | J56: =H56*I56 | K56: =IF(G56=0,,VLOOKUP(G56,'Industry Average Beta (Global)'!$A$2:$O$95,7)) | L56: =IF(I56=0,0,VLOOKUP(G56,'Industry Average Beta (Global)'!$A$2:$M$95,13))
A57: Levered Beta for equity = | C57: =IF(B21="Direct Input",B22,B23*(1+(1-B38)*(C60/B60))) | I57: =IF(G57=0,,VLOOKUP(G57,'Industry Average Beta (Global)'!$A$2:$O$95,15)) | J57: =H57*I57 | K57: =IF(G57=0,,VLOOKUP(G57,'Industry Average Beta (Global)'!$A$2:$O$95,7)) | L57: =IF(I57=0,0,VLOOKUP(G57,'Industry Average Beta (Global)'!$A$2:$M$95,13))
I58: =IF(G58=0,,VLOOKUP(G58,'Industry Average Beta (Global)'!$A$2:$O$95,15)) | J58: =H58*I58 | K58: =IF(G58=0,,VLOOKUP(G58,'Industry Average Beta (Global)'!$A$2:$O$95,7)) | L58: =IF(I58=0,0,VLOOKUP(G58,'Industry Average Beta (Global)'!$A$2:$M$95,13))
B59: Equity | C59: Debt | D59: Preferred Stock | E59: Capital | I59: =IF(G59=0,,VLOOKUP(G59,'Industry Average Beta (Global)'!$A$2:$O$95,15)) | J59: =H59*I59 | K59: =IF(G59=0,,VLOOKUP(G59,'Industry Average Beta (Global)'!$A$2:$O$95,7)) | L59: =IF(I59=0,0,VLOOKUP(G59,'Industry Average Beta (Global)'!$A$2:$M$95,13))
A60: Market Value | B60: =B18*B19 | C60: =C53+C54+C55 | D60: =B48*B49 | E60: =SUM(B60:D60) | I60: =IF(G60=0,,VLOOKUP(G60,'Industry Average Beta (Global)'!$A$2:$O$95,15)) | J60: =H60*I60 | K60: =IF(G60=0,,VLOOKUP(G60,'Industry Average Beta (Global)'!$A$2:$O$95,7)) | L60: =IF(I60=0,0,VLOOKUP(G60,'Industry Average Beta (Global)'!$A$2:$M$95,13)) | M60: The cost of capital is in US dollars, using the riskfree rate at the start of the year. It will be adjusted for the difference in riskfree rates to make it more current and to change currencies.
A61: Weight in Cost of Capital | B61: =B60/$E$60 | C61: =C60/$E$60 | D61: =D60/$E$60 | E61: =SUM(B61:D61) | I61: =IF(G61=0,,VLOOKUP(G61,'Industry Average Beta (Global)'!$A$2:$O$95,15)) | J61: =H61*I61 | K61: =IF(G61=0,,VLOOKUP(G61,'Industry Average Beta (Global)'!$A$2:$O$95,7)) | L61: =IF(I61=0,0,VLOOKUP(G61,'Industry Average Beta (Global)'!$A$2:$M$95,13))
A62: Cost of Component | B62: =B24+C57*B27 | C62: =B37*(1-B38) | D62: =B50/B49 | E62: =B61*B62+C61*C62+D61*D62 | I62: =IF(G62=0,,VLOOKUP(G62,'Industry Average Beta (Global)'!$A$2:$O$95,15)) | J62: =H62*I62 | K62: =IF(G62=0,,VLOOKUP(G62,'Industry Average Beta (Global)'!$A$2:$O$95,7)) | L62: =IF(I62=0,0,VLOOKUP(G62,'Industry Average Beta (Global)'!$A$2:$M$95,13))
I63: =IF(G63=0,,VLOOKUP(G63,'Industry Average Beta (Global)'!$A$2:$O$95,15)) | J63: =H63*I63 | K63: =IF(G63=0,,VLOOKUP(G63,'Industry Average Beta (Global)'!$A$2:$O$95,7)) | L63: =IF(I63=0,0,VLOOKUP(G63,'Industry Average Beta (Global)'!$A$2:$M$95,13))
G64: Company | H64: =SUM(H52:H63) | J64: =SUM(J52:J63) | K64: =K52*(J52/J64)+K53*J53/J64+K54*J54/J64+K55*J55/J64+K56*J56/J64+K57*J57/J64+K58*J58/J64+K59*J59/J64+K60*J60/J64+K61*J61/J64+K62*J62/J64+K63*J63/J64 | L64: =L52*(J52/J64)+L53*J53/J64+L54*J54/J64+L55*J55/J64+L56*J56/J64+L57*J57/J64+L58*J58/J64+L59*J59/J64+L60*J60/J64+L61*J61/J64+L62*J62/J64+L63*J63/J64
A65: Approach 2: industry average cost of capital, adjusted for riskfre rate differences
A66: Industry | B66: Multibusiness(US)
A67: Cost of capital, adjusted for riskfree rate difference | B67: =IF(B66="Single Business(US)",(VLOOKUP('Input sheet'!B8,'Industry Averages(US)'!A2:M95,13)+('Input sheet'!B34-3.88%)),IF(B66="Multibusiness(US)",L48+('Input sheet'!B34-3.88%),IF(B66="Single Business(Global)",(VLOOKUP('Input sheet'!B8,'Industry Average Beta (Global)'!A2:M95,13)+('Input sheet'!B34-3.88%)),L64+('Input sheet'!B34-3.88%))))
A69: Approach 3: Uae histogram of costs of capital of all publicly traded firms
A70: Which grouping (US, Emerging Markets, Global) | B70: US
A71: Which risk grouping does your company fall in? | B71: Median
A72: Cost of capital based upon decile/group chosen | B72: =VLOOKUP(B70,A75:F79,IF(B71="First Decile",2,IF(B71="First Quartile",3,IF(B71="Median",4,IF(B71="Third Quartile",5,6)))))
A74: Region | B74: First Decile | C74: First Quartile | D74: Median | E74: Third Quartile | F74: Ninth Decile
A75: Emerging | B75: ='Input sheet'!B34+2.37% | C75: ='Input sheet'!B34+3.43% | D75: ='Input sheet'!B34+4.74% | E75: ='Input sheet'!B34+5.94% | F75: ='Input sheet'!B34+7.77%
A76: Europe | B76: ='Input sheet'!B34+3.04% | C76: ='Input sheet'!B34+4.18% | D76: ='Input sheet'!B34+5.4% | E76: ='Input sheet'!B34+6.87% | F76: ='Input sheet'!B34+8.77%
A77: Global | B77: ='Input sheet'!B34+1.32% | C77: ='Input sheet'!B34+2.45% | D77: ='Input sheet'!B34+4.03% | E77: ='Input sheet'!B34+4.99% | F77: ='Input sheet'!B34+5.74%
A78: Japan | B78: ='Input sheet'!B34+2.6% | C78: ='Input sheet'!B34+3.58% | D78: ='Input sheet'!B34+4.74% | E78: ='Input sheet'!B34+5.59% | F78: ='Input sheet'!B34+6.83%
A79: US | B79: ='Input sheet'!B34+2.35% | C79: ='Input sheet'!B34+3.67% | D79: ='Input sheet'!B34+4.52% | E79: ='Input sheet'!B34+4.76% | F79: ='Input sheet'!B34+5.29%
A80: These costs of capital are all in US dollars and reflect the US dollar riskfree rate at the start of the year. Once you make your choice, though, I will adjust the rate by the difference in riskfree rates, effectively converting currency and bringing it up to date.

Sheet Failure Rate worksheet
A1: Estimating the likelihood of failure
A2: Approach 1: Using a corporate bond rating
A4: Default Probabilities over time (1 - 10 year time horizons)
A5: Rating | B5: 1 | C5: 2 | D5: 3 | E5: 4 | F5: 5 | G5: 6 | H5: 7 | I5: 8 | J5: 9 | K5: 10
A6: AAA | B6: 0 | C6: 0.0003 | D6: 0.0013 | E6: 0.0024 | F6: 0.0035 | G6: 0.0045 | H6: 0.0051 | I6: 0.0059 | J6: 0.0064 | K6: 0.007
A7: AA | B7: 0.0002 | C7: 0.0006 | D7: 0.0012 | E7: 0.0021 | F7: 0.0031 | G7: 0.0042 | H7: 0.005 | I7: 0.0058 | J7: 0.0065 | K7: 0.0072
A8: A | B8: 0.0005 | C8: 0.0014 | D8: 0.0023 | E8: 0.0035 | F8: 0.0047 | G8: 0.0062 | H8: 0.0079 | I8: 0.0093 | J8: 0.0108 | K8: 0.0124
A9: BBB | B9: 0.0016 | C9: 0.0045 | D9: 0.0078 | E9: 0.0117 | F9: 0.0158 | G9: 0.0198 | H9: 0.0233 | I9: 0.0267 | J9: 0.03 | K9: 0.0332
A10: BB | B10: 0.0061 | C10: 0.0192 | D10: 0.0348 | E10: 0.0505 | F10: 0.0652 | G10: 0.0785 | H10: 0.0901 | I10: 0.1004 | J10: 0.1097 | K10: 0.1178
A11: B | B11: 0.0333 | C11: 0.0771 | D11: 0.1155 | E11: 0.1458 | F11: 0.1693 | G11: 0.1883 | H11: 0.2036 | I11: 0.216 | J11: 0.227 | K11: 0.2374
A12: CCC/C | B12: 0.2708 | C12: 0.3664 | D12: 0.4141 | E12: 0.441 | F12: 0.4619 | G12: 0.4709 | H12: 0.4826 | I12: 0.4905 | J12: 0.4976 | K12: 0.5038
A14: Thus, if you use the 10-year likelihood of failure, the chance of failure for a BB rated firm is 11.78%.
A16: Approach 2: Using corporate age (for young companies)
O17: Survial Rate Data from Bureau of Labor Statistics (2022)
C18: Agriculture | D18: Mining | E18: Utilities | F18: Construction | G18: Manufacturing | H18: Retail | I18: Transportation | J18: Information | K18: Health Care | L18: All Sectors | O18: Agriculture | P18: Mining | Q18: Utilities | R18: Construction | S18: Manufacturing | T18: Retail | U18: Transportation | V18: Information | W18: Health Care | X18: All Sectors
A19: Failure Rate given age | B19: 0 | C19: =1-O28 | D19: =1-P28 | E19: =1-Q28 | F19: =1-R28 | G19: =1-S28 | H19: =1-T28 | I19: =1-U28 | J19: =1-V28 | ... L19: =1-X28 | N19: 1 | O19: 0.823 | P19: 0.818 | Q19: 0.84 | R19: 0.743 | S19: 0.828 | T19: 0.831 | U19: 0.769 | V19: 0.752 | W19: 0.814 | X19: 0.783
B20: 1 | C20: =O19-O$28 | D20: =P19-P$28 | E20: =Q19-Q$28 | F20: =R19-R$28 | G20: =S19-S$28 | H20: =T19-T$28 | I20: =U19-U$28 | J20: =V19-V$28 | ... L20: =X19-X$28 | N20: 2 | O20: 0.748 | P20: 0.712 | Q20: 0.735 | R20: 0.598 | S20: 0.724 | T20: 0.724 | U20: 0.636 | V20: 0.627 | W20: 0.722 | X20: 0.662
B21: 2 | C21: =O20-O$28 | D21: =P20-P$28 | E21: =Q20-Q$28 | F21: =R20-R$28 | G21: =S20-S$28 | H21: =T20-T$28 | I21: =U20-U$28 | J21: =V20-V$28 | ... L21: =X20-X$28 | N21: 3 | O21: 0.661 | P21: 0.629 | Q21: 0.67 | R21: 0.456 | S21: 0.622 | T21: 0.631 | U21: 0.523 | V21: 0.533 | W21: 0.674 | X21: 0.566
B22: 3 | C22: =O21-O$28 | D22: =P21-P$28 | E22: =Q21-Q$28 | F22: =R21-R$28 | G22: =S21-S$28 | H22: =T21-T$28 | I22: =U21-U$28 | J22: =V21-V$28 | ... L22: =X21-X$28 | N22: 4 | O22: 0.612 | P22: 0.538 | Q22: 0.629 | R22: 0.371 | S22: 0.541 | T22: 0.565 | U22: 0.45 | V22: 0.464 | W22: 0.613 | X22: 0.498
B23: 4 | C23: =O22-O$28 | D23: =P22-P$28 | E23: =Q22-Q$28 | F23: =R22-R$28 | G23: =S22-S$28 | H23: =T22-T$28 | I23: =U22-U$28 | J23: =V22-V$28 | ... L23: =X22-X$28 | N23: 5 | O23: 0.574 | P23: 0.512 | Q23: 0.565 | R23: 0.332 | S23: 0.494 | T23: 0.521 | U23: 0.411 | V23: 0.419 | W23: 0.559 | X23: 0.454
B24: 5 | C24: =O23-O$28 | D24: =P23-P$28 | E24: =Q23-Q$28 | F24: =R23-R$28 | G24: =S23-S$28 | H24: =T23-T$28 | I24: =U23-U$28 | J24: =V23-V$28 | ... L24: =X23-X$28 | N24: 6 | O24: 0.541 | P24: 0.472 | Q24: 0.556 | R24: 0.306 | S24: 0.463 | T24: 0.485 | U24: 0.377 | V24: 0.372 | W24: 0.548 | X24: 0.423
B25: 6 | C25: =O24-O$28 | D25: =P24-P$28 | E25: =Q24-Q$28 | F25: =R24-R$28 | G25: =S24-S$28 | H25: =T24-T$28 | I25: =U24-U$28 | J25: =V24-V$28 | ... L25: =X24-X$28 | N25: 7 | O25: 0.516 | P25: 0.429 | Q25: 0.516 | R25: 0.284 | S25: 0.438 | T25: 0.457 | U25: 0.349 | V25: 0.34 | W25: 0.529 | X25: 0.396
B26: 7 | C26: =O25-O$28 | D26: =P25-P$28 | E26: =Q25-Q$28 | F26: =R25-R$28 | G26: =S25-S$28 | H26: =T25-T$28 | I26: =U25-U$28 | J26: =V25-V$28 | ... L26: =X25-X$28 | N26: 8 | O26: 0.495 | P26: 0.405 | Q26: 0.503 | R26: 0.271 | S26: 0.415 | T26: 0.433 | U26: 0.324 | V26: 0.314 | W26: 0.484 | X26: 0.371
B27: 8 | C27: =O26-O$28 | D27: =P26-P$28 | E27: =Q26-Q$28 | F27: =R26-R$28 | G27: =S26-S$28 | H27: =T26-T$28 | I27: =U26-U$28 | J27: =V26-V$28 | ... L27: =X26-X$28 | N27: 9 | O27: 0.465 | P27: 0.371 | Q27: 0.476 | R27: 0.258 | S27: 0.4 | T27: 0.41 | U27: 0.305 | V27: 0.274 | W27: 0.455 | X27: 0.348
B28: 9 | C28: =O27-O$28 | D28: =P27-P$28 | E28: =Q27-Q$28 | F28: =R27-R$28 | G28: =S27-S$28 | H28: =T27-T$28 | I28: =U27-U$28 | J28: =V27-V$28 | ... L28: =X27-X$28 | N28: 10 | O28: 0.449 | P28: 0.323 | Q28: 0.449 | R28: 0.247 | S28: 0.381 | T28: 0.39 | U28: 0.284 | V28: 0.255 | W28: 0.425 | X28: 0.328
B29: 10 | C29: =O28-O$28 | D29: =P28-P$28 | E29: =Q28-Q$28 | F29: =R28-R$28 | G29: =S28-S$28 | H29: =T28-T$28 | I29: =U28-U$28 | J29: =V28-V$28 | ... L29: =X28-X$28
A30: Source; Bureau of Labor Statistics
A31: Thus, if you are valuing a technology firm that is 6 years old, the chance of failure is 11.70%.
A33: Factors to consider
A34: 1. The likelihood of failure decreases for larger firms.
A35: 2. The likelihood of failure decreases with access to capital, and is thus lower for publicly traded firms or firms with multiple high profile VCs
A36: 3. The likelihood of failure decreases as revenue growth increases, since hope for future growth will sustain the firm.
A37: 4. The likelihood of failure decreases with better unit economics, higher gross margins on the additional units sold

Sheet Country equity risk premiums
A1: Mature Market ERP + | B1: 0.0415 | C1: Updated February 1, 2024
A2: Changing this number will update all your country equity risk premiums.
A4: Country | B4: Moody's rating | C4: Adj. Default Spread | D4: Equity Risk Premium | E4: Country Risk Premium | F4: Corporate Tax Rate
A5: Abu Dhabi | B5: Aa2 | C5: 0.0053778763 | D5: =$B$1+E5 | E5: 0.007219474 | F5: 0.15
A6: Albania | B6: B1 | C6: 0.04904111 | D6: =$B$1+E6 | E6: 0.065834727 | F6: 0.15
A7: Algeria | B7: NR | C7: 0.04904111 | D7: =$B$1+E7 | E7: 0.065834727 | F7: 0.26
A8: Andorra (Principality of) | B8: Baa2 | C8: 0.020743237 | D8: =$B$1+E8 | E8: 0.027846543 | F8: 0.1898
A9: Angola | B9: B3 | C9: 0.070808704 | D9: =$B$1+E9 | E9: 0.095056408 | F9: 0.25
A10: Anguilla | B10: NR | C10: 0.1054311 | D10: =$B$1+E10 | E10: 0.18753488 | F10: 0.27245611
A11: Antigua & Barbuda | B11: NR | C11: 0.1054311 | D11: =$B$1+E11 | E11: 0.18753488 | F11: 0.27245611
A12: Argentina | B12: Ca | C12: 0.13073361 | D12: =$B$1+E12 | E12: 0.17550198 | F12: 0.35
A13: Armenia | B13: Ba3 | C13: 0.03918167 | D13: =$B$1+E13 | E13: 0.052599025 | F13: 0.18
A14: Aruba | B14: Baa2 | C14: 0.020743237 | D14: =$B$1+E14 | E14: 0.027846543 | F14: 0.25
A15: Australia | B15: Aaa | C15: 0 | D15: =$B$1+E15 | E15: 0 | F15: 0.3
A16: Austria | B16: Aa1 | C16: 0.0043535189 | D16: =$B$1+E16 | E16: 0.0058443361 | F16: 0.24
... A71: Greece | B71: Ba1 | C71: 0.027273515 | D71: =$B$1+E71 | E71: 0.036613047 | F71: 0.22
A72: Greenland | B72: NR | C72: =J72 | D72: =$B$1+E72 | E72: =H72 | F72: =K72
A73: Guatemala | B73: Ba1 | C73: 0.027273515 | D73: =$B$1+E73 | E73: 0.036613047 | F73: 0.25
A74: Guernsey (States of) | B74: A1 | C74: 0.0076826804 | D74: =$B$1+E74 | E74: 0.010313534 | F74: 0
A75: Guinea | B75: NR | C75: 0.09808222 | D75: =$B$1+E75 | E75: 0.13166945 | F75: 0.2915
A76: Guinea-Bissau | B76: NR | C76: 0.059924907 | D76: =$B$1+E76 | E76: 0.080445567 | F76: 0.2915
A77: Guyana | B77: NR | C77: 0.017414076 | D77: =$B$1+E77 | E77: 0.023377344 | F77: 0.1864
A78: Haiti | B78: NR | C78: 0.10896602 | D78: =$B$1+E78 | E78: 0.14628029 | F78: 0.1864
A79: Honduras | B79: B1 | C79: 0.04904111 | D79: =$B$1+E79 | E79: 0.065834727 | F79: 0.25
A80: Hong Kong | B80: Aa3 | C80: 0.0065302783 | D80: =$B$1+E80 | E80: 0.0087665041 | F80: 0.165
A81: Hungary | B81: Baa2 | C81: 0.020743237 | D81: =$B$1+E81 | E81: 0.027846543 | F81: 0.09
A82: Iceland | B82: A2 | C82: 0.0092192165 | D82: =$B$1+E82 | E82: 0.012376241 | F82: 0.2
A83: India | B83: Baa3 | C83: 0.023944354 | D83: =$B$1+E83 | E83: 0.032143849 | F83: 0.3
A84: Indonesia | B84: Baa2 | C84: 0.020743237 | D84: =$B$1+E84 | E84: 0.027846543 | F84: 0.22
... A116: Malta | B116: A2 | C116: 0.0092192165 | D116: =$B$1+E116 | E116: 0.012376241 | F116: 0.35
A117: Martinique | B117: NR | C117: =J117 | D117: =$B$1+E117 | E117: =H117 | F117: =K117
A118: Mauritius | B118: Baa3 | C118: 0.023944354 | D118: =$B$1+E118 | E118: 0.032143849 | F118: 0.15
A119: Mexico | B119: Baa2 | C119: 0.020743237 | D119: =$B$1+E119 | E119: 0.027846543 | F119: 0.3
A120: Monaco | B120: NR | C120: 0.0095882201 | D120: =$B$1+E120 | E120: 0.058871606 | F120: 0.2470735
A121: Moldova | B121: B3 | C121: 0.070808704 | D121: =$B$1+E121 | E121: 0.095056408 | F121: 0.12
A122: Mongolia | B122: B3 | C122: 0.070808704 | D122: =$B$1+E122 | E122: 0.095056408 | F122: 0.25
A123: Montenegro | B123: B1 | C123: 0.04904111 | D123: =$B$1+E123 | E123: 0.065834727 | F123: 0.15
A124: Montserrat | B124: Baa3 | C124: 0.023944354 | D124: =$B$1+E124 | E124: 0.032143849 | F124: 0.2853
A125: Morocco | B125: Ba1 | C125: 0.027273515 | D125: =$B$1+E125 | E125: 0.036613047 | F125: 0.32
A126: Mozambique | B126: Caa2 | C126: 0.09808222 | D126: =$B$1+E126 | E126: 0.13166945 | F126: 0.32
A127: Myanmar | B127: NR | C127: 0.10896602 | D127: =$B$1+E127 | E127: 0.14628029 | F127: 0.25
A128: Namibia | B128: B1 | C128: 0.04904111 | D128: =$B$1+E128 | E128: 0.065834727 | F128: 0.32
A129: Netherlands | B129: Aaa | C129: 0 | D129: =$B$1+E129 | E129: 0 | F129: 0.258
... A195: Zimbabwe | B195: NR | C195: 0.09808222 | D195: =$B$1+E195 | E195: 0.13166945 | F195: 0.25
A200: Region | B200: ERP | C200: Default Spread | D200: Tax Rate | E200: CRP
A201: Africa | B201: =$B$1+E201 | C201: 0.068262679 | D201: 0.27302836 | E201: 0.091638523
A202: Asia | B202: =$B$1+E202 | C202: 0.012518556 | D202: 0.25764375 | E202: 0.016805405
A203: Australia & New Zealand | B203: =$B$1+E203 | C203: 3.5698902e-05 | D203: 0.29744361 | E203: 4.7923619e-05
A204: Caribbean | B204: =$B$1+E204 | C204: 0.1054311 | D204: 0.27245611 | E204: 0.14153488
A205: Central and South America | B205: =$B$1+E205 | C205: 0.042915086 | D205: 0.31595749 | E205: 0.057610911
A206: Eastern Europe & Russia | B206: =$B$1+E206 | C206: 0.037670398 | D206: 0.18485819 | E206: 0.050579383
A207: Middle East | B207: =$B$1+E207 | C207: 0.016082654 | D207: 0.18760152 | E207: 0.021589991
A208: North America | B208: =$B$1+E208 | C208: 0 | D208: 0.25116287 | E208: 0
A209: Western Europe | B209: =$B$1+E209 | C209: 0.0095882201 | D209: 0.2470735 | E209: 0.012871606
A210: Global | B210: =$B$1+E210 | C210: 0.0135 | D210: 0.25225943 | E210: 0.0181

Sheet Industry Averages(US)
A1: Industry Name | B1: Number of firms | C1: Annual Average Revenue growth - Last 5 years | D1: Pre-tax Operating Margin (Unadjusted) | E1: After-tax ROC | F1: Average effective tax rate | G1: Unlevered Beta | H1: Equity (Levered) Beta | I1: Cost of equity | J1: Std deviation in stock prices | K1: Pre-tax cost of debt | L1: Market Debt/Capital | M1: Cost of capital | N1: Sales/Capital | O1: EV/Sales | P1: EV/EBITDA | Q1: EV/EBIT | R1: Price/Book | S1: Trailing PE | T1: Non-cash WC as % of Revenues | U1: Cap Ex as % of Revenues | V1: Net Cap Ex as % of Revenues | W1: Reinvestment Rate | X1: ROE | Y1: Dividend Payout Ratio | Z1: Equity Reinvestment Rate | AA1: Pre-tax Operating Margin (Lease & R&D adjusted)
A2: Advertising | B2: 57 | C2: 0.115684 | D2: 0.096130213 | E2: 0.31515111 | F2: 0.20554353 | G2: 1.1806104 | H2: 1.3723256 | I2: 0.10192698 | J2: 0.56414425 | K2: 0.053524 | L2: 0.25241808 | M2: 0.086331585 | N2: 3.283403 | O2: 2.2595129 | P2: 12.940313 | Q2: 22.238594 | R2: 5.7632981 | S2: 175.7347 | T2: 0.012534141 | U2: 0.018346747 | V2: -0.016886086 | W2: -0.00993406 | X2: 0.032541006 | Y2: 2.8284446 | Z2: 2.8284446 | AA2: 0.10140072
A3: Aerospace/Defense | B3: 70 | C3: 0.075882564 | D3: 0.085393847 | E3: 0.16167718 | F3: 0.15449878 | G3: 0.93085354 | H3: 1.076405 | I3: 0.088314631 | J3: 0.3640215 | K3: 0.050855 | L3: 0.20291778 | M3: 0.07813356 | N3: 1.9843396 | O3: 2.4783142 | P3: 18.488712 | Q3: 28.310279 | R3: 5.0771569 | S3: 32.517251 | T3: 0.45042764 | U3: 0.028342847 | V3: 0.022829232 | W3: 0.39247743 | X3: 0.13191484 | Y3: 0.53694697 | Z3: 0.53694697 | AA3: 0.087701154
A4: Air Transport | B4: 25 | C4: 0.029028333 | D4: 0.068956115 | E4: 0.10923252 | F4: 0.23528768 | G4: 0.64018805 | H4: 1.2668402 | I4: 0.097074648 | J4: 0.44650999 | K4: 0.050855 | L4: 0.61854039 | M4: 0.060621961 | N4: 1.77732 | O4: 0.9057918 | P4: 6.1674965 | Q4: 13.024538 | R4: 2.235942 | S4: 12.658954 | T4: 0.010944385 | U4: 0.11159926 | V4: 0.067202755 | W4: 1.1858967 | X4: 0.21936354 | Y4: 0.078632719 | Z4: 0.078632719 | AA4: 0.067227109
A5: Apparel | B5: 38 | C5: 0.057186 | D5: 0.087577812 | E5: 0.15293488 | F5: 0.32165919 | G5: 0.92957565 | H5: 1.1946999 | I5: 0.093756194 | J5: 0.3703551 | K5: 0.050855 | L5: 0.3277875 | M5: 0.075526311 | N5: 1.7730762 | O5: 1.2013804 | P5: 7.9181162 | Q5: 12.388401 | R5: 2.5581526 | S5: 18.688545 | T5: 0.24650262 | U5: 0.02417273 | V5: 0.0053650839 | W5: -0.072858763 | X5: 0.092041716 | Y5: 0.74982998 | Z5: 0.74982998 | AA5: 0.096042065
A6: Auto & Truck | B6: 34 | C6: 0.21942111 | D6: 0.04819732 | E6: 0.051866325 | F6: 0.13206978 | G6: 1.3040309 | H6: 1.5223779 | I6: 0.10882938 | J6: 0.59698514 | K6: 0.053524 | L6: 0.23675434 | M6: 0.092567584 | N6: 1.0487317 | O6: 2.4924482 | P6: 21.649291 | Q6: 49.578166 | R6: 4.5988812 | S6: 21.120153 | T6: -0.021993841 | U6: 0.064092755 | V6: 0.026576673 | W6: 0.81471032 | X6: 0.093709081 | Y6: 0.35459225 | Z6: 0.35459225 | AA6: 0.050979542
A7: Auto Parts | B7: 39 | C7: 0.062846957 | D7: 0.053068985 | E7: 0.10156047 | F7: 0.2795041 | G7: 1.1211039 | H7: 1.3444266 | I7: 0.10064362 | J7: 0.37071964 | K7: 0.050855 | L7: 0.27766272 | M7: 0.083289044 | N7: 2.004791 | O7: 0.81660916 | P7: 7.055527 | Q7: 14.116436 | R7: 1.9975303 | S7: 39.033425 | T7: 0.15450925 | U7: 0.037078148 | V7: 0.031693604 | W7: 0.95183325 | X7: 0.057236137 | Y7: 0.45365553 | Z7: 0.45365553 | AA7: 0.058520549
A8: Bank (Money Center) | B8: 15 | C8: 0.072753846 | D8: 0 | E8: 0.00017809966 | F8: 0.15860164 | G8: 0.64400512 | H8: 1.0613762 | I8: 0.087623304 | J8: 0.22510527 | K8: 0.045043 | L8: 0.68370661 | M8: 0.05081182 | N8: 0.266457 | O8: 5.2658799 | P8: NA | Q8: NA | R8: 1.0492602 | S8: 8.5473587 | T8: NA | U8: 0.019731137 | V8: 0.012953142 | W8: 55.728776 | X8: 0.14874035 | Y8: 0.2433797 | Z8: 0.2433797 | AA8: 0.00081200893
A9: Banks (Regional) | B9: 625 | C9: 0.092156242 | D9: 3.6415349e-08 | E9: -0.00053374958 | F9: 0.20724129 | G9: 0.33336661 | H9: 0.46115813 | I9: 0.060013274 | J9: 0.18677353 | K9: 0.045043 | L9: 0.50481829 | M9: 0.046771373 | N9: 0.36719246 | O9: 4.4737565 | P9: NA | Q9: NA | R9: 1.0188589 | S9: 35.966292 | T9: NA | U9: 0.02733682 | V9: -0.10087905 | W9: NA | X9: 0.12142592 | Y9: 0.32014618 | Z9: 0.32014618 | AA9: -0.0017660881
A10: Beverage (Alcoholic) | B10: 19 | C10: 0.12062222 | D10: 0.20626606 | E10: 0.16670847 | F10: 0.25595532 | G10: 0.97026335 | H10: 1.1318349 | I10: 0.090864406 | J10: 0.4970414 | K10: 0.050855 | L10: 0.19656022 | M10: 0.080501131 | N10: 0.89682312 | O10: 3.8916687 | P10: 14.84353 | Q10: 18.678841 | R10: 3.0993349 | S10: 35.375901 | T10: 0.17116248 | U10: 0.076631776 | V10: 0.093903058 | W10: 0.90812969 | X10: 0.086990898 | Y10: 0.54634665 | Z10: 0.54634665 | AA10: 0.20751043
A11: Beverage (Soft) | B11: 29 | C11: 0.28579077 | D11: 0.19303403 | E11: 0.3065163 | F11: 0.18728623 | G11: 0.70183335 | H11: 0.76414588 | I11: 0.07395071 | J11: 0.42961071 | K11: 0.050855 | L11: 0.14615788 | M11: 0.068716876 | N11: 1.6931991 | O11: 4.1646256 | P11: 18.067517 | Q11: 21.467254 | R11: 7.4226028 | S11: 33.673065 | T11: -0.071416169 | U11: 0.046538313 | V11: 0.023869928 | W11: 0.25676456 | X11: 0.30557354 | Y11: 0.66389669 | Z11: 0.66389669 | AA11: 0.19397268
A12: Broadcasting | B12: 22 | C12: 0.054847059 | D12: 0.11778498 | E12: 0.12063889 | F12: 0.2627115 | G12: 0.49975667 | H12: 1.0609244 | I12: 0.087602522 | J12: 0.38457134 | K12: 0.050855 | L12: 0.63820799 | M12: 0.056035943 | N12: 1.1159894 | O12: 1.253302 | P12: 7.3098296 | Q12: 10.673058 | R12: 0.80101351 | S12: 7.8167812 | T12: 0.10922957 | U12: 0.025150013 | V12: -0.020612152 | W12: 2.1143669 | X12: -0.021565149 | Y12: 0.002195876 | Z12: 0.002195876 | AA12: 0.11731512
A13: Brokerage & Investment Banking | B13: 27 | C13: 0.12787474 | D13: 0.0077058531 | E13: 0.0013074469 | F13: 0.21046665 | G13: 0.55077822 | H13: 1.1203262 | I13: 0.090335005 | J13: 0.25213732 | K13: 0.050855 | L13: 0.69330766 | M13: 0.054148675 | N13: 0.27949922 | O13: 5.6097535 | P13: NA | Q13: NA | R13: 1.6565413 | S13: 222.18515 | T13: NA | U13: 0.034125848 | V13: 0.016766163 | W13: 56.433656 | X13: 0.10413111 | Y13: 0.43525111 | Z13: 0.43525111 | AA13: 0.0057932474
A14: Building Materials | B14: 44 | C14: 0.064077647 | D14: 0.13549669 | E14: 0.25267057 | F14: 0.24749104 | G14: 1.2090472 | H14: 1.3177985 | I14: 0.099418732 | J14: 0.2871588 | K14: 0.050855 | L14: 0.15361123 | M14: 0.090005823 | N14: 2.2882187 | O14: 2.1109365 | P14: 12.010469 | Q14: 15.394244 | R14: 4.7352003 | S14: 24.847889 | T14: 0.18356211 | U14: 0.032512734 | V14: 0.024513126 | W14: -0.0076166545 | X14: 0.21354651 | Y14: 0.29019406 | Z14: 0.29019406 | AA14: 0.13773259
A15: Business & Consumer Services | B15: 162 | C15: 0.06692427 | D15: 0.11098788 | E15: 0.2745236 | F15: 0.24242513 | G15: 0.92964266 | H15: 1.0221017 | I15: 0.085816679 | J15: 0.41290055 | K15: 0.050855 | L15: 0.15210607 | M15: 0.078564957 | N15: 2.7218927 | O15: 2.6819988 | P15: 16.123378 | Q15: 23.49344 | R15: 5.5355121 | S15: 86.899382 | T15: 0.13484425 | U15: 0.029848449 | V15: 0.016940121 | W15: 0.25446821 | X15: 0.13997547 | Y15: 0.59783008 | Z15: 0.59783008 | AA15: 0.11307359
A16: Cable TV | B16: 10 | C16: 0.16231667 | D16: 0.19465082 | E16: 0.11311872 | F16: 0.25555177 | G16: 0.73562954 | H16: 1.2767983 | I16: 0.097532723 | J16: 0.33005304 | K16: 0.050855 | L16: 0.50426003 | M16: 0.067583977 | N16: 0.77672237 | O16: 2.5465854 | P16: 7.8008724 | Q16: 13.348956 | R16: 2.0630945 | S16: 16.12066 | T16: -0.00097741192 | U16: 0.14079354 | V16: 0.016512641 | W16: 0.15767367 | X16: 0.19466771 | Y16: 0.21927067 | Z16: 0.21927067 | AA16: 0.19087795
A17: Chemical (Basic) | B17: 32 | C17: 0.113161 | D17: 0.078809382 | E17: 0.11808932 | F17: 0.23971308 | G17: 0.87469078 | H17: 1.0962671 | I17: 0.089228286 | J17: 0.38924524 | K17: 0.050855 | L17: 0.31354658 | M17: 0.07321012 | N17: 1.6175128 | O17: 1.1499986 | P17: 8.0995323 | Q17: 14.056068 | R17: 1.9757813 | S17: 12.407994 | T17: 0.14739172 | U17: 0.055075324 | V17: 0.030793498 | W17: 0.173667 | X17: 0.088946042 | Y17: 1.3126657 | Z17: 1.3126657 | AA17: 0.080172536
A18: Chemical (Diversified) | B18: 4 | C18: -0.00755 | D18: 0.015232689 | E18: 0.015720853 | F18: 0.44293366 | G18: 0.81346086 | H18: 1.1332797 | I18: 0.090930868 | J18: 0.37242278 | K18: 0.050855 | L18: 0.41012862 | M18: 0.069280335 | N18: 1.2786447 | O18: 1.1597139 | P18: 15.396064 | Q18: 73.615159 | R18: 1.9746043 | S18: 30.52773 | T18: 0.17621389 | U18: 0.04511777 | V18: -0.0057903354 | W18: -5.5565142 | X18: -0.023605004 | Y18: 0.01037037 | Z18: 0.01037037 | AA18: 0.014639497
A19: Chemical (Specialty) | B19: 68 | C19: 0.07331875 | D19: 0.13090391 | E19: 0.13505276 | F19: 0.182667 | G19: 0.93813574 | H19: 1.0873833 | I19: 0.088819631 | J19: 0.36600539 | K19: 0.050855 | L19: 0.21148852 | M19: 0.078101735 | N19: 1.1573241 | O19: 2.6791416 | P19: 12.849678 | Q19: 19.995555 | R19: 2.6727607 | S19: 60.901134 | T19: 0.22747766 | U19: 0.084587825 | V19: 0.098115173 | W19: 1.0348497 | X19: 0.14943273 | Y19: 0.33249927 | Z19: 0.33249927 | AA19: 0.13047366
A20: Coal & Related Energy | B20: 18 | C20: 0.0556 | D20: 0.20509759 | E20: 0.29497551 | F20: 0.13126064 | G20: 1.242725 | H20: 1.2707581 | I20: 0.097254872 | J20: 0.5569226 | K20: 0.053524 | L20: 0.18396816 | M20: 0.086748106 | N20: 1.4739521 | O20: 1.3292639 | P20: 2.7528991 | Q20: 4.0368282 | R20: 1.790144 | S20: 91.912423 | T20: 0.061300783 | U20: 0.09304612 | V20: 0.01594012 | W20: 0.13283665 | X20: 0.29069216 | Y20: 0.15155666 | Z20: 0.15155666 | AA20: 0.20552884
A21: Computer Services | B21: 72 | C21: 0.10926474 | D21: 0.069781751 | E21: 0.24167411 | F21: 0.18859681 | G21: 0.85869751 | H21: 0.99732354 | I21: 0.084676883 | J21: 0.49612773 | K21: 0.050855 | L21: 0.22566036 | M21: 0.074175635 | N21: 3.5867521 | O21: 1.3742207 | P21: 12.610911 | Q21: 18.862943 | R21: 4.374578 | S21: 76.1322 | T21: 0.13853122 | U21: 0.01232575 | V21: 0.008234391 | W21: 0.23795589 | X21: 0.18772571 | Y21: 0.57072644 | Z21: 0.57072644 | AA21: 0.073034387
A22: Computers/Peripherals | B22: 36 | C22: 0.023118148 | D22: 0.210639 | E22: 0.37798197 | F22: 0.14611861 | G22: 1.1003544 | H22: 1.1329224 | I22: 0.090914429 | J22: 0.38898165 | K22: 0.050855 | L22: 0.057417447 | M22: 0.087884328 | N22: 1.9227871 | O22: 5.5117306 | P22: 21.831632 | Q22: 25.971419 | R22: 30.98288 | S22: 31.833391 | T22: -0.098693445 | U22: 0.03059766 | V22: 0.0090047013 | W22: 0.092441187 | X22: -1.234289e-05 | Y22: 0.17443899 | Z22: 0.17443899 | AA22: 0.21483117
A23: Construction Supplies | B23: 11 | C23: 0.093214286 | D23: 0.19042806 | E23: 0.16917185 | F23: 0.20587655 | G23: 0.85045702 | H23: 0.93781622 | I23: 0.081939546 | J23: 0.30297084 | K23: 0.050855 | L23: 0.13984163 | M23: 0.075814721 | N23: 1.0504345 | O23: 4.0960652 | P23: 14.937132 | Q23: 21.86743 | R23: 3.7678129 | S23: 63.097849 | T23: 0.22904316 | U23: 0.094668418 | V23: 0.034544526 | W23: 0.39648111 | X23: 0.17203971 | Y23: 0.1519331 | Z23: 0.1519331 | AA23: 0.18714102
A24: Diversified | B24: 23 | C24: 0.069406364 | D24: 0.22931749 | E24: 0.20395198 | F24: 0.17651836 | G24: 1.0923486 | H24: 1.1948544 | I24: 0.093763304 | J24: 0.52250503 | K24: 0.053524 | L24: 0.16074208 | M24: 0.085144265 | N24: 0.93313862 | O24: 2.4285334 | P24: 8.9346372 | Q24: 10.510497 | R24: 1.8732586 | S24: 13.800009 | T24: 0.050020771 | U24: 0.044830249 | V24: 0.04610103 | W24: 0.25080421 | X24: 0.15867711 | Y24: 0.081605407 | Z24: 0.081605407 | AA24: 0.23068357
A25: Drugs (Biotechnology) | B25: 572 | C25: 0.18950851 | D25: 0.010772126 | E25: 0.015551579 | F25: 0.16414119 | G25: 1.0890965 | H25: 1.1233547 | I25: 0.090474318 | J25: 0.61980948 | K25: 0.053524 | L25: 0.14082268 | M25: 0.083386527 | N25: 0.40681193 | O25: 6.888047 | P25: 13.519817 | Q25: NA | R25: 6.1352917 | S25: 30.391605 | T25: 0.099810417 | U25: 0.038231005 | V25: 0.03468872 | W25: NA | X25: -0.1159004 | Y25: 0.00088496674 | Z25: 0.00088496674 | AA25: 0.038302994
A26: Drugs (Pharmaceutical) | B26: 245 | C26: 0.41537667 | D26: 0.18160472 | E26: 0.13375271 | F26: 0.14924679 | G26: 0.94399769 | H26: 1.026962 | I26: 0.08604025 | J26: 0.65303414 | K26: 0.060879 | L26: 0.13828828 | M26: 0.080456031 | N26: 0.64296182 | O26: 5.0792398 | P26: 16.617974 | Q26: 27.42848 | R26: 5.1951083 | S26: 57.625877 | T26: 0.22369121 | U26: 0.053053464 | V26: 0.12973516 | W26: 0.85392632 | X26: 0.17320808 | Y26: 0.69958362 | Z26: 0.69958362 | AA26: 0.21327301
A27: Education | B27: 31 | C27: 0.041181875 | D27: 0.058152138 | E27: 0.059280308 | F27: 0.32156187 | G27: 1.1467394 | H27: 1.2251856 | I27: 0.095158535 | J27: 0.43781301 | K27: 0.050855 | L27: 0.1638311 | M27: 0.085817331 | N27: 1.2894169 | O27: 2.3038717 | P27: 10.798855 | Q27: 31.741208 | R27: 2.7160288 | S27: 34.57347 | T27: 0.090768336 | U27: 0.029240502 | V27: 0.0033245289 | W27: 0.9750398 | X27: 0.016746881 | Y27: 0.38078808 | Z27: 0.38078808 | AA27: 0.05162999
A28: Electrical Equipment | B28: 103 | C28: 0.1490783 | D28: 0.090010628 | E28: 0.13265964 | F28: 0.21670554 | G28: 1.1458435 | H28: 1.2410544 | I28: 0.095888501 | J28: 0.54423899 | K28: 0.053524 | L28: 0.17619595 | M28: 0.086066369 | N28: 1.4659763 | O28: 2.975718 | P28: 14.654555 | Q28: 28.892016 | R28: 2.923649 | S28: 24.688706 | T28: 0.28273149 | U28: 0.06163253 | V28: 0.098179239 | W28: 2.1463998 | X28: 0.23703236 | Y28: 0.17177866 | Z28: 0.17177866 | AA28: 0.095714676
A29: Electronics (Consumer & Office) | B29: 13 | C29: -0.06321 | D29: -0.00076434016 | E29: 0.0095426355 | F29: 0.69442344 | G29: 1.3029636 | H29: 1.2951788 | I29: 0.098378224 | J29: 0.39424155 | K29: 0.050855 | L29: 0.15486982 | M29: 0.089049334 | N29: 1.6732154 | O29: 0.84607344 | P29: 19.143942 | Q29: NA | R29: 1.903149 | S29: 38.632883 | T29: 0.15533543 | U29: 0.015568093 | V29: -0.0022079528 | W29: NA | X29: -0.066268001 | Y29: 0 | Z29: 0 | AA29: 0.0056724355
A30: Electronics (General) | B30: 129 | C30: 0.15823965 | D30: 0.094816606 | E30: 0.15114384 | F30: 0.22613288 | G30: 0.87720517 | H30: 0.9339546 | I30: 0.081761912 | J30: 0.42942644 | K30: 0.050855 | L30: 0.14673841 | M30: 0.075361085 | N30: 1.6768879 | O30: 2.1770119 | P30: 13.5896 | Q30: 22.109356 | R30: 3.2790177 | S30: 102.26028 | T30: 0.24013987 | U30: 0.040634673 | V30: 0.04116814 | W30: 0.70431641 | X30: 0.087976601 | Y30: 0.28526884 | Z30: 0.28526884 | AA30: 0.097970185
A31: Engineering/Construction | B31: 77 | C31: 0.065536667 | D31: 0.10360185 | E31: 0.18528356 | F31: 0.23687332 | G31: 0.92403959 | H31: 1.0580761 | I31: 0.087471502 | J31: 0.36589094 | K31: 0.050855 | L31: 0.21102554 | M31: 0.077061559 | N31: 2.0378501 | O31: 1.5719288 | P31: 11.036891 | Q31: 14.820564 | R31: 3.7460429 | S31: 36.142453 | T31: 0.18944889 | U31: 0.037420769 | V31: 0.028433402 | W31: 0.66623551 | X31: 0.21241763 | Y31: 0.2474936 | Z31: 0.2474936 | AA31: 0.10638181
A32: Entertainment | B32: 98 | C32: 0.15469138 | D32: 0.070067936 | E32: 0.075578912 | F32: 0.1999716 | G32: 0.86571919 | H32: 0.99455943 | I32: 0.084549734 | J32: 0.6118583 | K32: 0.053524 | L32: 0.22327359 | M32: 0.074634883 | N32: 1.1059341 | O32: 3.0674273 | P32: 16.372327 | Q32: 42.533399 | R32: 2.5929692 | S32: 31.168325 | T32: 0.038054347 | U32: 0.043745016 | V32: -0.022575917 | W32: -0.20650613 | X32: -0.0027275544 | Y32: 0.0034346523 | Z32: 0.0034346523 | AA32: 0.070525654
A33: Environmental & Waste Services | B33: 57 | C33: 0.13381231 | D33: 0.13553472 | E33: 0.29942484 | F33: 0.24029481 | G33: 0.7857302 | H33: 0.90699903 | I33: 0.080521956 | J33: 0.46066419 | K33: 0.050855 | L33: 0.17996903 | M33: 0.072894741 | N33: 2.2902045 | O33: 3.3833884 | P33: 15.000346 | Q33: 24.256339 | R33: 6.2476402 | S33: 31.275191 | T33: 0.10180592 | U33: 0.078381742 | V33: 0.064845914 | W33: 0.70099824 | X33: 0.21011635 | Y33: 0.36342219 | Z33: 0.36342219 | AA33: 0.13822317
A34: Farming/Agriculture | B34: 42 | C34: 0.2138381 | D34: 0.10178672 | E34: 0.17930588 | F34: 0.20906219 | G34: 0.76921334 | H34: 0.99162451 | I34: 0.084414727 | J34: 0.54139722 | K34: 0.053524 | L34: 0.31178335 | M34: 0.07061154 | N34: 1.8306605 | O34: 1.1055364 | P34: 8.9728446 | Q34: 10.56471 | R34: 2.7330368 | S34: 21.611875 | T34: 0.147225 | U34: 0.033959386 | V34: 0.02698979 | W34: 0.53012036 | X34: 0.27512097 | Y34: 0.17330467 | Z34: 0.17330467 | AA34: 0.10487455
A35: Financial Svcs. (Non-bank & Insurance) | B35: 192 | C35: 0.19123908 | D35: 0.15992934 | E35: 0.0096330086 | F35: 0.18997827 | G35: 0.3285147 | H35: 1.1400491 | I35: 0.091242258 | J35: 0.38102135 | K35: 0.050855 | L35: 0.77415085 | M35: 0.050134067 | N35: 0.06711915 | O35: 18.642987 | P35: 57.680539 | Q35: 77.494582 | R35: 3.3808152 | S35: 25.806044 | T35: 12.604429 | U35: 0.028409763 | V35: 0.027841238 | W35: 0.20105977 | X35: 0.21311644 | Y35: 0.31700384 | Z35: 0.31700384 | AA35: 0.16014177
A36: Food Processing | B36: 93 | C36: 0.064526667 | D36: 0.1049105 | E36: 0.16632788 | F36: 0.22335962 | G36: 0.56908998 | H36: 0.70750534 | I36: 0.071345245 | J36: 0.35521017 | K36: 0.050855 | L36: 0.26892857 | M36: 0.062415742 | N36: 1.7135539 | O36: 1.7282134 | P36: 11.437949 | Q36: 16.118698 | R36: 2.3044997 | S36: 30.031722 | T36: 0.077500137 | U36: 0.044694927 | V36: 0.033044851 | W36: 0.464556 | X36: 0.089774903 | Y36: 0.76422138 | Z36: 0.76422138 | AA36: 0.10671026
A37: Food Wholesalers | B37: 14 | C37: 0.18654 | D37: 0.022317778 | E37: 0.14961754 | F37: 0.244019 | G37: 0.73507045 | H37: 0.96571097 | I37: 0.083222705 | J37: 0.27303412 | K37: 0.050855 | L37: 0.30860321 | M37: 0.069310423 | N37: 8.019146 | O37: 0.4004885 | P37: 11.256367 | Q37: 18.051542 | R37: 4.102757 | S37: 26.104224 | T37: 0.057756763 | U37: 0.009305648 | V37: 0.0089900829 | W37: 0.47194526 | X37: 0.21114375 | Y37: 0.38161391 | Z37: 0.38161391 | AA37: 0.022183645
A38: Furn/Home Furnishings | B38: 31 | C38: 0.031330476 | D38: 0.058633421 | E38: 0.10314616 | F38: 0.34491478 | G38: 0.86118749 | H38: 1.1071062 | I38: 0.089726887 | J38: 0.4665248 | K38: 0.050855 | L38: 0.32226062 | M38: 0.073102868 | N38: 1.9608741 | O38: 1.0479459 | P38: 9.3651533 | Q38: 16.699225 | R38: 2.2525462 | S38: 19.580017 | T38: 0.1397377 | U38: 0.032449168 | V38: 0.072155188 | W38: 0.97314551 | X38: -0.065262791 | Y38: 0.0085617108 | Z38: 0.0085617108 | AA38: 0.061113859
A39: Green & Renewable Energy | B39: 17 | C39: 0.03735 | D39: 0.23439692 | E39: 0.041502731 | F39: 0.070572558 | G39: 0.55608602 | H39: 1.1067077 | I39: 0.089708555 | J39: 0.57336205 | K39: 0.053524 | L39: 0.58576062 | M39: 0.060675005 | N39: 0.19933189 | O39: 7.4719646 | P39: 12.631995 | Q39: 33.578775 | R39: 0.85442229 | S39: 39.872418 | T39: -0.27981625 | U39: 0.44316772 | V39: 0.20460876 | W39: 1.1590198 | X39: 0.10675101 | Y39: 0.25595302 | Z39: 0.25595302 | AA39: 0.21775571
A40: Healthcare Products | B40: 230 | C40: 0.179484 | D40: 0.13294968 | E40: 0.13081182 | F40: 0.20580163 | G40: 1.0054181 | H40: 1.0620799 | I40: 0.087655675 | J40: 0.52205535 | K40: 0.053524 | L40: 0.1123973 | M40: 0.082315379 | N40: 0.99169607 | O40: 5.1610657 | P40: 21.511373 | Q40: 36.992221 | R40: 4.629147 | S40: 61.891562 | T40: 0.25574202 | U40: 0.049018238 | V40: 0.020771729 | W40: 0.49512455 | X40: 0.083057979 | Y40: 0.41765479 | Z40: 0.41765479 | AA40: 0.1383574
A41: Healthcare Support Services | B41: 119 | C41: 0.12421877 | D41: 0.03918342 | E41: 0.45741028 | F41: 0.22529395 | G41: 0.94030625 | H41: 1.0326229 | I41: 0.086300654 | J41: 0.49525733 | K41: 0.050855 | L41: 0.21175231 | M41: 0.076102789 | N41: 12.880998 | O41: 0.60947097 | P41: 11.292454 | Q41: 15.455595 | R41: 3.3377128 | S41: 80.168287 | T41: -0.065254137 | U41: 0.0070548224 | V41: 0.019151403 | W41: 0.6275372 | X41: 0.1562031 | Y41: 0.29625921 | Z41: 0.29625921 | AA41: 0.038635102
... A48: Insurance (General) | B48: 21 | C48: 0.077637273 | D48: 0.1522733 | E48: 0.15653547 | F48: 0.2067199 | G48: 0.89461782 | H48: 1.0331486 | I48: 0.086324837 | J48: 0.40381704 | K48: 0.050855 | L48: 0.20592429 | M48: 0.076402666 | N48: 1.1879799 | O48: 2.6563933 | P48: 11.479314 | Q48: 17.340884 | R48: 2.8550545 | S48: 92.177288 | T48: -9.3256253e-05 | U48: 0.0092788699 | V48: -0.025998498 | W48: 0.37896875 | X48: 0.13524697 | Y48: 0.3275306 | Z48: 0.3275306 | AA48: 0.15267058
A49: Insurance (Life) | B49: 23 | C49: -0.000625 | D49: 0.00065616738 | E49: 0.001081681 | F49: 0.17734933 | G49: 0.53983112 | H49: 0.76576087 | I49: 0.074025 | J49: 0.30849685 | K49: 0.050855 | L49: 0.47983381 | M49: 0.056806764 | N49: 0.93697128 | O49: 1.5653336 | P49: 17.244921 | Q49: NA | R49: 1.6173451 | S49: 176.37863 | T49: 0.28615881 | U49: 0.0018122428 | V49: -0.025614436 | W49: NA | X49: 0.013240127 | Y49: 3.8120725 | Z49: 3.8120725 | AA49: 0.0012852923
A50: Insurance (Prop/Cas.) | B50: 50 | C50: 0.061676591 | D50: 0.074121043 | E50: 0.11118635 | F50: 0.18944213 | G50: 0.67520762 | H50: 0.73875776 | I50: 0.072782857 | J50: 0.27404178 | K50: 0.050855 | L50: 0.16235417 | M50: 0.067158648 | N50: 1.6945937 | O50: 1.3577626 | P50: 11.773605 | Q50: 15.658886 | R50: 2.2989009 | S50: 20.722521 | T50: -0.4093749 | U50: 0.0077982821 | V50: -0.0013016926 | W50: 0.28662294 | X50: 0.10356883 | Y50: 0.35133432 | Z50: 0.35133432 | AA50: 0.074917281
A51: Investments & Asset Management | B51: 334 | C51: 0.046036863 | D51: 0.14999164 | E51: 0.061639718 | F51: 0.18978292 | G51: 0.39129393 | H51: 0.45700547 | I51: 0.059822252 | J51: 0.1515089 | K51: 0.045043 | L51: 0.28742574 | M51: 0.052337685 | N51: 0.47398718 | O51: 5.4154547 | P51: 34.845251 | Q51: 34.896041 | R51: 2.0039088 | S51: 69.378833 | T51: NA | U51: 0.029725747 | V51: 0.061361472 | W51: 0.54669683 | X51: 0.13783635 | Y51: 0.42105651 | Z51: 0.42105651 | AA51: 0.14670723
A52: Machinery | B52: 103 | C52: 0.047126 | D52: 0.14779213 | E52: 0.24909385 | F52: 0.21716795 | G52: 0.93760955 | H52: 1.0260564 | I52: 0.085998596 | J52: 0.33444214 | K52: 0.050855 | L52: 0.14430986 | M52: 0.079092309 | N52: 1.8716132 | O52: 3.0699195 | P52: 15.461408 | Q52: 20.312384 | R52: 4.3438248 | S52: 26.951755 | T52: 0.25173396 | U52: 0.024425885 | V52: 0.064279581 | W52: 0.66768065 | X52: 0.19022656 | Y52: 0.36269981 | Z52: 0.36269981 | AA52: 0.15061466
A53: Metals & Mining | B53: 68 | C53: -0.013133333 | D53: 0.19621084 | E53: 0.24026697 | F53: 0.35286413 | G53: 0.91212435 | H53: 0.96247841 | I53: 0.083074007 | J53: 0.60559365 | K53: 0.053524 | L53: 0.13659353 | M53: 0.077209909 | N53: 1.2535014 | O53: 2.9379145 | P53: 10.355847 | Q53: 14.873774 | R53: 3.222492 | S53: 33.132598 | T53: 0.15321558 | U53: 0.13030145 | V53: 0.059114049 | W53: 0.63149629 | X53: 0.12165895 | Y53: 0.95470595 | Z53: 0.95470595 | AA53: 0.19557868
A54: Office Equipment & Services | B54: 17 | C54: 0.15850385 | D54: 0.072923118 | E54: 0.12926389 | F54: 0.44322557 | G54: 0.87643281 | H54: 1.1394185 | I54: 0.091213252 | J54: 0.30280063 | K54: 0.050855 | L54: 0.34456841 | M54: 0.072926317 | N54: 2.0704086 | O54: 1.1711023 | P54: 9.3426486 | Q54: 15.610563 | R54: 2.5364199 | S54: 249.15655 | T54: 0.091260792 | U54: 0.022936761 | V54: 0.01983353 | W54: 0.1658016 | X54: 0.026638 | Y54: 2.2516908 | Z54: 2.2516908 | AA54: 0.075269931
A55: Oil/Gas (Integrated) | B55: 4 | C55: 0.0176 | D55: 0.15595794 | E55: 0.1703977 | F55: 0.29512419 | G55: 0.64404501 | H55: 0.67065158 | I55: 0.069649973 | J55: 0.26444809 | K55: 0.050855 | L55: 0.11113223 | M55: 0.066148338 | N55: 1.3700897 | O55: 1.3474821 | P55: 6.2381265 | Q55: 8.5388407 | R55: 1.8169447 | S55: 8.0182129 | T55: 0.033696495 | U55: 0.073867786 | V55: -0.00021484268 | W55: -0.016712152 | X55: 0.19851814 | Y55: 0.37142297 | Z55: 0.37142297 | AA55: 0.15779317
A56: Oil/Gas (Production and Exploration) | B56: 166 | C56: 0.23280059 | D56: 0.3726584 | E56: 0.28405709 | F56: 0.20342464 | G56: 0.8214205 | H56: 0.92989874 | I56: 0.081575342 | J56: 0.46310335 | K56: 0.050855 | L56: 0.18884247 | M56: 0.073373141 | N56: 0.7985633 | O56: 2.6500043 | P56: 4.6683778 | Q56: 6.9825673 | R56: 1.943123 | S56: 16.325943 | T56: 0.0099951289 | U56: 0.30047597 | V56: 0.16046403 | W56: 0.50395049 | X56: 0.310948 | Y56: 0.31272316 | Z56: 0.31272316 | AA56: 0.37686234
A57: Oil/Gas Distribution | B57: 24 | C57: 0.27451533 | D57: 0.37953024 | E57: 0.20602083 | F57: 0.18244448 | G57: 0.52912157 | H57: 0.79075215 | I57: 0.075174599 | J57: 0.32547547 | K57: 0.050855 | L57: 0.41252097 | M57: 0.059897566 | N57: 0.59413677 | O57: 3.5771916 | P57: 7.3117668 | Q57: 9.2923198 | R57: 2.3169738 | S57: 18.41284 | T57: 0.025338522 | U57: 0.16531344 | V57: 0.13121071 | W57: 0.40284568 | X57: 0.42406084 | Y57: 0.39844096 | Z57: 0.39844096 | AA57: 0.38210569
A58: Oilfield Svcs/Equip. | B58: 100 | C58: 0.077372121 | D58: 0.087209149 | E58: 0.28021407 | F58: 0.21837987 | G58: 0.85290174 | H58: 0.97955003 | I58: 0.083859301 | J58: 0.43728736 | K58: 0.050855 | L58: 0.24322695 | M58: 0.072739439 | N58: 3.5534627 | O58: 0.6282383 | P58: 5.4241304 | Q58: 7.0794353 | R58: 1.9840962 | S58: 70.298228 | T58: 0.063418447 | U58: 0.023634819 | V58: 0.0057629495 | W58: 0.15485673 | X58: 0.29646914 | Y58: 0.18808725 | Z58: 0.18808725 | AA58: 0.088462457
A59: Packaging & Container | B59: 11 | C59: 0.046281 | D59: 0.10136344 | E59: 0.1446895 | F59: 0.21436678 | G59: 0.59401446 | H59: 0.86758968 | I59: 0.078709125 | J59: 0.22797403 | K59: 0.045043 | L59: 0.41684588 | M59: 0.059981542 | N59: 1.8070981 | O59: 1.4851152 | P59: 9.2815278 | Q59: 14.548467 | R59: 2.9619163 | S59: 17.370818 | T59: 0.076715871 | U59: 0.06763321 | V59: 0.038600393 | W59: 0.70321265 | X59: 0.19622776 | Y59: 0.25848829 | Z59: 0.25848829 | AA59: 0.10208646
A60: Paper/Forest Products | B60: 7 | C60: 0.038425 | D60: 0.099619899 | E60: 0.18901374 | F60: 0.30911701 | G60: 1.5902926 | H60: 1.9382232 | I60: 0.12795827 | J60: 0.43036487 | K60: 0.050855 | L60: 0.2720368 | M60: 0.10352473 | N60: 2.1382237 | O60: 1.0399789 | P60: 7.0633687 | Q60: 10.30993 | R60: 2.420836 | S60: 19.990268 | T60: 0.12896672 | U60: 0.075908106 | V60: 0.050747159 | W60: 0.9970294 | X60: 0.15165444 | Y60: 0.27578599 | Z60: 0.27578599 | AA60: 0.10140988
A61: Power | B61: 50 | C61: 0.05328 | D61: 0.16292989 | E61: 0.057838809 | F61: 0.16140323 | G61: 0.38850619 | H61: 0.65062742 | I61: 0.068728861 | J61: 0.2039437 | K61: 0.045043 | L61: 0.48166098 | M61: 0.051896442 | N61: 0.41143198 | O61: 3.7153854 | P61: 11.691846 | Q61: 22.33991 | R61: 1.7113226 | S61: 23.191582 | T61: 0.082551594 | U61: 0.3395409 | V61: 0.22702952 | W61: 1.7342756 | X61: 0.086033634 | Y61: 0.76674407 | Z61: 0.76674407 | AA61: 0.1628701
A62: Precious Metals | B62: 61 | C62: 0.116358 | D62: 0.094815348 | E62: 0.046929693 | F62: 0.22878494 | G62: 0.83008391 | H62: 0.86895094 | I62: 0.078771743 | J62: 0.63609474 | K62: 0.053524 | L62: 0.13198989 | M62: 0.07367314 | N62: 0.50505304 | O62: 3.9558021 | P62: 13.009573 | Q62: 40.056478 | R62: 2.0363466 | S62: 34.232639 | T62: 0.098325052 | U62: 0.2540797 | V62: 0.095405976 | W62: 1.4626232 | X62: -0.02334197 | Y62: 0.0088351217 | Z62: 0.0088351217 | AA62: 0.094817432
A63: Publishing & Newspapers | B63: 13 | C63: 0.018868889 | D63: 0.075860536 | E63: 0.11743909 | F63: 0.33496727 | G63: 0.80705437 | H63: 0.91822392 | I63: 0.081038301 | J63: 0.31017152 | K63: 0.050855 | L63: 0.22320484 | M63: 0.071463471 | N63: 1.8067191 | O63: 1.6155965 | P63: 11.874912 | Q63: 22.460692 | R63: 2.0327329 | S63: 33.96661 | T63: 0.11799857 | U63: 0.037843627 | V63: -0.014497011 | W63: -0.12400404 | X63: 0.02538476 | Y63: 0.96086621 | Z63: 0.96086621 | AA63: 0.072628248
... A66: Real Estate (General/Diversified) | B66: 11 | C66: 0.090804 | D66: 0.16131826 | E66: 0.053122204 | F66: 0.17400095 | G66: 0.51252675 | H66: 0.56357224 | I66: 0.064724323 | J66: 0.35907097 | K66: 0.050855 | L66: 0.2417147 | M66: 0.058298803 | N66: 0.37242041 | O66: 4.7788406 | P66: 18.009159 | Q66: 28.438668 | R66: 1.2470692 | S66: 33.226231 | T66: 2.0129995 | U66: 0.028403729 | V66: -0.051359512 | W66: -0.59412378 | X66: 0.091092056 | Y66: 0.24923182 | Z66: 0.24923182 | AA66: 0.16435429
A67: Real Estate (Operations & Services) | B67: 60 | C67: 0.054392667 | D67: -0.0028357036 | E67: 0.0006711916 | F67: 0.18035278 | G67: 0.88284639 | H67: 1.0801189 | I67: 0.088485469 | J67: 0.44192229 | K67: 0.050855 | L67: 0.30827148 | M67: 0.072965782 | N67: 1.4452431 | O67: 1.507422 | P67: 14.981931 | Q67: NA | R67: 2.8721502 | S67: 104.23605 | T67: 0.09693828 | U67: 0.013030956 | V67: -0.011660648 | W67: NA | X67: -0.082699454 | Y67: 0.0076188461 | Z67: 0.0076188461 | AA67: 0.00048652777
A68: Recreation | B68: 55 | C68: 0.10951862 | D68: 0.096590437 | E68: 0.095367542 | F68: 0.27908974 | G68: 0.84887801 | H68: 1.1712869 | I68: 0.092679199 | J68: 0.44295221 | K68: 0.050855 | L68: 0.36938218 | M68: 0.072533852 | N68: 1.283185 | O68: 1.8421119 | P68: 9.9873894 | Q68: 21.717962 | R68: 3.4596231 | S68: 27.700116 | T68: 0.18037794 | U68: 0.07111561 | V68: 0.032100923 | W68: 0.56158343 | X68: 0.02562663 | Y68: 1.9958513 | Z68: 1.9958513 | AA68: 0.081009095
A69: Reinsurance | B69: 1 | C69: 0.0695 | D69: 0.096556719 | E69: 0.3011691 | F69: 0.2295302 | G69: 0.60985092 | H69: 0.65514403 | I69: 0.068936625 | J69: 0.17094029 | K69: 0.045043 | L69: 0.29842459 | M69: 0.058445695 | N69: 4.0484415 | O69: 0.68963176 | P69: 7.2830308 | Q69: 7.1425014 | R69: 1.307764 | S69: 9.34461 | T69: 0.17093827 | U69: 0.0014486294 | V69: 0.043263873 | W69: 0.75607995 | X69: 0.31234602 | Y69: 0.18930762 | Z69: 0.18930762 | AA69: 0.096553255
A70: Restaurant/Dining | B70: 64 | C70: 0.06796 | D70: 0.15800226 | E70: 0.19557553 | F70: 0.19967846 | G70: 1.0243277 | H70: 1.1945773 | I70: 0.093750557 | J70: 0.35372311 | K70: 0.050855 | L70: 0.20462609 | M70: 0.082371442 | N70: 1.619689 | O70: 4.1943616 | P70: 16.59891 | Q70: 29.333021 | R70: NA | S70: 94.189098 | T70: 0.0086042888 | U70: 0.057944026 | V70: 0.035722685 | W70: 0.34511083 | X70: NA | Y70: 0.53075599 | Z70: 0.53075599 | AA70: 0.13614064
A71: Retail (Automotive) | B71: 30 | C71: 0.17498636 | D71: 0.061756206 | E71: 0.13195481 | F71: 0.23751486 | G71: 1.0587643 | H71: 1.494496 | I71: 0.10754681 | J71: 0.46787575 | K71: 0.050855 | L71: 0.36513247 | M71: 0.082204588 | N71: 2.6698338 | O71: 1.049476 | P71: 11.625721 | Q71: 17.424466 | R71: 6.9701147 | S71: 17.888728 | T71: 0.099833698 | U71: 0.019066371 | V71: 0.021762603 | W71: 0.71346117 | X71: 0.47328546 | Y71: 0.057941597 | Z71: 0.057941597 | AA71: 0.05713005
A72: Retail (Building Supply) | B72: 16 | C72: 0.089053846 | D72: 0.12513816 | E72: 0.39426101 | F72: 0.24040749 | G72: 1.7041532 | H72: 1.9381786 | I72: 0.12795621 | J72: 0.45210583 | K72: 0.050855 | L72: 0.16613035 | M72: 0.11303522 | N72: 3.6418166 | O72: 2.1699325 | P72: 13.331902 | Q72: 17.190761 | R72: NA | S72: 27.870807 | T72: 0.084696828 | U72: 0.024278468 | V72: 0.0084849636 | W72: 0.023337338 | X72: NA | Y72: 0.46644742 | Z72: 0.46644742 | AA72: 0.12384325
A73: Retail (Distributors) | B73: 62 | C73: 0.058054595 | D73: 0.11953214 | E73: 0.18608588 | F73: 0.23449867 | G73: 0.90932555 | H73: 1.1060427 | I73: 0.089677964 | J73: 0.3773575 | K73: 0.050855 | L73: 0.24408909 | M73: 0.077098414 | N73: 1.8156574 | O73: 1.8130781 | P73: 11.632873 | Q73: 13.82275 | R73: 4.0303872 | S73: 28.908314 | T73: 0.17415505 | U73: 0.062556536 | V73: 0.092151064 | W73: 1.0375036 | X73: 0.25451623 | Y73: 0.25220531 | Z73: 0.25220531 | AA73: 0.12168553
A74: Retail (General) | B74: 26 | C74: 0.18063053 | D74: 0.044133968 | E74: 0.098929938 | F74: 0.21721237 | G74: 1.1710629 | H74: 1.2466771 | I74: 0.096147144 | J74: 0.38283199 | K74: 0.050855 | L74: 0.11835252 | M74: 0.089282001 | N74: 2.4115594 | O74: 1.5688483 | P74: 16.631296 | Q74: 38.46583 | R74: 7.2422855 | S74: 29.844016 | T74: 0.0076876136 | U74: 0.052009665 | V74: 0.022820228 | W74: 0.79447834 | X74: 0.19550145 | Y74: 0.21744723 | Z74: 0.21744723 | AA74: 0.046967035
A75: Retail (Grocery and Food) | B75: 14 | C75: 0.0659125 | D75: 0.024225597 | E75: 0.10989245 | F75: 0.22911929 | G75: 0.36476115 | H75: 0.49360806 | I75: 0.061505971 | J75: 0.25647927 | K75: 0.050855 | L75: 0.3583171 | M75: 0.053133992 | N75: 4.7564464 | O75: 0.41252131 | P75: 6.3798048 | Q75: 19.804921 | R75: 2.9031713 | S75: 16.757683 | T75: -0.0024323899 | U75: 0.026633515 | V75: 0.013260602 | W75: 1.1428223 | X75: 0.14777603 | Y75: 0.36924016 | Z75: 0.36924016 | AA75: 0.026473632
A76: Retail (REITs) | B76: 28 | C76: 0.041101852 | D76: 0.36745097 | E76: 0.044585628 | F76: 0.042019304 | G76: 0.7866747 | H76: 1.1208678 | I76: 0.090359917 | J76: 0.20718002 | K76: 0.045043 | L76: 0.37042377 | M76: 0.069402205 | N76: 0.13065981 | O76: 12.151989 | P76: 17.431874 | Q76: 34.71101 | R76: 1.935672 | S76: 74.090504 | T76: -0.098708987 | U76: 0.051678639 | V76: -0.26525962 | W76: -0.81803643 | X76: 0.065230632 | Y76: 1.5557235 | Z76: 1.5557235 | AA76: 0.3500971
A77: Retail (Special Lines) | B77: 105 | C77: 0.12071968 | D77: 0.046172631 | E77: 0.13499346 | F77: 0.24714983 | G77: 0.97306922 | H77: 1.1814057 | I77: 0.093144664 | J77: 0.44007854 | K77: 0.050855 | L77: 0.26552005 | M77: 0.078540155 | N77: 3.1090001 | O77: 0.98357084 | P77: 9.3415486 | Q77: 20.31757 | R77: 4.7786066 | S77: 48.788377 | T77: 0.050599262 | U77: 0.025889269 | V77: 0.026622349 | W77: 0.55230156 | X77: 0.096438784 | Y77: 0.87042655 | Z77: 0.87042655 | AA77: 0.047981611
A78: Rubber& Tires | B78: 3 | C78: 0.0902 | D78: 0.018445123 | E78: 0.031240927 | F78: #DIV/0! | G78: 0.26316933 | H78: 0.67451977 | I78: 0.069827909 | J78: 0.40772527 | K78: 0.050855 | L78: 0.70174055 | M78: 0.047592095 | N78: 1.4484048 | O78: 0.62828692 | P78: 7.9475866 | Q78: 29.777573 | R78: 0.78946449 | S78: #DIV/0! | T78: 0.10694212 | U78: 0.054186799 | V78: 0.0070628985 | W78: -0.32002681 | X78: -0.099980552 | Y78: #DIV/0! | Z78: #DIV/0! | AA78: 0.021569197
A79: Semiconductor | B79: 63 | C79: 0.064411628 | D79: 0.19711976 | E79: 0.11368358 | F79: 0.093092671 | G79: 1.4602446 | H79: 1.4952412 | I79: 0.10758109 | J79: 0.41471434 | K79: 0.050855 | L79: 0.057008103 | M79: 0.10362246 | N79: 0.58072921 | O79: 10.596723 | P79: 31.594447 | Q79: 53.315004 | R79: 7.3817915 | S79: 82.750516 | T79: 0.22403023 | U79: 0.17000864 | V79: 0.068986976 | W79: 0.49863224 | X79: 0.12611876 | Y79: 0.48873979 | Z79: 0.48873979 | AA79: 0.20539851
A80: Semiconductor Equip | B80: 30 | C80: 0.0992575 | D80: 0.24186751 | E80: 0.25683632 | F80: 0.12268561 | G80: 1.5077651 | H80: 1.5279822 | I80: 0.10908718 | J80: 0.37040143 | K80: 0.050855 | L80: 0.072165764 | M80: 0.10396731 | N80: 1.1649954 | O80: 5.2442582 | P80: 18.178195 | Q80: 21.529733 | R80: 8.1009759 | S80: 163.51842 | T80: 0.34562808 | U80: 0.050796555 | V80: 0.026035463 | W80: 0.13881169 | X80: 0.32890668 | Y80: 0.20089989 | Z80: 0.20089989 | AA80: 0.25001236
A81: Shipbuilding & Marine | B81: 8 | C81: -0.0068033333 | D81: 0.1065074 | E81: 0.092351395 | F81: 0.18850961 | G81: 0.68659497 | H81: 0.81083614 | I81: 0.076098463 | J81: 0.45074725 | K81: 0.050855 | L81: 0.22942152 | M81: 0.067390261 | N81: 0.82933964 | O81: 1.7047397 | P81: 8.3847206 | Q81: 14.228088 | R81: 1.364263 | S81: 24.757088 | T81: 0.11299865 | U81: 0.10241615 | V81: 0.040299198 | W81: 0.50270712 | X81: 0.078173177 | Y81: 0.29337529 | Z81: 0.29337529 | AA81: 0.11940028
A82: Shoe | B82: 13 | C82: 0.1149125 | D82: 0.12199139 | E82: 0.24043081 | F82: 0.17460546 | G82: 1.2730955 | H82: 1.2915789 | I82: 0.098212631 | J82: 0.36279909 | K82: 0.050855 | L82: 0.080114408 | M82: 0.093400048 | N82: 2.2253945 | O82: 2.8863045 | P82: 18.953734 | Q82: 23.682872 | R82: 8.7107691 | S82: 19.768872 | T82: 0.19614446 | U82: 0.0085762705 | V82: -0.0052012498 | W82: -0.20182595 | X82: 0.29903215 | Y82: 0.32261311 | Z82: 0.32261311 | AA82: 0.1218072
A83: Software (Entertainment) | B83: 84 | C83: 0.17412533 | D83: 0.26804849 | E83: 0.19944873 | F83: 0.16568125 | G83: 1.1136805 | H83: 1.1083306 | I83: 0.089783206 | J83: 0.52789322 | K83: 0.053524 | L83: 0.030561495 | M83: 0.088266127 | N83: 0.7438485 | O83: 6.0250177 | P83: 17.157816 | Q83: 22.221744 | R83: 6.2430547 | S83: 30.81807 | T83: 0.047763248 | U83: 0.12672459 | V83: 0.087039144 | W83: 0.46794431 | X83: 0.23255939 | Y83: 0.0025063969 | Z83: 0.0025063969 | AA83: 0.28167769
A84: Software (Internet) | B84: 35 | C84: 0.22244545 | D84: -0.033594817 | E84: -0.0048109533 | F84: 0.17878408 | G84: 1.5117563 | H84: 1.6160843 | I84: 0.11313988 | J84: 0.65221603 | K84: 0.060879 | L84: 0.10698654 | M84: 0.10592036 | N84: 0.63612336 | O84: 8.3828737 | P84: 19.329879 | Q84: NA | R84: 9.0021141 | S84: 35.177443 | T84: 0.096695754 | U84: 0.055778078 | V84: 0.028310083 | W84: NA | X84: -0.14540651 | Y84: 0 | Z84: 0 | AA84: -0.0083175074
A85: Software (System & Application) | B85: 351 | C85: 0.15903338 | D85: 0.25298656 | E85: 0.2322439 | F85: 0.17853262 | G85: 1.272459 | H85: 1.2939647 | I85: 0.098322378 | J85: 0.5208649 | K85: 0.053524 | L85: 0.05841338 | M85: 0.094923923 | N85: 0.92035565 | O85: 10.721552 | P85: 28.433139 | Q85: 39.481991 | R85: 11.028708 | S85: 88.724573 | T85: 0.11204453 | U85: 0.08674641 | V85: 0.059162107 | W85: 0.36380231 | X85: 0.24441835 | Y85: 0.27220591 | Z85: 0.27220591 | AA85: 0.26295962
A86: Steel | B86: 29 | C86: 0.0787332 | D86: 0.12104449 | E86: 0.22180836 | F86: 0.19962963 | G86: 1.0774711 | H86: 1.1263717 | I86: 0.090613099 | J86: 0.38102205 | K86: 0.050855 | L86: 0.16794349 | M86: 0.081800794 | N86: 2.1668462 | O86: 0.94134699 | P86: 5.9315455 | Q86: 7.7262016 | R86: 1.7639738 | S86: 14.5417 | T86: 0.1902387 | U86: 0.062015491 | V86: 0.042105107 | W86: 0.15698783 | X86: 0.22194709 | Y86: 0.12471208 | Z86: 0.12471208 | AA86: 0.12145782
A87: Telecom (Wireless) | B87: 13 | C87: 0.092977143 | D87: 0.16792801 | E87: 0.065483784 | F87: 0.24652435 | G87: 0.74731172 | H87: 1.0873614 | I87: 0.088818623 | J87: 0.60305869 | K87: 0.053524 | L87: 0.39084318 | M87: 0.069794087 | N87: 0.48441213 | O87: 3.5147102 | P87: 9.0095139 | Q87: 23.512661 | R87: 2.532248 | S87: 67.853833 | T87: 0.062680579 | U87: 0.15310948 | V87: -0.0029960671 | W87: 0.55104505 | X87: 0.097395978 | Y87: 0.1104528 | Z87: 0.1104528 | AA87: 0.14947762
A88: Telecom. Equipment | B88: 66 | C88: 0.09616449 | D88: 0.19578374 | E88: 0.28182162 | F88: 0.16906478 | G88: 1.045648 | H88: 1.0805072 | I88: 0.088503331 | J88: 0.46622145 | K88: 0.050855 | L88: 0.10245105 | M88: 0.083343683 | N88: 1.446427 | O88: 3.6067815 | P88: 13.979069 | Q88: 17.645248 | R88: 5.1449679 | S88: 70.491277 | T88: 0.23092381 | U88: 0.027789569 | V88: 0.039799623 | W88: 0.36669384 | X88: 0.24550541 | Y88: 0.46084833 | Z88: 0.46084833 | AA88: 0.20713525
A89: Telecom. Services | B89: 42 | C89: 0.13169957 | D89: 0.20861579 | E89: 0.11796483 | F89: 0.21774221 | G89: 0.41411156 | H89: 0.78450471 | I89: 0.074887217 | J89: 0.50416714 | K89: 0.053524 | L89: 0.55538379 | M89: 0.055590842 | N89: 0.60200338 | O89: 2.3574881 | P89: 6.178012 | Q89: 11.21287 | R89: 1.2986532 | S89: 77.102401 | T89: -0.032235362 | U89: 0.1671517 | V89: 0.024292122 | W89: 0.20122305 | X89: -0.0034470942 | Y89: 0.0016337691 | Z89: 0.0016337691 | AA89: 0.20983809
A90: Tobacco | B90: 16 | C90: 0.34968889 | D90: 0.40818351 | E90: 0.8036056 | F90: 0.21139682 | G90: 0.98708023 | H90: 1.2232908 | I90: 0.095071378 | J90: 0.48000268 | K90: 0.050855 | L90: 0.25873063 | M90: 0.08034181 | N90: 2.1763696 | O90: 4.7953049 | P90: 10.842664 | Q90: 11.67413 | R90: NA | S90: 17.746085 | T90: 0.15300181 | U90: 0.027084959 | V90: 0.33428394 | W90: 1.1763987 | X90: NA | Y90: 0.8798406 | Z90: 0.8798406 | AA90: 0.41002252
A91: Transportation | B91: 110 | C91: 0.073925854 | D91: 0.085076188 | E91: 0.1608839 | F91: 0.22120376 | G91: 0.8446387 | H91: 0.99780729 | I91: 0.084699135 | J91: 0.56203928 | K91: 0.053524 | L91: 0.23574453 | M91: 0.07419527 | N91: 2.0142049 | O91: 1.8733601 | P91: 12.825656 | Q91: 21.707095 | R91: 5.3511884 | S91: 26.994752 | T91: 0.077146823 | U91: 0.079332478 | V91: 0.04791948 | W91: 0.72064766 | X91: 0.22056295 | Y91: 1.0930209 | Z91: 1.0930209 | AA91: 0.085810767
A92: Transportation (Railroads) | B92: 4 | C92: 0.0249 | D92: 0.35113467 | E92: 0.14261953 | F92: 0.22982533 | G92: 0.85599781 | H92: 1.0172724 | I92: 0.08559453 | J92: 0.22277358 | K92: 0.045043 | L92: 0.21142467 | M92: 0.074640136 | N92: 0.49324628 | O92: 6.6295597 | P92: 14.31968 | Q92: 18.966126 | R92: 6.9113811 | S92: 22.288253 | T92: 0.022557472 | U92: 0.15703202 | V92: 0.055988647 | W92: 0.22178443 | X92: 0.31677945 | Y92: 0.43519528 | Z92: 0.43519528 | AA92: 0.34954739
A93: Trucking | B93: 22 | C93: 0.061907222 | D93: 0.084934052 | E93: 0.12748742 | F93: 0.25564934 | G93: 1.0291549 | H93: 1.1484075 | I93: 0.091626743 | J93: 0.28328549 | K93: 0.050855 | L93: 0.16632305 | M93: 0.082730873 | N93: 1.84241 | O93: 1.8055802 | P93: 10.57224 | Q93: 20.589003 | R93: 3.5846943 | S93: 36.079463 | T93: 0.067480207 | U93: 0.1493425 | V93: 0.09098037 | W93: 1.2178075 | X93: 0.12974692 | Y93: 0.17362719 | Z93: 0.17362719 | AA93: 0.086910837
A94: Utility (General) | B94: 14 | C94: 0.043405 | D94: 0.21805081 | E94: 0.0647314 | F94: 0.16016204 | G94: 0.35679519 | H94: 0.58043231 | I94: 0.065499886 | J94: 0.14927275 | K94: 0.045043 | L94: 0.45897703 | M94: 0.05094222 | N94: 0.34799061 | O94: 4.1288173 | P94: 11.696398 | Q94: 19.078267 | R94: 1.6473566 | S94: 17.483751 | T94: 0.13370152 | U94: 0.38606605 | V94: 0.25906871 | W94: 1.505257 | X94: 0.11153677 | Y94: 0.58882822 | Z94: 0.58882822 | AA94: 0.21642128
A95: Utility (Water) | B95: 13 | C95: 0.10849091 | D95: 0.30791616 | E95: 0.067989566 | F95: 0.14918991 | G95: 0.52231147 | H95: 0.71396343 | I95: 0.071642318 | J95: 0.2819872 | K95: 0.050855 | L95: 0.33727313 | M95: 0.060343308 | N95: 0.2492474 | O95: 7.8955738 | P95: 16.861059 | Q95: 25.637409 | R95: 2.3031518 | S95: 34.884505 | T95: 0.11350574 | U95: 0.53908431 | V95: 0.401751 | W95: 1.495051 | X95: 0.15979159 | Y95: 0.60585496 | Z95: 0.39244973 | AA95: 0.30680998

Sheet Industry Average Beta (Global)
A1: Industry Name | B1: Number of firms | C1: Annual Average Revenue growth - Last 5 years | D1: Pre-tax Operating Margin (Unadjusted) | E1: After-tax ROC | F1: Average effective tax rate | G1: Unlevered Beta | H1: Equity (Levered) Beta | I1: Cost of equity | J1: Std deviation in stock prices | K1: Pre-tax cost of debt | L1: Market Debt/Capital | M1: Cost of capital | N1: Sales/Capital | O1: EV/Sales | P1: EV/EBITDA | Q1: EV/EBIT | R1: Price/Book | S1: Trailing PE | T1: Non-cash WC as % of Revenues | U1: Cap Ex as % of Revenues | V1: Net Cap Ex as % of Revenues | W1: Reinvestment Rate | X1: ROE | Y1: Dividend Payout Ratio | Z1: Equity Reinvestment Rate | AA1: Pre-tax Operating Margin (Lease & R&D adjusted)
A2: Advertising | B2: 391 | C2: 0.060678733 | D2: 0.07893289 | E2: 0.22318415 | F2: 0.24671862 | G2: 1.2309227 | H2: 1.3525261 | I2: 0.12549692 | J2: 0.38891118 | K2: 0.064355 | L2: 0.23971066 | M2: 0.10693454 | N2: 3.2269278 | O2: 1.5597582 | P2: 11.941458 | Q2: 18.468198 | R2: 2.5969841 | S2: 53.676864 | T2: -0.025138145 | U2: 0.017243189 | V2: 0.0017319182 | W2: 0.25114078 | X2: 0.07535655 | Y2: 0.7601358 | Z2: 0.7601358 | AA2: 0.080659837
A3: Aerospace/Defense | B3: 289 | C3: 0.09309568 | D3: 0.079923618 | E3: 0.13938187 | F3: 0.16177288 | G3: 0.90338326 | H3: 0.98430307 | I3: 0.10189383 | J3: 0.35101019 | K3: 0.064355 | L3: 0.17197349 | M3: 0.09263589 | N3: 1.832262 | O3: 2.2616279 | P3: 17.907632 | Q3: 27.409854 | R3: 4.467579 | S3: 77.145602 | T3: 0.38805334 | U3: 0.035404722 | V3: 0.021536227 | W3: 0.40167246 | X3: 0.14143383 | Y3: 0.44958156 | Z3: 0.44958156 | AA3: 0.083597009
A4: Air Transport | B4: 155 | C4: 0.02483496 | D4: 0.072832786 | E4: 0.076090439 | F4: 0.18079323 | G4: 0.81040341 | H4: 1.2872128 | I4: 0.12131034 | J4: 0.30061794 | K4: 0.064355 | L4: 0.50981682 | M4: 0.083966244 | N4: 1.1974038 | O4: 1.4160607 | P4: 8.4210655 | Q4: 18.088757 | R4: 2.4000358 | S4: 96.631584 | T4: -0.028523145 | U4: 0.09872859 | V4: 0.034606502 | W4: 0.30360301 | X4: 0.19646294 | Y4: 0.25209575 | Z4: 0.25209575 | AA4: 0.072336877
A5: Apparel | B5: 1152 | C5: 0.029902593 | D5: 0.14639551 | E5: 0.213148 | F5: 0.25306546 | G5: 0.77946573 | H5: 0.8327733 | I5: 0.092180769 | J5: 0.32723669 | K5: 0.064355 | L5: 0.14561415 | M5: 0.085756206 | N5: 1.6689116 | O5: 2.4393038 | P5: 13.19284 | Q5: 16.125325 | R5: 3.6292339 | S5: 42.488215 | T5: 0.22428068 | U5: 0.051634121 | V5: 0.034267563 | W5: 0.52147231 | X5: 0.17062717 | Y5: 0.4237836 | Z5: 0.4237836 | AA5: 0.14804138
A6: Auto & Truck | B6: 165 | C6: 0.081321569 | D6: 0.075594609 | E6: 0.086167571 | F6: 0.21881135 | G6: 1.1030216 | H6: 1.3606863 | I6: 0.12602 | J6: 0.36463723 | K6: 0.064355 | L6: 0.35609741 | M6: 0.098258755 | N6: 1.2339367 | O6: 1.2010454 | P6: 9.8422842 | Q6: 15.278939 | R6: 1.6673634 | S6: 42.264064 | T6: 0.0212791 | U6: 0.060660184 | V6: 0.03461175 | W6: 0.70382133 | X6: 0.14502972 | Y6: 0.26552011 | Z6: 0.26552011 | AA6: 0.077383713
A7: Auto Parts | B7: 761 | C7: 0.068719932 | D7: 0.050112865 | E7: 0.069513427 | F7: 0.2407743 | G7: 1.2090552 | H7: 1.3055576 | I7: 0.12248625 | J7: 0.30389336 | K7: 0.064355 | L7: 0.23444227 | M7: 0.10503766 | N7: 1.730294 | O7: 0.82655482 | P7: 8.5539997 | Q7: 15.807322 | R7: 1.4984185 | S7: 130.48898 | T7: 0.11764661 | U7: 0.053688521 | V7: 0.038473888 | W7: 1.1613589 | X7: 0.0757882 | Y7: 0.41658239 | Z7: 0.41658239 | AA7: 0.048274278
A8: Bank (Money Center) | B8: 607 | C8: 0.1202628 | D8: 0.0028364376 | E8: 0.00038710601 | F8: 0.18590464 | G8: 0.42062216 | H8: 0.87661223 | I8: 0.094990844 | J8: 0.21280779 | K8: 0.058543 | L8: 0.74422548 | M8: 0.05683371 | N8: 0.15911568 | O8: 6.7699193 | P8: 189.89899 | Q8: NA | R8: 0.84234957 | S8: 14.729078 | T8: NA | U8: 0.033254364 | V8: 0.050798671 | W8: 19.575019 | X8: 0.12654306 | Y8: 0.30695422 | Z8: 0.30695422 | AA8: 0.0031046483
A9: Banks (Regional) | B9: 881 | C9: 0.084004418 | D9: -0.00010767473 | E9: -0.0001474166 | F9: 0.1917831 | G9: 0.28391224 | H9: 0.52308361 | I9: 0.072329659 | J9: 0.18295557 | K9: 0.058543 | L9: 0.71756531 | M9: 0.051800297 | N9: 0.17196644 | O9: 5.8371202 | P9: NA | Q9: NA | R9: 0.74498598 | S9: 28.980754 | T9: NA | U9: 0.029584981 | V9: -0.042662563 | W9: NA | X9: 0.098266835 | Y9: 0.29089509 | Z9: 0.29089509 | AA9: -0.0010386505
A10: Beverage (Alcoholic) | B10: 220 | C10: 0.082478475 | D10: 0.21689012 | E10: 0.16067498 | F10: 0.21945068 | G10: 0.68658211 | H10: 0.74556336 | I10: 0.086590611 | J10: 0.27489398 | K10: 0.064355 | L10: 0.15736772 | M10: 0.080527186 | N10: 0.8820906 | O10: 3.6455195 | P10: 13.890019 | Q10: 16.68246 | R10: 3.1761893 | S10: 49.806145 | T10: 0.10799586 | U10: 0.051080513 | V10: 0.029178936 | W10: 0.39674912 | X10: 0.16528004 | Y10: 0.4461457 | Z10: 0.4461457 | AA10: 0.21737063
A11: Beverage (Soft) | B11: 100 | C11: 0.13106444 | D11: 0.16712852 | E11: 0.26082973 | F11: 0.20408116 | G11: 0.65633361 | H11: 0.70711616 | I11: 0.084126146 | J11: 0.32238073 | K11: 0.064355 | L11: 0.14148945 | M11: 0.079023211 | N11: 1.7627547 | O11: 3.5378584 | P11: 17.269454 | Q11: 21.066832 | R11: 6.2212477 | S11: 34.110062 | T11: -0.046222998 | U11: 0.04667917 | V11: 0.022693159 | W11: 0.2835381 | X11: 0.25763421 | Y11: 0.63108793 | Z11: 0.63108793 | AA11: 0.16780765
A12: Broadcasting | B12: 130 | C12: 0.040306759 | D12: 0.099129608 | E12: 0.088152853 | F12: 0.2529277 | G12: 0.66373824 | H12: 0.98196857 | I12: 0.10174419 | J12: 0.31539633 | K12: 0.064355 | L12: 0.46662627 | M12: 0.076693881 | N12: 1.0482623 | O12: 1.1859946 | P12: 7.8705782 | Q12: 11.66682 | R12: 0.74709201 | S12: 45.336231 | T12: 0.12358975 | U12: 0.037688123 | V12: -0.0027459631 | W12: 1.5367973 | X12: -0.0035567527 | Y12: 0.0047085165 | Z12: 0.0047085165 | AA12: 0.098763143
A13: Brokerage & Investment Banking | B13: 590 | C13: 0.10416122 | D13: 0.01177559 | E13: 0.0018058244 | F13: 0.18959735 | G13: 0.39976611 | H13: 0.92867817 | I13: 0.09832827 | J13: 0.31951734 | K13: 0.064355 | L13: 0.71231609 | M13: 0.062521596 | N13: 0.18374812 | O13: 6.8227984 | P13: 189.17464 | Q13: NA | R13: 1.2584233 | S13: 115.17714 | T13: NA | U13: 0.032147268 | V13: 0.017840381 | W13: 8.4602071 | X13: 0.076645177 | Y13: 0.59630235 | Z13: 0.59630235 | AA13: 0.011347045
A14: Building Materials | B14: 457 | C14: 0.06034178 | D14: 0.10639298 | E14: 0.1673029 | F14: 0.22838372 | G14: 0.94049139 | H14: 1.0314798 | I14: 0.10491785 | J14: 0.28001304 | K14: 0.064355 | L14: 0.1780086 | M14: 0.094796723 | N14: 1.8434296 | O14: 1.7142682 | P14: 11.505962 | Q14: 15.690307 | R14: 2.82074 | S14: 28.790077 | T14: 0.17489299 | U14: 0.04351106 | V14: 0.051551982 | W14: 0.67999327 | X14: 0.13388148 | Y14: 0.38887234 | Z14: 0.38887234 | AA14: 0.10786547
A15: Business & Consumer Services | B15: 980 | C15: 0.074751887 | D15: 0.09154535 | E15: 0.2105184 | F15: 0.24712005 | G15: 0.96407248 | H15: 1.0420887 | I15: 0.10559788 | J15: 0.3330641 | K15: 0.064355 | L15: 0.16018507 | M15: 0.096381225 | N15: 2.7153343 | O15: 2.0557336 | P15: 15.4443 | Q15: 21.52399 | R15: 4.4253805 | S15: 215.34905 | T15: 0.10538725 | U15: 0.027100047 | V15: 0.014473205 | W15: 0.30416219 | X15: 0.13588912 | Y15: 0.54379559 | Z15: 0.54379559 | AA15: 0.093079704
A16: Cable TV | B16: 48 | C16: 0.041942683 | D16: 0.18608744 | E16: 0.12004315 | F16: 0.25003543 | G16: 0.60757746 | H16: 1.0211435 | I16: 0.1042553 | J16: 0.30910674 | K16: 0.064355 | L16: 0.4922968 | M16: 0.076590687 | N16: 0.7593723 | O16: 2.5412604 | P16: 7.8754764 | Q16: 13.842133 | R16: 1.8679222 | S16: 34.875966 | T16: 0.0075306298 | U16: 0.14155246 | V16: 0.014127988 | W16: 0.18025282 | X16: 0.15882582 | Y16: 0.24726749 | Z16: 0.24726749 | AA16: 0.18267772
A17: Chemical (Basic) | B17: 888 | C17: 0.085872087 | D17: 0.046542236 | E17: 0.046390051 | F17: 0.19898679 | G17: 0.90192729 | H17: 1.0727321 | I17: 0.10756213 | J17: 0.28877339 | K17: 0.064355 | L17: 0.30060028 | M17: 0.089675864 | N17: 1.1423312 | O17: 1.3267681 | P17: 12.709581 | Q17: 26.906774 | R17: 1.4647626 | S17: 113.95451 | T17: 0.13109122 | U17: 0.093408742 | V17: 0.066481922 | W17: 1.9459033 | X17: 0.038401073 | Y17: 1.4179037 | Z17: 1.4179037 | AA17: 0.047045769
A18: Chemical (Diversified) | B18: 64 | C18: 0.081043455 | D18: 0.066238601 | E18: 0.054454419 | F18: 0.22367776 | G18: 0.84636701 | H18: 1.0926753 | I18: 0.10884048 | J18: 0.22362857 | K18: 0.058543 | L18: 0.35776017 | M18: 0.085542937 | N18: 1.0817263 | O18: 1.0157982 | P18: 7.9802615 | Q18: 14.423534 | R18: 1.1205498 | S18: 82.991454 | T18: 0.19327838 | U18: 0.072577921 | V18: 0.02999193 | W18: 0.4901687 | X18: 0.029144223 | Y18: 1.7073694 | Z18: 1.7073694 | AA18: 0.065288297
A19: Chemical (Specialty) | B19: 949 | C19: 0.094848672 | D19: 0.1194729 | E19: 0.12380682 | F19: 0.20888361 | G19: 0.94095302 | H19: 1.0268135 | I19: 0.10461875 | J19: 0.31217964 | K19: 0.064355 | L19: 0.17874753 | M19: 0.094509066 | N19: 1.2093762 | O19: 2.2521789 | P19: 12.466233 | Q19: 18.488181 | R19: 2.4503177 | S19: 46.34969 | T19: 0.18241925 | U19: 0.088331116 | V19: 0.067377141 | W19: 0.78861872 | X19: 0.12070412 | Y19: 0.51719762 | Z19: 0.51719762 | AA19: 0.11942988
A20: Coal & Related Energy | B20: 215 | C20: 0.14781404 | D20: 0.24031355 | E20: 0.32220934 | F20: 0.22559346 | G20: 1.0773642 | H20: 1.006257 | I20: 0.10330107 | J20: 0.50421473 | K20: 0.067024 | L20: 0.16520602 | M20: 0.094504259 | N20: 1.4921479 | O20: 1.3071148 | P20: 4.0711931 | Q20: 5.1735913 | R20: 1.5046538 | S20: 25.295557 | T20: -0.030186939 | U20: 0.090487992 | V20: 0.051223276 | W20: 0.2494509 | X20: 0.21362535 | Y20: 0.76433442 | Z20: 0.76433442 | AA20: 0.2407923
A21: Computer Services | B21: 1164 | C21: 0.10303602 | D21: 0.075579066 | E21: 0.2109495 | F21: 0.23628691 | G21: 1.0014532 | H21: 1.0414843 | I21: 0.10555914 | J21: 0.32895363 | K21: 0.064355 | L21: 0.1239104 | M21: 0.098434439 | N21: 3.2861205 | O21: 1.5245899 | P21: 14.677564 | Q21: 19.463101 | R21: 3.9981873 | S21: 64.471243 | T21: 0.15358638 | U21: 0.015317633 | V21: 0.011342016 | W21: 0.2766352 | X21: 0.16017731 | Y21: 0.53071092 | Z21: 0.53071092 | AA21: 0.076819539
A22: Computers/Peripherals | B22: 338 | C22: 0.0057764981 | D22: 0.11390914 | E22: 0.15747684 | F22: 0.15096535 | G22: 1.2534021 | H22: 1.2665979 | I22: 0.11998893 | J22: 0.32935741 | K22: 0.064355 | L22: 0.070298242 | M22: 0.11493247 | N22: 1.6364958 | O22: 3.0481583 | P22: 18.661506 | Q22: 26.442663 | R22: 6.7989481 | S22: 54.682422 | T22: 0.020955925 | U22: 0.056849932 | V22: 0.034593625 | W22: 0.38943366 | X22: 0.28447577 | Y22: 0.24867757 | Z22: 0.24867757 | AA22: 0.1101324
A23: Construction Supplies | B23: 453 | C23: 0.094758754 | D23: 0.09885473 | E23: 0.077513427 | F23: 0.22830902 | G23: 0.73700428 | H23: 0.8950019 | I23: 0.096169622 | J23: 0.26865017 | K23: 0.064355 | L23: 0.29922439 | M23: 0.081774144 | N23: 0.94894788 | O23: 1.6529552 | P23: 10.165 | Q23: 16.387287 | R23: 1.3202123 | S23: 82.491171 | T23: 0.13298628 | U23: 0.078721679 | V23: 0.042007946 | W23: 0.78193429 | X23: 0.083677486 | Y23: 0.4649158 | Z23: 0.4649158 | AA23: 0.098539623
A24: Diversified | B24: 326 | C24: 0.08091494 | D24: 0.15638956 | E24: 0.11943532 | F24: 0.17383651 | G24: 0.74470552 | H24: 0.9535675 | I24: 0.099923677 | J24: 0.27139035 | K24: 0.064355 | L24: 0.34006148 | M24: 0.082286945 | N24: 0.85444722 | O24: 1.8308485 | P24: 8.9318342 | Q24: 11.141035 | R24: 1.2240144 | S24: 18.171079 | T24: -0.094527901 | U24: 0.048969043 | V24: 0.036123723 | W24: 0.37089583 | X24: 0.130976 | Y24: 0.20065345 | Z24: 0.20065345 | AA24: 0.16233636
A25: Drugs (Biotechnology) | B25: 1259 | C25: 0.20205506 | D25: -0.0043496542 | E25: 0.0069302625 | F25: 0.16290318 | G25: 1.1499581 | H25: 1.1735861 | I25: 0.11402687 | J25: 0.53278357 | K25: 0.067024 | L25: 0.12539389 | M25: 0.106005 | N25: 0.42240185 | O25: 6.964535 | P25: 15.315541 | Q25: NA | R25: 5.1098851 | S25: 127.83565 | T25: 0.17156985 | U25: 0.056708801 | V25: 0.09623601 | W25: NA | X25: -0.088267685 | Y25: 0.0046600509 | Z25: 0.0046600509 | AA25: 0.016293477
A26: Drugs (Pharmaceutical) | B26: 1299 | C26: 0.18011463 | D26: 0.18171078 | E26: 0.12868088 | F26: 0.16609342 | G26: 0.88577514 | H26: 0.9463177 | I26: 0.099458964 | J26: 0.41512557 | K26: 0.064355 | L26: 0.13356717 | M26: 0.092593792 | N26: 0.71335756 | O26: 4.0501863 | P26: 14.601133 | Q26: 21.71034 | R26: 3.8805329 | S26: 41.506467 | T26: 0.15494978 | U26: 0.050126177 | V26: 0.057092304 | W26: 0.44219809 | X26: 0.13204955 | Y26: 0.63542627 | Z26: 0.63542627 | AA26: 0.19790655
A27: Education | B27: 260 | C27: 0.10492715 | D27: 0.11068502 | E27: 0.092684764 | F27: 0.20115514 | G27: 0.76004819 | H27: 0.8310439 | I27: 0.092069914 | J27: 0.34525639 | K27: 0.064355 | L27: 0.2238175 | M27: 0.082219795 | N27: 0.97000135 | O27: 2.2863341 | P27: 10.920841 | Q27: 18.170084 | R27: 1.9459813 | S27: 125.42376 | T27: 0.034761841 | U27: 0.057202129 | V27: 0.030121777 | W27: 0.57594987 | X27: 0.051181871 | Y27: 0.57708042 | Z27: 0.57708042 | AA27: 0.10893549
A28: Electrical Equipment | B28: 1072 | C28: 0.10648473 | D28: 0.07125667 | E28: 0.10900313 | F28: 0.18776406 | G28: 1.103838 | H28: 1.1304438 | I28: 0.11126145 | J28: 0.35113385 | K28: 0.064355 | L28: 0.14982262 | M28: 0.10179249 | N28: 1.6654991 | O28: 1.9374739 | P28: 15.546387 | Q28: 24.885789 | R28: 2.8201041 | S28: 97.34873 | T28: 0.2172457 | U28: 0.068861989 | V28: 0.06026384 | W28: 1.622376 | X28: 0.10855338 | Y28: 0.39383157 | Z28: 0.39383157 | AA28: 0.073928527
A29: Electronics (Consumer & Office) | B29: 127 | C29: 0.030448866 | D29: 0.046753507 | E29: 0.062281609 | F29: 0.14511189 | G29: 1.1252478 | H29: 1.2272209 | I29: 0.11746486 | J29: 0.33860994 | K29: 0.064355 | L29: 0.2324043 | M29: 0.10133495 | N29: 1.4795011 | O29: 0.93723071 | P29: 11.435557 | Q29: 19.485954 | R29: 1.7221992 | S29: 40.793478 | T29: 0.066260614 | U29: 0.041996586 | V29: 0.026957625 | W29: 0.8712161 | X29: 0.073103505 | Y29: 0.32240989 | Z29: 0.32240989 | AA29: 0.047475839
A30: Electronics (General) | B30: 1486 | C30: 0.058386103 | D30: 0.052816363 | E30: 0.06442013 | F30: 0.18363373 | G30: 1.2783309 | H30: 1.2819639 | I30: 0.12097389 | J30: 0.32533099 | K30: 0.064355 | L30: 0.15707809 | M30: 0.10952076 | N30: 1.359642 | O30: 1.5902472 | P30: 14.162266 | Q30: 28.293548 | R30: 2.271368 | S30: 102.00099 | T30: 0.18920481 | U30: 0.063112177 | V30: 0.035719374 | W30: 0.9658047 | X30: 0.066824042 | Y30: 0.61911602 | Z30: 0.61911602 | AA30: 0.053403823
A31: Engineering/Construction | B31: 1623 | C31: 0.063632522 | D31: 0.056830671 | E31: 0.087832769 | F31: 0.22550851 | G31: 0.8082989 | H31: 1.0134173 | I31: 0.10376005 | J31: 0.30521755 | K31: 0.064355 | L31: 0.40137684 | M31: 0.081403466 | N31: 1.79554 | O31: 0.78265543 | P31: 9.3963917 | Q31: 13.16986 | R31: 1.3065437 | S31: 42.843281 | T31: 0.15922667 | U31: 0.03367122 | V31: 0.022302216 | W31: 1.0727987 | X31: 0.10080519 | Y31: 0.53466879 | Z31: 0.53466879 | AA31: 0.057689743
A32: Entertainment | B32: 741 | C32: 0.096076652 | D32: 0.073014559 | E32: 0.074713947 | F32: 0.22104866 | G32: 1.0326457 | H32: 1.1080718 | I32: 0.1098274 | J32: 0.41350767 | K32: 0.064355 | L32: 0.18212969 | M32: 0.09857778 | N32: 1.0903965 | O32: 2.9125408 | P32: 15.776376 | Q32: 36.435754 | R32: 2.4782438 | S32: 156.16716 | T32: 0.039983541 | U32: 0.037191471 | V32: -0.025549451 | W32: -0.34121715 | X32: 0.022666951 | Y32: 0.89236563 | Z32: 0.89236563 | AA32: 0.074795523
A33: Environmental & Waste Services | B33: 383 | C33: 0.082141268 | D33: 0.10594278 | E33: 0.10776036 | F33: 0.22828573 | G33: 0.82790886 | H33: 1.0018793 | I33: 0.10302047 | J33: 0.33888162 | K33: 0.064355 | L33: 0.2593043 | M33: 0.088769062 | N33: 1.1590208 | O33: 2.7759011 | P33: 14.044705 | Q33: 24.861013 | R33: 3.0192594 | S33: 39.262853 | T33: 0.14714494 | U33: 0.08649035 | V33: 0.074507317 | W33: 1.3468736 | X33: 0.080683417 | Y33: 0.63167403 | Z33: 0.63167403 | AA33: 0.10712906
A34: Farming/Agriculture | B34: 430 | C34: 0.11069166 | D34: 0.081559189 | E34: 0.10564639 | F34: 0.21465598 | G34: 0.57398339 | H34: 0.77392079 | I34: 0.088408322 | J34: 0.34054792 | K34: 0.064355 | L34: 0.36687002 | M34: 0.073605848 | N34: 1.4546832 | O34: 1.0834452 | P34: 9.7489631 | Q34: 12.674166 | R34: 1.826141 | S34: 26.811988 | T34: 0.16202092 | U34: 0.04191541 | V34: 0.02711998 | W34: 0.59827152 | X34: 0.14471014 | Y34: 0.33023374 | Z34: 0.33023374 | AA34: 0.083784585
A35: Financial Svcs. (Non-bank & Insurance) | B35: 1258 | C35: 0.12562276 | D35: 0.12676164 | E35: 0.0094098181 | F35: 0.17186208 | G35: 0.27764418 | H35: 0.9064411 | I35: 0.096902875 | J35: 0.34608474 | K35: 0.064355 | L35: 0.76985807 | M35: 0.059301035 | N35: 0.085866413 | O35: 14.427254 | P35: 48.685478 | Q35: 67.19285 | R35: 2.2423073 | S35: 75.538288 | T35: NA | U35: 0.040021054 | V35: -0.073819923 | W35: -0.68655709 | X35: 0.1804461 | Y35: 0.25756972 | Z35: 0.25756972 | AA35: 0.12765948
A36: Food Processing | B36: 1657 | C36: 0.084663066 | D36: 0.076612696 | E36: 0.11456981 | F36: 0.23277823 | G36: 0.61262228 | H36: 0.72111816 | I36: 0.085023674 | J36: 0.28613127 | K36: 0.064355 | L36: 0.25097433 | M36: 0.075746819 | N36: 1.759098 | O36: 1.3920067 | P36: 12.154853 | Q36: 17.800402 | R36: 2.2665404 | S36: 46.464615 | T36: 0.10527082 | U36: 0.046154263 | V36: 0.025405255 | W36: 0.61952642 | X36: 0.099151351 | Y36: 0.6585422 | Z36: 0.6585422 | AA36: 0.077140853
A37: Food Wholesalers | B37: 173 | C37: 0.077620738 | D37: 0.024705013 | E37: 0.10682869 | F37: 0.24528806 | G37: 0.49621393 | H37: 0.66918428 | I37: 0.081694712 | J37: 0.30822331 | K37: 0.064355 | L37: 0.36579862 | M37: 0.069391296 | N37: 5.2660012 | O37: 0.37040946 | P37: 9.7054738 | Q37: 14.908329 | R37: 2.1484245 | S37: 49.788417 | T37: 0.05873509 | U37: 0.014196922 | V37: 0.0090395737 | W37: 0.48474528 | X37: 0.089141668 | Y37: 0.56945565 | Z37: 0.56945565 | AA37: 0.024650662
A38: Furn/Home Furnishings | B38: 383 | C38: 0.051528209 | D38: 0.072368211 | E38: 0.1312851 | F38: 0.18188021 | G38: 0.93432143 | H38: 0.94909499 | I38: 0.099636989 | J38: 0.29724029 | K38: 0.064355 | L38: 0.21842612 | M38: 0.088371296 | N38: 2.0889193 | O38: 1.0263903 | P38: 9.7423344 | Q38: 13.621347 | R38: 2.0500314 | S38: 37.844392 | T38: 0.049111422 | U38: 0.035884467 | V38: 0.030953297 | W38: 0.53441064 | X38: 0.11207479 | Y38: 0.70048042 | Z38: 0.70048042 | AA38: 0.073326345
A39: Green & Renewable Energy | B39: 253 | C39: 0.1356263 | D39: 0.29235498 | E39: 0.071734087 | F39: 0.15996917 | G39: 0.60906205 | H39: 0.86538505 | I39: 0.094271182 | J39: 0.33373654 | K39: 0.064355 | L39: 0.39204417 | M39: 0.07615448 | N39: 0.27487755 | O39: 7.4006674 | P39: 13.945214 | Q39: 22.786692 | R39: 2.0118014 | S39: 49.912197 | T39: 0.097204349 | U39: 0.41558884 | V39: 0.36675488 | W39: 1.5213912 | X39: 0.10750115 | Y39: 0.66386814 | Z39: 0.66386814 | AA39: 0.29146342
A40: Healthcare Products | B40: 849 | C40: 0.15227077 | D40: 0.12429655 | E40: 0.11043988 | F40: 0.20586319 | G40: 1.0434097 | H40: 1.0980823 | I40: 0.10918707 | J40: 0.42342967 | K40: 0.064355 | L40: 0.11702455 | M40: 0.10203374 | N40: 0.93443822 | O40: 4.4129152 | P40: 20.066048 | Q40: 33.885138 | R40: 3.5770653 | S40: 94.725775 | T40: 0.25687717 | U40: 0.0542584 | V40: 0.034683575 | W40: 0.67329218 | X40: 0.07578216 | Y40: 0.50703233 | Z40: 0.50703233 | AA40: 0.12860324
A41: Healthcare Support Services | B41: 463 | C41: 0.12621487 | D41: 0.039498904 | E41: 0.2893124 | F41: 0.23065814 | G41: 0.82121099 | H41: 0.91020464 | I41: 0.097144117 | J41: 0.37805794 | K41: 0.064355 | L41: 0.23001143 | M41: 0.085854282 | N41: 8.6589822 | O41: 0.60840309 | P41: 11.056728 | Q41: 15.221991 | R41: 2.6222806 | S41: 57.500895 | T41: -0.027295865 | U41: 0.0087350112 | V41: 0.016595146 | W41: 0.57451391 | X41: 0.1215032 | Y41: 0.36882229 | Z41: 0.36882229 | AA41: 0.039065888
A42: Heathcare Information and Technology | B42: 443 | C42: 0.1660805 | D42: 0.1360342 | E42: 0.12755598 | F42: 0.14063027 | G42: 1.170677 | H42: 1.2336178 | I42: 0.1178749 | J42: 0.4493294 | K42: 0.064355 | L42: 0.1208871 | M42: 0.10943522 | N42: 0.98068089 | O42: 5.2454773 | P42: 21.657558 | Q42: 36.682737 | R42: 3.9372988 | S42: 128.07264 | T42: 0.23898001 | U42: 0.07151954 | V42: 0.061350006 | W42: 0.71590478 | X42: 0.06025566 | Y42: 0.24427342 | Z42: 0.24427342 | AA42: 0.13842722
A43: Homebuilding | B43: 173 | C43: 0.078341888 | D43: 0.13284172 | E43: 0.14415922 | F43: 0.24284596 | G43: 1.0113882 | H43: 1.0947074 | I43: 0.10897075 | J43: 0.28965125 | K43: 0.064355 | L43: 0.23108292 | M43: 0.094895386 | N43: 1.3895016 | O43: 1.1836836 | P43: 8.0294493 | Q43: 9.1651714 | R43: 1.5788153 | S43: 20.550712 | T43: 0.60934414 | U43: 0.0069435146 | V43: 0.0051463808 | W43: 0.20287092 | X43: 0.16610004 | Y43: 0.18138713 | Z43: 0.18138713 | AA43: 0.12789569
A44: Hospitals/Healthcare Facilities | B44: 232 | C44: 0.11022303 | D44: 0.10856497 | E44: 0.12323476 | F44: 0.20089466 | G44: 0.58022191 | H44: 0.76494921 | I44: 0.087833245 | J44: 0.29529431 | K44: 0.064355 | L44: 0.32208492 | M44: 0.075022984 | N44: 1.3816579 | O44: 2.3100825 | P44: 12.437423 | Q44: 20.576674 | R44: 4.0772284 | S44: 41.979481 | T44: 0.069638859 | U44: 0.071738628 | V44: 0.024492222 | W44: 0.40774982 | X44: 0.11949723 | Y44: 0.45894118 | Z44: 0.45894118 | AA44: 0.10768275
A45: Hotel/Gaming | B45: 650 | C45: 0.034793381 | D45: 0.14018792 | E45: 0.082653906 | F45: 0.20563328 | G45: 0.78536963 | H45: 0.97912748 | I45: 0.10156207 | J45: 0.33832877 | K45: 0.064355 | L45: 0.31642145 | M45: 0.084632968 | N45: 0.75800943 | O45: 3.5637068 | P45: 15.089381 | Q45: 28.372078 | R45: 3.9615827 | S45: 60.185329 | T45: -0.019780753 | U45: 0.063055972 | V45: 0.0084609041 | W45: 0.16016478 | X45: 0.10909197 | Y45: 0.2713693 | Z45: 0.2713693 | AA45: 0.12340734
A46: Household Products | B46: 178 | C46: 0.039548647 | D46: 0.16559847 | E46: 0.25243133 | F46: 0.22232585 | G46: 0.67520464 | H46: 0.72747138 | I46: 0.085430915 | J46: 0.29781296 | K46: 0.064355 | L46: 0.13333772 | M46: 0.080448005 | N46: 1.778318 | O46: 3.1017984 | P46: 15.108859 | Q46: 18.460413 | R46: 6.0419945 | S46: 53.668869 | T46: 0.053235794 | U46: 0.035742252 | V46: 0.013238667 | W46: 0.070553054 | X46: 0.26800939 | Y46: 0.65689101 | Z46: 0.65689101 | AA46: 0.16660655
A47: Information Services | B47: 81 | C47: 0.020683617 | D47: 0.10927794 | E47: 0.21875033 | F47: 0.25722216 | G47: 1.022862 | H47: 1.2103299 | I47: 0.11638215 | J47: 0.33631953 | K47: 0.064355 | L47: 0.25719481 | M47: 0.098810126 | N47: 2.3003858 | O47: 1.9345204 | P47: 11.3806 | Q47: 16.969841 | R47: 3.3749991 | S47: 143.50473 | T47: 0.14317421 | U47: 0.0197349 | V47: -0.013947351 | W47: 0.001496213 | X47: 0.0898208 | Y47: 0.55284058 | Z47: 0.55284058 | AA47: 0.11380793
... A50: Insurance (Prop/Cas.) | B50: 228 | C50: 0.090641658 | D50: 0.097581466 | E50: 0.13311213 | F50: 0.18702298 | G50: 0.66476895 | H50: 0.71082251 | I50: 0.084363723 | J50: 0.26743777 | K50: 0.064355 | L50: 0.18249068 | M50: 0.077738689 | N50: 1.6491131 | O50: 1.1297486 | P50: 9.2472287 | Q50: 10.817649 | R50: 1.5899489 | S50: 19.552938 | T50: -0.2847603 | U50: 0.0069659939 | V50: -0.0031311811 | W50: 0.19017906 | X50: 0.12312294 | Y50: 0.31767303 | Z50: 0.31767303 | AA50: 0.097921921
A51: Investments & Asset Management | B51: 1374 | C51: 0.11473422 | D51: 0.17622005 | E51: 0.055770237 | F51: 0.17295985 | G51: 0.53979286 | H51: 0.75382192 | I51: 0.087119985 | J51: 0.29524731 | K51: 0.064355 | L51: 0.42424609 | M51: 0.070549072 | N51: 0.34866273 | O51: 4.6552158 | P51: 16.809441 | Q51: 20.170579 | R51: 1.3814511 | S51: 56.350073 | T51: NA | U51: 0.036008276 | V51: 0.076788118 | W51: 0.5242061 | X51: 0.10448447 | Y51: 0.56047597 | Z51: 0.56047597 | AA51: 0.17504604
A52: Machinery | B52: 1492 | C52: 0.060736807 | D52: 0.099188092 | E52: 0.12714982 | F52: 0.21301565 | G52: 1.038361 | H52: 1.0707089 | I52: 0.10743244 | J52: 0.2975652 | K52: 0.064355 | L52: 0.13307684 | M52: 0.099531383 | N52: 1.4758445 | O52: 2.1520512 | P52: 14.740091 | Q52: 20.507888 | R52: 2.9318972 | S52: 59.821455 | T52: 0.28320475 | U52: 0.041859504 | V52: 0.042353512 | W52: 0.91591251 | X52: 0.11997301 | Y52: 0.41450281 | Z52: 0.41450281 | AA52: 0.10081767
A53: Metals & Mining | B53: 1815 | C53: 0.19804778 | D53: 0.10664862 | E53: 0.14836569 | F53: 0.30835377 | G53: 0.98882838 | H53: 1.090734 | I53: 0.10871605 | J53: 0.57513374 | K53: 0.067024 | L53: 0.21730036 | M53: 0.09596866 | N53: 1.4403961 | O53: 1.3218409 | P53: 7.8168871 | Q53: 11.719209 | R53: 1.8383154 | S53: 54.204297 | T53: 0.11976333 | U53: 0.08001764 | V53: 0.0489513 | W53: 0.84861811 | X53: 0.10498913 | Y53: 0.85950262 | Z53: 0.85950262 | AA53: 0.10717264
A54: Office Equipment & Services | B54: 137 | C54: 0.07100703 | D54: 0.07096158 | E54: 0.11212639 | F54: 0.2667675 | G54: 0.77554815 | H54: 0.82887591 | I54: 0.091930946 | J54: 0.27908767 | K54: 0.064355 | L54: 0.22256684 | M54: 0.082166798 | N54: 1.9486921 | O54: 1.0643054 | P54: 9.4331644 | Q54: 14.408234 | R54: 1.8408621 | S54: 148.70651 | T54: 0.13322723 | U54: 0.024677177 | V54: 0.016106126 | W54: 0.3043774 | X54: 0.082629468 | Y54: 0.52401833 | Z54: 0.52401833 | AA54: 0.071497526
A55: Oil/Gas (Integrated) | B55: 36 | C55: 0.17374848 | D55: 0.1833045 | E55: 0.21955647 | F55: 0.41146505 | G55: 0.93789804 | H55: 0.99082953 | I55: 0.10231217 | J55: 0.26835269 | K55: 0.064355 | L55: 0.14876667 | M55: 0.094241304 | N55: 1.657744 | O55: 1.2699079 | P55: 5.3293757 | Q55: 6.9103766 | R55: 1.995999 | S55: 14.031827 | T55: 0.032549088 | U55: 0.075515815 | V55: 0.017882863 | W55: 0.1470973 | X55: 0.2111799 | Y55: 0.48938589 | Z55: 0.48938589 | AA55: 0.18395151
A56: Oil/Gas (Production and Exploration) | B56: 590 | C56: 0.26669155 | D56: 0.36359811 | E56: 0.24158268 | F56: 0.31260731 | G56: 0.96400288 | H56: 1.0888559 | I56: 0.10859567 | J56: 0.48387767 | K56: 0.064355 | L56: 0.21367469 | M56: 0.095660794 | N56: 0.72177788 | O56: 2.3810527 | P56: 4.2234318 | Q56: 6.3968446 | R56: 1.5420415 | S56: 17.550484 | T56: 0.011379439 | U56: 0.27791758 | V56: 0.14230625 | W56: 0.53680368 | X56: 0.21873527 | Y56: 0.38354606 | Z56: 0.38354606 | AA56: 0.36597779
A57: Oil/Gas Distribution | B57: 174 | C57: 0.14224071 | D57: 0.20652392 | E57: 0.12634031 | F57: 0.17576165 | G57: 0.58306892 | H57: 0.85477328 | I57: 0.093590967 | J57: 0.29604835 | K57: 0.064355 | L57: 0.41344814 | M57: 0.074766403 | N57: 0.70119353 | O57: 2.4350441 | P57: 8.653831 | Q57: 11.667657 | R57: 1.7319473 | S57: 379.61372 | T57: 0.040400031 | U57: 0.11718132 | V57: 0.080230525 | W57: 0.47879737 | X57: 0.19802991 | Y57: 0.58133832 | Z57: 0.58133832 | AA57: 0.2076674
A58: Oilfield Svcs/Equip. | B58: 444 | C58: 0.077933924 | D58: 0.067211946 | E58: 0.14553326 | F58: 0.23018695 | G58: 0.81650032 | H58: 0.97654622 | I58: 0.10139661 | J58: 0.36102582 | K58: 0.064355 | L58: 0.29357722 | M58: 0.085738291 | N58: 2.4835719 | O58: 0.64414148 | P58: 6.4382791 | Q58: 8.8875255 | R58: 1.4899585 | S58: 46.826722 | T58: 0.064448066 | U58: 0.039255162 | V58: 0.021534722 | W58: 0.41173453 | X58: 0.16710585 | Y58: 0.25278543 | Z58: 0.25278543 | AA58: 0.067815316
A59: Packaging & Container | B59: 164 | C59: 0.057694754 | D59: 0.091697469 | E59: 0.12158429 | F59: 0.21199308 | G59: 0.63169706 | H59: 0.82652071 | I59: 0.091779978 | J59: 0.25952513 | K59: 0.064355 | L59: 0.34484163 | M59: 0.076703618 | N59: 1.5635258 | O59: 1.404069 | P59: 9.292199 | Q59: 15.085462 | R59: 2.2006561 | S59: 29.949387 | T59: 0.13503323 | U59: 0.073430272 | V59: 0.040861988 | W59: 0.76467093 | X59: 0.12437616 | Y59: 0.40548112 | Z59: 0.40548112 | AA59: 0.092122168
A60: Paper/Forest Products | B60: 266 | C60: 0.03015177 | D60: 0.065469265 | E60: 0.049573756 | F60: 0.2085298 | G60: 0.67452726 | H60: 0.91123562 | I60: 0.097210203 | J60: 0.29232143 | K60: 0.064355 | L60: 0.39221478 | M60: 0.07793289 | N60: 0.86614494 | O60: 1.3103287 | P60: 10.145296 | Q60: 19.409726 | R60: 1.0700113 | S60: 53.229041 | T60: 0.19301024 | U60: 0.10356254 | V60: 0.068286822 | W60: 1.5270402 | X60: 0.064685813 | Y60: 0.5588183 | Z60: 0.5588183 | AA60: 0.065270027
A61: Power | B61: 488 | C61: 0.10553491 | D61: 0.13542992 | E61: 0.077773291 | F61: 0.20805972 | G61: 0.4470974 | H61: 0.73654518 | I61: 0.086012546 | J61: 0.2534238 | K61: 0.064355 | L61: 0.49590794 | M61: 0.067191733 | N61: 0.68526874 | O61: 1.984244 | P61: 8.71086 | Q61: 14.113054 | R61: 1.3054398 | S61: 19.746455 | T61: 0.051321053 | U61: 0.16145031 | V61: 0.097845997 | W61: 0.93997522 | X61: 0.12425006 | Y61: 0.63064006 | Z61: 0.63064006 | AA61: 0.13547672
A62: Precious Metals | B62: 853 | C62: 0.3966128 | D62: 0.11716428 | E62: 0.090931099 | F62: 0.25659863 | G62: 1.0402351 | H62: 1.0916417 | I62: 0.10877423 | J62: 0.60159261 | K62: 0.067024 | L62: 0.15542889 | M62: 0.099647339 | N62: 0.80766548 | O62: 2.3882434 | P62: 8.8129812 | Q62: 18.827938 | R62: 1.6763221 | S62: 250.1674 | T62: 0.10876921 | U62: 0.18593105 | V62: 0.11279334 | W62: 1.5606818 | X62: 0.043236321 | Y62: 0.98308006 | Z62: 0.98308006 | AA62: 0.11750297
A63: Publishing & Newspapers | B63: 205 | C63: 0.025649286 | D63: 0.07573367 | E63: 0.091693019 | F63: 0.11845025 | G63: 0.9817444 | H63: 0.98667455 | I63: 0.10204584 | J63: 0.30045958 | K63: 0.064355 | L63: 0.17696837 | M63: 0.092492108 | N63: 1.4375095 | O63: 1.5447616 | P63: 12.197354 | Q63: 19.632013 | R63: 1.6779599 | S63: 41.064074 | T63: 0.084396816 | U63: 0.030230211 | V63: -0.013126563 | W63: -0.10842879 | X63: 0.089123022 | Y63: 0.4136493 | Z63: 0.4136493 | AA63: 0.073676112
... A83: Software (Entertainment) | B83: 317 | C83: 0.090190864 | D83: 0.24397492 | E83: 0.15958092 | F83: 0.16758546 | G83: 1.355352 | H83: 1.3567754 | I83: 0.1257693 | J83: 0.43820902 | K83: 0.064355 | L83: 0.047797712 | M83: 0.12205499 | N83: 0.70387222 | O83: 5.6046231 | P83: 17.539469 | Q83: 22.713778 | R83: 5.1419967 | S83: 235.20711 | T83: 0.012379849 | U83: 0.10657483 | V83: 0.069392998 | W83: 0.40565234 | X83: 0.20902109 | Y83: 0.027408127 | Z83: 0.027408127 | AA83: 0.25396813
A84: Software (Internet) | B84: 151 | C84: 0.12337152 | D84: -0.00079294627 | E84: 0.013073769 | F84: 0.19524857 | G84: 1.2987745 | H84: 1.3617461 | I84: 0.12608793 | J84: 0.46982264 | K84: 0.064355 | L84: 0.099754446 | M84: 0.11830433 | N84: 0.87876345 | O84: 6.0148366 | P84: 20.437795 | Q84: NA | R84: 7.9662272 | S84: 62.967864 | T84: 0.05207558 | U84: 0.059528225 | V84: 0.033495177 | W84: NA | X84: -0.10004457 | Y84: 0.0037426538 | Z84: 0.0037426538 | AA84: 0.014866689
A85: Software (System & Application) | B85: 1616 | C85: 0.14317632 | D85: 0.2024516 | E85: 0.18335838 | F85: 0.18835127 | G85: 1.2856288 | H85: 1.2989897 | I85: 0.12206524 | J85: 0.43591421 | K85: 0.064355 | L85: 0.058498553 | M85: 0.11773606 | N85: 0.93431463 | O85: 9.202136 | P85: 28.477415 | Q85: 41.069428 | R85: 9.1521655 | S85: 96.429559 | T85: 0.13353321 | U85: 0.072338647 | V85: 0.058858353 | W85: 0.47630102 | X85: 0.16957095 | Y85: 0.32891323 | Z85: 0.32891323 | AA85: 0.21284948
A86: Steel | B86: 718 | C86: 0.089877694 | D86: 0.07188271 | E86: 0.090490647 | F86: 0.20410892 | G86: 1.0067867 | H86: 1.1651511 | I86: 0.11348618 | J86: 0.32684206 | K86: 0.064355 | L86: 0.29282308 | M86: 0.094327978 | N86: 1.4569432 | O86: 0.82345152 | P86: 6.8965107 | Q86: 10.902343 | R86: 1.1441037 | S86: 42.976378 | T86: 0.14636397 | U86: 0.060461242 | V86: 0.038355539 | W86: 0.53656825 | X86: 0.00010149487 | Y86: 0.50757039 | Z86: 0.50757039 | AA86: 0.072216298
A87: Telecom (Wireless) | B87: 98 | C87: 0.058909873 | D87: 0.14601325 | E87: 0.083083945 | F87: 0.22352796 | G87: 0.6530667 | H87: 0.89702716 | I87: 0.096299441 | J87: 0.29268715 | K87: 0.064355 | L87: 0.40042659 | M87: 0.076983212 | N87: 0.70559135 | O87: 2.2521573 | P87: 7.3658215 | Q87: 15.636399 | R87: 1.5396712 | S87: 33.140192 | T87: -0.13702131 | U87: 0.15233253 | V87: 0.015600504 | W87: 0.30505836 | X87: 0.081817965 | Y87: 0.73581411 | Z87: 0.73581411 | AA87: 0.14327448
A88: Telecom. Equipment | B88: 453 | C88: 0.045972243 | D88: 0.10996964 | E88: 0.13621199 | F88: 0.14782676 | G88: 1.1744669 | H88: 1.1857162 | I88: 0.11480441 | J88: 0.36121152 | K88: 0.064355 | L88: 0.11422833 | M88: 0.10718034 | N88: 1.2621053 | O88: 2.3180552 | P88: 14.280877 | Q88: 19.412426 | R88: 3.4564202 | S88: 120.31624 | T88: 0.2467527 | U88: 0.031587752 | V88: 0.025610341 | W88: 0.53624244 | X88: 0.12935477 | Y88: 0.53281684 | Z88: 0.53281684 | AA88: 0.11666475
A89: Telecom. Services | B89: 288 | C89: 0.083990326 | D89: 0.15465251 | E89: 0.095021299 | F89: 0.21847468 | G89: 0.54380766 | H89: 0.84937394 | I89: 0.09324487 | J89: 0.30131886 | K89: 0.064355 | L89: 0.4567224 | M89: 0.072608071 | N89: 0.70336612 | O89: 2.162779 | P89: 6.8782617 | Q89: 13.871231 | R89: 1.3805704 | S89: 41.987957 | T89: -0.00226734 | U89: 0.14743048 | V89: -0.014085193 | W89: -0.03284304 | X89: 0.077965825 | Y89: 0.89726293 | Z89: 0.89726293 | AA89: 0.15572277
A90: Tobacco | B90: 56 | C90: 0.17277632 | D90: 0.33764511 | E90: 0.23171725 | F90: 0.22440219 | G90: 0.55335166 | H90: 0.66681535 | I90: 0.081542864 | J90: 0.31215896 | K90: 0.064355 | L90: 0.24862145 | M90: 0.073218384 | N90: 0.82776359 | O90: 3.4660579 | P90: 9.3346135 | Q90: 10.234059 | R90: 3.165594 | S90: 32.345262 | T90: 0.16055763 | U90: 0.027943883 | V90: 0.12228403 | W90: 0.54791426 | X90: 0.28431447 | Y90: 0.71673296 | Z90: 0.71673296 | AA90: 0.33880306
A91: Transportation | B91: 814 | C91: 0.06881983 | D91: 0.081729681 | E91: 0.11094139 | F91: 0.23217618 | G91: 0.83459832 | H91: 0.96150402 | I91: 0.10043241 | J91: 0.33828755 | K91: 0.064355 | L91: 0.23398055 | M91: 0.088178356 | N91: 1.5702161 | O91: 1.7510056 | P91: 13.095158 | Q91: 20.734648 | R91: 2.9795085 | S91: 67.818917 | T91: 0.04168477 | U91: 0.047915082 | V91: 0.017927106 | W91: 0.26742536 | X91: 0.13669979 | Y91: 0.70694546 | Z91: 0.70694546 | AA91: 0.082544147
A92: Transportation (Railroads) | B92: 49 | C92: -0.0030885714 | D92: 0.21498145 | E92: 0.069119561 | F92: 0.2450507 | G92: 0.49774817 | H92: 0.62873301 | I92: 0.079101786 | J92: 0.19255174 | K92: 0.058543 | L92: 0.29637584 | M92: 0.068615454 | N92: 0.41782903 | O92: 4.3308077 | P92: 13.3124 | Q92: 19.991498 | R92: 2.3646194 | S92: 54.741204 | T92: 0.057506948 | U92: 0.15777753 | V92: 0.093695085 | W92: 0.59998075 | X92: 0.1184748 | Y92: 0.40046903 | Z92: 0.40046903 | AA92: 0.21543368
A93: Trucking | B93: 106 | C93: 0.030212821 | D93: 0.086002602 | E93: 0.11601095 | F93: 0.25768128 | G93: 0.86855446 | H93: 1.0142471 | I93: 0.10381324 | J93: 0.29115151 | K93: 0.064355 | L93: 0.22285087 | M93: 0.091388652 | N93: 1.6608902 | O93: 1.5858226 | P93: 9.9759117 | Q93: 17.984158 | R93: 2.8560845 | S93: 27.978466 | T93: 0.068875806 | U93: 0.11440306 | V93: 0.070906289 | W93: 1.0534269 | X93: 0.12020694 | Y93: 0.20666339 | Z93: 0.20666339 | AA93: 0.087568536
A94: Utility (General) | B94: 50 | C94: 0.078220444 | D94: 0.12264771 | E94: 0.083203295 | F94: 0.20200999 | G94: 0.4506286 | H94: 0.6833212 | I94: 0.082600889 | J94: 0.1849322 | K94: 0.058543 | L94: 0.44487457 | M94: 0.065303731 | N94: 0.81265792 | O94: 1.877489 | P94: 9.85764 | Q94: 15.288914 | R94: 1.6154897 | S94: 20.357421 | T94: -0.0059726752 | U94: 0.1420647 | V94: 0.077470214 | W94: 0.78421627 | X94: 0.10614482 | Y94: 0.66703362 | Z94: 0.66703362 | AA94: 0.12236645
A95: Utility (Water) | B95: 102 | C95: 0.064320127 | D95: 0.23268695 | E95: 0.062337784 | F95: 0.19785675 | G95: 0.42747496 | H95: 0.67007062 | I95: 0.081751527 | J95: 0.23638246 | K95: 0.058543 | L95: 0.46441397 | M95: 0.064089114 | N95: 0.31191832 | O95: 4.5867306 | P95: 12.671747 | Q95: 19.574008 | R95: 1.4758104 | S95: 26.689561 | T95: 0.073514917 | U95: 0.2267281 | V95: 0.11572838 | W95: 0.96245009 | X95: 0.0086431792 | Y95: 0.8329099 | Z95: 0.46710436 | AA95: 0.2325429

Sheet Input Stat Distributioons
C1: Revenue Growth Rate = Last 3 years | F1: Pre-tax Operating Margin | I1: Sales to Invested Capital | L1: Cost of Capital | O1: Beta | P1: Debt to Capital Ratio
A2: Industry Group | B2: count | C2: First Quartlie | D2: Median | E2: Third Quartile | F2: First Quartlie | G2: Median | H2: Third Quartile | I2: First Quartlie | J2: Median | K2: Third Quartile | L2: First Quartlie | M2: Median | N2: Third Quartile | O2: median(Beta) | P2: First Quartlie | Q2: Median | R2: Third Quartile
A3: Advertising | B3: 391 | C3: -0.0227 | D3: 0.0793 | E3: 0.207 | F3: -0.051633987 | G3: 0.035119048 | H3: 0.098708288 | I3: 1.3965446 | J3: 3.1693198 | K3: 6.7938931 | L3: 0.098368913 | M3: 0.10517643 | N3: 0.10733442 | O3: 0.64404645 | P3: 1.2031446 | Q3: 1.8256868 | R3: 0.0087259591 | S3: 0.091552858 | T3: 0.28106528
A4: Aerospace/Defense | B4: 289 | C4: 0.00268 | D4: 0.0613 | E4: 0.167 | F4: -0.063316944 | G4: 0.059474979 | H4: 0.12214499 | I4: 0.57950371 | J4: 1.2162067 | K4: 2.1735731 | L4: 0.079271238 | M4: 0.085859807 | N4: 0.08888429 | O4: 0.50679934 | P4: 0.92591218 | Q4: 1.4204689 | R4: 0.011750014 | S4: 0.097744361 | T4: 0.23568301
A5: Air Transport | B5: 155 | C5: 0.0921 | D5: 0.188 | E5: 0.311 | F5: -0.033665262 | G5: 0.086426015 | H5: 0.15355805 | I5: 0.4822615 | J5: 0.98182341 | K5: 2.1586647 | L5: 0.075486343 | M5: 0.08078842 | N5: 0.095110904 | O5: 0.77849645 | P5: 1.2407132 | Q5: 1.6762919 | R5: 0.15363175 | S5: 0.43675794 | T5: 0.62652889
A6: Apparel | B6: 1152 | C6: -0.0119 | D6: 0.0803 | E6: 0.205 | F6: -0.029923664 | G6: 0.038841808 | H6: 0.091279393 | I6: 0.64100738 | J6: 1.2141442 | K6: 1.8321429 | L6: 0.08099399 | M6: 0.096238828 | N6: 0.0992287 | O6: 0.31337177 | P6: 0.7884321 | Q6: 1.3044853 | R6: 0.059593524 | S6: 0.23447537 | T6: 0.51264045
A7: Auto & Truck | B7: 165 | C7: 0.0434 | D7: 0.153 | E7: 0.243 | F7: -0.25438101 | G7: 0.032249786 | H7: 0.085247447 | I7: 0.59156383 | J7: 1.3672722 | K7: 2.8775542 | L7: 0.08551538 | M7: 0.093588292 | N7: 0.09926697 | O7: 0.85006706 | P7: 1.3914007 | Q7: 1.824496 | R7: 0.012847363 | S7: 0.13077098 | T7: 0.37923897
A8: Auto Parts | B8: 761 | C8: 0.0775 | D8: 0.133 | E8: 0.217 | F8: 0.017917866 | G8: 0.047520185 | H8: 0.087266958 | I8: 1.0043183 | J8: 1.6017004 | K8: 2.3607488 | L8: 0.097752784 | M8: 0.10353986 | N8: 0.10586756 | O8: 0.83343193 | P8: 1.2326264 | Q8: 1.7032183 | R8: 0.046287869 | S8: 0.18155645 | T8: 0.41995532
A9: Bank (Money Center) | B9: 607 | C9: 0.0823 | D9: 0.142 | E9: 0.239 | F9: 0 | G9: 0 | H9: 0 | I9: 0.14832234 | J9: 0.25302319 | K9: 0.47250593 | L9: 0.061057185 | M9: 0.070350183 | N9: 0.093087082 | O9: 0.26227643 | P9: 0.83581185 | Q9: 1.3217032 | R9: 0.24816505 | S9: 0.52342237 | T9: 0.71974504
A10: Banks (Regional) | B10: 881 | C10: 0.0444 | D10: 0.0913 | E10: 0.154 | F10: 0 | G10: 0 | H10: 0.0011762703 | I10: 0.18584906 | J10: 0.36245903 | K10: 0.64026207 | L10: 0.0488122 | M10: 0.050690933 | N10: 0.052263342 | O10: 0.20576877 | P10: 0.44183421 | Q10: 0.75755964 | R10: 0.13924487 | S10: 0.40390391 | T10: 0.64856574
A11: Beverage (Alcoholic) | B11: 220 | C11: 0.0462 | D11: 0.104 | E11: 0.18 | F11: 0.018807906 | G11: 0.084073416 | H11: 0.19276318 | I11: 0.59735066 | J11: 1.0992019 | K11: 2.2064187 | L11: 0.070590254 | M11: 0.077635009 | N11: 0.092296428 | O11: 0.33462101 | P11: 0.7149947 | Q11: 1.0818417 | R11: 0.0015985314 | S11: 0.062278575 | T11: 0.25914834
A12: Beverage (Soft) | B12: 100 | C12: 0.0394 | D12: 0.0991 | E12: 0.161 | F12: -0.15729531 | G12: 0.069186224 | H12: 0.12481614 | I12: 1.2203143 | J12: 1.8078935 | K12: 2.8819053 | L12: 0.068987518 | M12: 0.074663148 | N12: 0.084541278 | O12: 0.22786479 | P12: 0.60046732 | Q12: 0.9609438 | R12: 0.0069323618 | S12: 0.069020998 | T12: 0.31843428
A13: Broadcasting | B13: 130 | C13: -0.00195 | D13: 0.0452 | E13: 0.0912 | F13: -0.025093168 | G13: 0.053386868 | H13: 0.12275574 | I13: 0.62006683 | J13: 0.97970831 | K13: 1.7490028 | L13: 0.073671986 | M13: 0.077105049 | N13: 0.09098039 | O13: 0.505076 | P13: 1.0215667 | Q13: 1.50821 | R13: 0.040979425 | S13: 0.27675556 | T13: 0.58266642
A14: Brokerage & Investment Banking | B14: 590 | C14: -0.038 | D14: 0.0722 | E14: 0.253 | F14: 0 | G14: 0 | H14: 0 | I14: 0.074910108 | J14: 0.22056465 | K14: 0.83927016 | L14: 0.059162075 | M14: 0.067316647 | N14: 0.070016295 | O14: 0.34934817 | P14: 0.91188622 | Q14: 1.4545657 | R14: 0.0072254335 | S14: 0.14216164 | T14: 0.53527194
... A54: Metals & Mining | B54: 1815 | C54: 0.0325 | D54: 0.167 | E54: 0.328 | F54: -9.6111111 | G54: -0.015299198 | H54: 0.070664321 | I54: 0 | J54: 0 | K54: 0.55307035 | L54: 0.084010488 | M54: 0.084074116 | N54: 0.086244568 | O54: 0.55947449 | P54: 1.0440285 | Q54: 1.5375599 | R54: 0 | S54: 0.0038133767 | T54: 0.1134594
A55: Missing | B55: 17 | F55: 0 | G55: 0.021161049 | H55: 0.021161049 | O55: 1.2580306 | P55: 1.2580306 | Q55: 1.2580306 | R55: 0 | S55: 0 | T55: 0
A56: Office Equipment & Services | B56: 137 | C56: 0.0209 | D56: 0.061 | E56: 0.136 | F56: 0.0087773723 | G56: 0.060883995 | H56: 0.097406705 | I56: 0.9243663 | J56: 1.5803579 | K56: 2.4852431 | L56: 0.077228965 | M56: 0.081547382 | N56: 0.095739935 | O56: 0.34835113 | P56: 0.78599736 | Q56: 1.2544459 | R56: 0.023267388 | S56: 0.10576078 | T56: 0.33667799
A57: Oil/Gas (Integrated) | B57: 36 | C57: 0.154 | D57: 0.213 | E57: 0.282 | F57: 0.066673988 | G57: 0.13340238 | H57: 0.21035493 | I57: 1.2192141 | J57: 1.7111561 | K57: 2.1765851 | L57: 0.081627721 | M57: 0.088874147 | N57: 0.11200425 | O57: 0.5309155 | P57: 0.89697496 | Q57: 1.3404511 | R57: 0.14053426 | S57: 0.29928173 | T57: 0.42674253
A58: Oil/Gas (Production and Exploration) | B58: 590 | C58: 0.0847 | D58: 0.246 | E58: 0.438 | F58: -0.31809524 | G58: 0.15921569 | H58: 0.40594059 | I58: 0.06046313 | J58: 0.47227926 | K58: 0.88531179 | L58: 0.082381345 | M58: 0.083043656 | N58: 0.089786139 | O58: 0.539073 | P58: 0.99768095 | Q58: 1.5462508 | R58: 0 | S58: 0.082505598 | T58: 0.34406154
A59: Oil/Gas Distribution | B59: 174 | C59: 0.0158 | D59: 0.112 | E59: 0.224 | F59: 0.020721868 | G59: 0.12210236 | H59: 0.31260485 | I59: 0.34862696 | J59: 0.71256155 | K59: 1.6612263 | L59: 0.066365448 | M59: 0.07353051 | N59: 0.084694755 | O59: 0.37432675 | P59: 0.82986206 | Q59: 1.2607923 | R59: 0.099061836 | S59: 0.33495146 | T59: 0.47313007
A60: Oilfield Svcs/Equip. | B60: 444 | C60: 0.0254 | D60: 0.156 | E60: 0.274 | F60: -0.002202225 | G60: 0.042378954 | H60: 0.10289575 | I60: 0.74167434 | J60: 1.7083897 | K60: 3.4515144 | L60: 0.075258622 | M60: 0.081521893 | N60: 0.094585097 | O60: 0.44918164 | P60: 0.96682864 | Q60: 1.462264 | R60: 0.051790776 | S60: 0.23349736 | T60: 0.50152953
A61: Packaging & Container | B61: 164 | C61: 0.0342 | D61: 0.0775 | E61: 0.141 | F61: 0.030259366 | G61: 0.067430276 | H61: 0.11523179 | I61: 1.0137226 | J61: 1.3960041 | K61: 1.9075 | L61: 0.070846687 | M61: 0.074828788 | N61: 0.087012502 | O61: 0.3803494 | P61: 0.76373515 | Q61: 1.29295 | R61: 0.062734116 | S61: 0.21713941 | T61: 0.45210045
A62: Paper/Forest Products | B62: 266 | C62: 0.0338 | D62: 0.0986 | E62: 0.186 | F62: -0.012552783 | G62: 0.037960954 | H62: 0.10822898 | I62: 0.57858377 | J62: 1.0127213 | K62: 1.6135704 | L62: 0.071738731 | M62: 0.076824794 | N62: 0.09055747 | O62: 0.4104869 | P62: 0.83386906 | Q62: 1.3265602 | R62: 0.094326241 | S62: 0.27329193 | T62: 0.50635461
A63: Power | B63: 488 | C63: 0.0654 | D63: 0.127 | E63: 0.207 | F63: 0.043889796 | G63: 0.10188919 | H63: 0.2062462 | I63: 0.39908432 | J63: 0.69734511 | K63: 1.3009936 | L63: 0.060776392 | M63: 0.064796487 | N63: 0.075773405 | O63: 0.33364962 | P63: 0.64839784 | Q63: 1.0578483 | R63: 0.11640697 | S63: 0.38684211 | T63: 0.58837637
A64: Precious Metals | B64: 853 | C64: 0.00285 | D64: 0.111 | E64: 0.289 | F64: -3.8 | G64: -0.0037873134 | H64: 0.1622807 | I64: 0 | J64: 0 | K64: 0.24519231 | L64: 0.086166589 | M64: 0.086419998 | N64: 0.086419998 | O64: 0.57973451 | P64: 1.0404102 | Q64: 1.5468351 | R64: 0 | S64: 0.0045423794 | T64: 0.087173466
A65: Publishing & Newspapers | B65: 205 | C65: -0.0131 | D65: 0.0447 | E65: 0.109 | F65: -0.032207792 | G65: 0.046142755 | H65: 0.10583016 | I65: 0.70868825 | J65: 1.4398542 | K65: 2.88 | L65: 0.089592268 | M65: 0.093891598 | N65: 0.11172473 | O65: 0.42991479 | P65: 0.91087556 | Q65: 1.429335 | R65: 0.004244205 | S65: 0.059703921 | T65: 0.3124889
A66: R.E.I.T. | B66: 633 | C66: 0.0114 | D66: 0.0698 | E66: 0.174 | F66: 0.1851258 | G66: 0.49888143 | H66: 0.66 | I66: 0.057774358 | J66: 0.080942459 | K66: 0.12396147 | L66: 0.05948161 | M66: 0.06322497 | N66: 0.073606567 | O66: 0.41653383 | P66: 0.7917797 | Q66: 1.1510292 | R66: 0.23554789 | S66: 0.41427397 | T66: 0.59593346
A67: Real Estate (Development) | B67: 884 | C67: -0.109 | D67: 0.0476 | E67: 0.239 | F67: -0.072955975 | G67: 0.088947368 | H67: 0.20433947 | I67: 0.10200553 | J67: 0.24153253 | K67: 0.52198856 | L67: 0.063375311 | M67: 0.069508695 | N67: 0.074228988 | O67: 0.42872483 | P67: 0.92622775 | Q67: 1.4162684 | R67: 0.085162602 | S67: 0.4099532 | T67: 0.72408537
... A97: Utility (Water) | B97: 102 | C97: 0.00155 | D97: 0.0688 | E97: 0.131 | F97: 0.072075783 | G97: 0.20313374 | H97: 0.27598566 | I97: 0.21020327 | J97: 0.34106955 | K97: 0.59236205 | L97: 0.058785843 | M97: 0.062298383 | N97: 0.066846835 | O97: 0.42112367 | P97: 0.6038672 | Q97: 0.91490264 | R97: 0.06670579 | S97: 0.3233526 | T97: 0.6080076

Sheet Trailing 12 month Worskheet
A1: If you are midway through a year, and want to compute updated trailing twelve month numbers, this worksheet may help. You will need your most recent quartely financials (or 10Q) as well as your most recent annual (or 10K).
B6: Last Annual | C6: First X months: Last year | D6: First X months: Current year | E6: Trailing 12 month
A7: Revenues | B7: 15794.34 | C7: 7608.13 | D7: 9444.11 | E7: =B7-C7+D7
A8: Technology & Content | B8: 1221.81 | C8: 581.41 | D8: 756 | E8: =B8-C8+D8
A9: Operating income or EBIT | B9: 1605.23 | C9: 908.79 | D9: 1165.5 | E9: =B9-C9+D9
A10: Interest expenses | B10: 420.49 | C10: 182.82 | D10: 287.56 | E10: =B10-C10+D10
A11: Book value of equity | B11: 5238.77 | D11: 6105.55
A12: Book value of debt | B12: 10360 | D12: 12594.14
A13: Do you have operating lease commitments?
A14: Cash and cross holdings | B14: 3794.48 | D14: 5004.25
A15: Non-operating assets | B15: 0 | D15: 0
A16: Minority interests | B16: 0 | D16: 0
A17: Number of shares outstanding =
A18: Current stock price =
A19: Effective tax rate = | B19: =15885/61372 | C19: =6965/27030 | D19: =3941/23906
A20: Marginal tax rate =
A21: Lease commitments
A22: Year 1 | B22: 172.47 | D22: NA
A23: Year 2 | B23: 139.4 | C23: Copy into operating lease worksheet | D23: NA
A24: Year 3 | B24: 145.18 | D24: NA
A25: Year 4 | B25: 156.53 | D25: NA
A26: Year 5 | B26: 151.2 | D26: NA
A27: Beyond year 5 | B27: 943.63 | D27: NA
A30: Current year's lease expense | B30: 107
D34: 75872
D35: 2404
D36: 24171
D37: 276
A41: G&A | B41: 630.29 | C41: 286.14 | D41: 426.61 | E41: =B41-C41+D41
A42: Marketing Costs | B42: 2369.47 | C42: 1128.78 | D42: 1219.73 | E42: =B42-C42+D42
A43: Content Costs | B43: 9967.54 | C43: 4703.01 | D43: 5876.21 | E43: =B43-C43+D43
A45: Content Costs (Cash Flows) | B45: 13043 | C45: 6020.47 | D45: 6322.85 | E45: =B45-C45+D45

Sheet Answer keys
A1: Yes/No | B1: Book or Market Value | C1: ERP choices | D1: Cost of debt | E1: Synthetic rating | F1: Beta | G1: Rating is | H1: Region | I1: Cost of Capital Approach | J1: Reinvestment lag
A2: Yes | B2: B | C2: Will input | D2: Direct input | E2: 1 | F2: Direct input | G2: Aaa/AAA | H2: First Decile | I2: I will input | J2: 0
A3: No | B3: V | C3: Country of incorporation | D3: Synthetic rating | E3: 2 | F3: Single Business(US) | G3: Aa2/AA | H3: First Quartile | I3: Detailed | J3: 1
C4: Operating countries | D4: Actual rating | F4: Single Business(Global) | G4: A1/A+ | H4: Median | I4: Industry Average | J4: 2
C5: Operating regions | F5: Multibusiness(US) | G5: A2/A | H5: Third Quartile | I5: Distribution | J5: 3
F6: Multibusiness(Global) | G6: A3/A- | H6: Ninth Decile
G7: Baa2/BBB
G8: Ba1/BB+
G9: Ba2/BB
G10: B1/B+
G11: B2/B
G12: B3/B-
G13: C2/C
G14: Ca2/CC
G15: Caa/CCC
G16: D2/D
